Workbook
Name __123Graph_ACURRENT: [1]FitOutConfCentre!#REF!
Name _SEC15030: #REF!
Name _SEC15030: #REF!
Name _SEC15030: #REF!
Name _SEC15030: #REF!
Name _SEC15060: #REF!
Name _SEC15060: #REF!
Name _SEC15060: #REF!
Name _SEC15060: #REF!
Name _SEC15100: #REF!
Name _SEC15100: #REF!
Name _SEC15100: #REF!
Name _SEC15100: #REF!
Name _SEC15110: #REF!
Name _SEC15110: #REF!
Name _SEC15110: #REF!
Name _SEC15110: #REF!
Name _SEC15125: #REF!
Name _SEC15125: #REF!
Name _SEC15125: #REF!
Name _SEC15125: #REF!
Name _SEC15160: #REF!
Name _SEC15160: #REF!
Name _SEC15160: #REF!
Name _SEC15160: #REF!
Name _SEC15175: #REF!
Name _SEC15175: #REF!
Name _SEC15175: #REF!
Name _SEC15175: #REF!
Name _SEC15290: #REF!
Name _SEC15290: #REF!
Name _SEC15290: #REF!
Name _SEC15290: #REF!
Name _SEC15310: #REF!
Name _SEC15310: #REF!
Name _SEC15310: #REF!
Name _SEC15310: #REF!
Name _SEC15420: #REF!
Name _SEC15420: #REF!
Name _SEC15420: #REF!
Name _SEC15420: #REF!
Name _SEC15440: #REF!
Name _SEC15440: #REF!
Name _SEC15440: #REF!
Name _SEC15440: #REF!
Name _SEC15470: #REF!
Name _SEC15470: #REF!
Name _SEC15470: #REF!
Name _SEC15470: #REF!
Name _SEC15486: #REF!
Name _SEC15486: #REF!
Name _SEC15486: #REF!
Name _SEC15486: #REF!
Name _SEC15540: #REF!
Name _SEC15540: #REF!
Name _SEC15540: #REF!
Name _SEC15540: #REF!
Name _SEC15610: #REF!
Name _SEC15610: #REF!
Name _SEC15610: #REF!

Sheet Couverture
H2: Date: | I2: =TODAY() -> 46098
E22: Sales List
E24: Panneaux Photovoltaïques
E29: Usage interne uniquement
A44: I.ON Energy Services
A45: Route De Gilly 30 1180 Rolle | E45: Infoline 0800 800 840 | I45: www.ion-e.ch

Sheet Financial Data
A1: Section | B1: Référence | C1: Valeur
A2: COEFICIENTS SYSTEME SOLAIRE
A3: Matériel | B3: Accessoires | C3: 0.03
A4: Approvisionnement | B4: Expédition | C4: 0
B5: Douanes | C5: 0
B6: Frais Supplémentaires | C6: 0.02
B7: Transport | C7: 0.05
A8: Construction | B8: Main-d'œuvre Panneaux | C8: 65
B9: Main-d'œuvre Electricité | C9: 90
B10: Project Management | C10: =8*C9+480 -> 1200
B11: Frais Administratifs | C11: =10*C9 -> 900
A12: Sales | B12: Frais Généraux Sales | C12: 0.15
A13: Profit | B13: Profit Approvisionnement | C13: 0.25
B14: Profit Construction | C14: 0.25
A16: COEFICIENTS BATTERIES ET BORNES DE RECHARGE
A17: Matériel | B17: Accessoires | C17: 0
A18: Construction | B18: Project Management | C18: 0.07
B19: Frais Administratifs | C19: 0.06
A20: Profit | B20: Profit Approvisionnement | C20: 0.1925
B21: Profit Construction | C21: 0.1925
A23: Marques | B23: Référence | C23: Coût HT
A24: PANNEAUX
A25: Jinko | B25: JINKO JKM455N-54HL4R-V | C25: 52.4
B26: JINKO JKM465N-48QL6-DB | C26: 62.45
A27: Longi | B27: LONGi Hi-MO X10 Explorer LR7-54HVH-485M | C27: 75.35
B28: LONGi Hi-MO X10 Artist LR7-54HVB-485M | C28: 105.55
A29: Aiko | B29: AIKO Neostar G3 3P54 A480-MCE54Mw | C29: 74.3
B30: AIKO Neostar G3 3S54 A485-MCE54Mb | C30: 102.95
A32: ONDULEURS
A33: Huawei (Hybrid) | B33: SUN2000-6K-MAP0 | C33: 900.85
B34: SUN2000-8K-MAP0 | C34: 1068.05
B35: SUN2000-10K-MAP0 | C35: 1199.9
B36: SUN2000-12K-MAP0 | C36: 1296.35
B37: SUN2000-15K-MB0 | C37: 1731.05
B38: SUN2000-17K-MB0 | C38: 1766.4
B39: SUN2000-20K-MB0 | C39: 1865.8
B40: EMMA-A02 | C40: 251
B41: Optimiseur (/panneau) | C41: 27
A42: Fronius (Hybrid) | B42: Symo GEN24 6.0 SC | C42: 1333.85
B43: Symo GEN24 8.0 SC | C43: 1612.7
B44: Symo GEN24 10.0 SC | C44: 1711.95
B45: Symo GEN24 12.0 SC | C45: 1817.7
B46: Symo GEN24 6.0 Plus SC | C46: 1809.75
B47: Symo GEN24 8.0 Plus SC | C47: 2083.85
B48: Symo GEN24 10.0 Plus SC | C48: 2176.9
B49: Symo GEN24 12.0 Plus SC | C49: 2286.4
B50: Verto 15.0 Plus SPD 1+2 | C50: 2714.75
B51: Verto 17.5 Plus SPD 1+2 | C51: 2904.15
B52: Verto 20.0 Plus SPD 1+2 | C52: 3093.55
B53: Parafoudre DC (à rajouter pour 6, 8, 10, 12 KVA) | C53: 147.4
B54: Parafoudre AC (à rajouter pour 6, 8, 10, 12 KVA) | C54: 135
... B56: Optimiseur (pas besoin car système diodes intégré) | C56: 0
A57: Fronius (String) | B57: Verto 15.0 SPD 1+2 | C57: 2117.45
B58: Verto 17.5 SPD 1+2 | C58: 2149.85
B59: Verto 20.0 SPD 1+2 | C59: 2181.6
A61: BATTERIES
A62: Huawei | B62: LUNA2000-7-S1 | C62: 3020.9
B63: LUNA2000-14-S1 | C63: 5249.4
B64: LUNA2000-21-S1 | C64: 7477.9
A65: Fronius | B65: Reserva 6.3 | C65: 2303.85
B66: Reserva 9.5 | C66: 3090.4
B67: Reserva 12.6 | C67: 3876.9
B68: Reserva 15.8 | C68: 4663.45
B69: Reserva Pro 12.0 | C69: 4459.1
B70: Reserva Pro 16.0 | C70: 5666.75
B71: Reserva Pro 20.0 | C71: 6874.4
B72: Reserva Pro 24.0 | C72: 8082.05
B73: Reserva Pro 28.0 | C73: 9289.75
B74: Reserva Pro 32.0 | C74: 10497.4
A76: BORNE DE RECHARGE
A77: Huawei | B77: Smart Charger 22kW/32A | C77: 341.7
A78: Fronius | B78: Wattpilot Flex Home 22 C6 (up to 22kW) | C78: 677.4

Sheet Technical Data
A1: PANNEAUX
A2: Marques | B2: Références | C2: Puissance | D2: Garantie Produit | E2: Garantie Production | F2: Solidité | H2: Rendement | I2: Sales List Code (usage interne)
A3: Jinko | B3: ='Financial Data'!B25 -> JINKO JKM455N-54HL4R-V | C3: 455 W | D3: 15 | E3: 30 | G3: X | H3: 0.227 | I3: Jinko 455W Non Full Black
B4: ='Financial Data'!B26 -> JINKO JKM465N-48QL6-DB | C4: 465 W | D4: 15 | E4: 30 | F4: X | H4: 0.2327 | I4: Jinko 465W Full Black
A5: Longi | B5: ='Financial Data'!B27 -> LONGi Hi-MO X10 Explorer LR7-54HVH-485M | C5: 485 W | D5: 30 | E5: 30 | G5: X | H5: 0.238 | I5: Longi 485W Non Full Black
B6: ='Financial Data'!B28 -> LONGi Hi-MO X10 Artist LR7-54HVB-485M | C6: 485 W | D6: 30 | E6: 30 | G6: X | H6: 0.238 | I6: Longi 485W Full Black
A7: Aiko | B7: ='Financial Data'!B29 -> AIKO Neostar G3 3P54 A480-MCE54Mw | C7: 480 W | D7: 25 | E7: 30 | G7: X | H7: 0.24 | I7: Aiko 480W Non Full Black
B8: ='Financial Data'!B30 -> AIKO Neostar G3 3S54 A485-MCE54Mb | C8: 485 W | D8: 25 | E8: 30 | G8: X | H8: 0.243 | I8: Aiko 485W Full Black
A10: ONDULEURS
A11: Marques | B11: Références | C11: Puissance | D11: Garantie Basique | F11: MPPT | G11: Entrée | L11: Parafoudre intégré | N11: Back up
A12: Huawei (Hybrid) | B12: ='Financial Data'!B33 -> SUN2000-6K-MAP0 | C12: 6 KVA | D12: 10 | F12: 2 | G12: 1 | L12: X | N12: non | O12: non
B13: ='Financial Data'!B34 -> SUN2000-8K-MAP0 | C13: 8 KVA | D13: 10 | F13: 2 | G13: 1 | L13: X | N13: non | O13: non
B14: ='Financial Data'!B35 -> SUN2000-10K-MAP0 | C14: 10 KVA | D14: 10 | F14: 2 | G14: 1 | L14: X | N14: non | O14: non
B15: ='Financial Data'!B36 -> SUN2000-12K-MAP0 | C15: 12 KVA | D15: 10 | F15: 2 | G15: 1 | L15: X | N15: non | O15: non
B16: ='Financial Data'!B37 -> SUN2000-15K-MB0 | C16: 15 KVA | D16: 10 | F16: 2 | G16: 2 | L16: X | N16: non | O16: non
B17: ='Financial Data'!B38 -> SUN2000-17K-MB0 | C17: 17 KVA | D17: 10 | F17: 2 | G17: 2 | L17: X | N17: non | O17: non
B18: ='Financial Data'!B39 -> SUN2000-20K-MB0 | C18: 20 KVA | D18: 10 | F18: 2 | G18: 2 | L18: X | N18: non | O18: non
A19: Fronius (Hybrid) | B19: ='Financial Data'!B42 -> Symo GEN24 6.0 SC | C19: 6 KVA | D19: 10 | F19: 2 | G19: 1 | M19: X | N19: oui | O19: non
B20: ='Financial Data'!B43 -> Symo GEN24 8.0 SC | C20: 8 KVA | D20: 10 | F20: 2 | G20: 1 | M20: X | N20: oui | O20: non
B21: ='Financial Data'!B44 -> Symo GEN24 10.0 SC | C21: 10 KVA | D21: 10 | F21: 2 | G21: 1 | M21: X | N21: oui | O21: non
B22: ='Financial Data'!B45 -> Symo GEN24 12.0 SC | C22: 12 KVA | D22: 10 | F22: 2 | G22: 1 | M22: X | N22: oui | O22: non
B23: ='Financial Data'!B46 -> Symo GEN24 6.0 Plus SC | C23: 6 KVA | D23: 10 | F23: 2 | G23: 1 | M23: X | N23: oui | O23: non
B24: ='Financial Data'!B47 -> Symo GEN24 8.0 Plus SC | C24: 8 KVA | D24: 10 | F24: 2 | G24: 1 | M24: X | N24: oui | O24: non
B25: ='Financial Data'!B48 -> Symo GEN24 10.0 Plus SC | C25: 10 KVA | D25: 10 | F25: 2 | G25: 1 | M25: X | N25: oui | O25: non
B26: ='Financial Data'!B49 -> Symo GEN24 12.0 Plus SC | C26: 12 KVA | D26: 10 | F26: 2 | G26: 1 | M26: X | N26: oui | O26: non
B27: ='Financial Data'!B50 -> Verto 15.0 Plus SPD 1+2 | C27: 15 KVA | D27: 5 | F27: 3 | G27: 2 | L27: X | N27: oui | O27: oui
B28: ='Financial Data'!B51 -> Verto 17.5 Plus SPD 1+2 | C28: 17.5 KVA | D28: 5 | F28: 3 | G28: 2 | L28: X | N28: oui | O28: oui
B29: ='Financial Data'!B52 -> Verto 20.0 Plus SPD 1+2 | C29: 20 KVA | D29: 5 | F29: 3 | G29: 2 | L29: X | N29: oui | O29: oui
A30: Fronius (String) | B30: ='Financial Data'!B57 -> Verto 15.0 SPD 1+2 | C30: 15 Kva | D30: 5 | F30: 3 | G30: 2 | L30: X | N30: oui | O30: oui
B31: ='Financial Data'!B58 -> Verto 17.5 SPD 1+2 | C31: 17.5 kva | D31: 5 | F31: 3 | G31: 2 | L31: X | N31: oui | O31: oui
B32: ='Financial Data'!B59 -> Verto 20.0 SPD 1+2 | C32: 20 Kva | D32: 5 | F32: 3 | G32: 2 | L32: X | N32: oui | O32: oui
A34: BATTERIES
A35: Marques | B35: Références | C35: Puissance | D35: Garantie
A36: Huawei | B36: LUNA2000-7-S1 | C36: 7 kWh | D36: 15
B37: LUNA2000-14-S1 | C37: 14 kWh | D37: 15
B38: LUNA2000-21-S1 | C38: 21 kWh | D38: 15
A39: Fronius | B39: ='Financial Data'!B65 -> Reserva 6.3 | C39: 6.3 kWh | D39: 10
B40: ='Financial Data'!B66 -> Reserva 9.5 | C40: 9.5 kWh | D40: 10
B41: ='Financial Data'!B67 -> Reserva 12.6 | C41: 12.6 kWh | D41: 10
B42: ='Financial Data'!B68 -> Reserva 15.8 | C42: 15.8 kWh | D42: 10
B43: Reserva Pro 12.0 | C43: 12 kWh | D43: 10
B44: Reserva Pro 16.0 | C44: 16 kWh | D44: 10
B45: Reserva Pro 20.0 | C45: 20 kWh | D45: 10
B46: Reserva Pro 24.0 | C46: 24 kWh | D46: 10
B47: Reserva Pro 28.0 | C47: 28 kWh | D47: 10
B48: Reserva Pro 32.0 | C48: 32 kWh | D48: 10
A50: BORNE DE RECHARGE
A51: Marques | B51: Références | C51: Puissance | D51: Garantie
A52: Huawei | B52: Smart Charger 22kW/32A | C52: 22 kW | D52: 3
A53: Fronius | B53: Wattpilot Flex Home 22 C6 (up to 22kW) | C53: 22 kW | D53: 3
B54: Plug pour une charge bidirectionnelle future

Sheet Huawei-Hybrid-10 to 50P
A1: N° | B1: DESCRIPTION | C1: QUANTITE | D1: UNITE DE MESURE | E1: PRIX UNITAIRE | F1: PRIX TOTAL | H1: Calcul Matériel | O1: Approvisionnement | U1: Construction | Y1: Sales | Z1: Profit | AB1: P.U. CHF | AC1: TOTAL Approvisionnement | AI1: TOTAL Construction | AM1: Sales | AN1: TOTAL Profit | AP1: TOTAL Frais | AQ1: COUT TOTAL | AR1: PROFIT TOTAL | AS1: PRIX TOTAL | AU1: Appro. Matériel Net | AW1: Main-d'œuvre Construction | AY1: Project Management | BA1: Frais Administratifs et Sales | BC1: Profit | BF1: Cout Total | BH1: Profit | BK1: Prix TTC | BM1: Pronovo | BN1: Prix Pronovo TTC | BO1: Prix TTC/kWc
E2: CHF (HT) | F2: CHF (HT) | H2: Matériel Avant Rabais | L2: Matériel Après Rabais | O2: Matériel Net | P2: Expédition | Q2: Douanes | R2: Frais Supp. | S2: Transport | T2: P.U. Matériel | U2: Main-d'œuvre | V2: Project Management | W2: Frais Administratifs | X2: P.U. Construction | Y2: Frais Généraux Sales | Z2: Profit Appro | AA2: Profit Construction | AC2: TOTAL Matériel Net | AD2: TOTAL Expédition | AE2: TOTAL Douanes | AF2: TOTAL Frais Supp. | AG2: TOTAL Transport | AH2: TOTAL Approvision-nement | AI2: TOTAL Main-d'œuvre | AJ2: TOTAL Project Management | AK2: TOTAL Frais Administratifs | AL2: TOTAL Construction | AM2: TOTAL Frais Généraux Sales | AN2: TOTAL Profit Appro. | AO2: TOTAL Profit Construction | AP2: TOTAL Frais Administratifs et Ingénierie
B3: Choisir le panneau : | H3: MAT (1) | I3: MAT (2) | J3: ACC | K3: Rabais | L3: MAT (1) | M3: MAT (2) | N3: ACC
B4: Jinko 455W Non Full Black | J4: ='Financial Data'!$C$3 -> 0.03 | P4: ='Financial Data'!C4 -> 0 | Q4: ='Financial Data'!C5 -> 0 | R4: ='Financial Data'!C6 -> 0.02 | S4: ='Financial Data'!C7 -> 0.05 | U4: ='Financial Data'!C8 -> 65 | V4: ='Financial Data'!C10 -> 1200 | W4: ='Financial Data'!C11 -> 900 | Y4: ='Financial Data'!C12 -> 0.15 | Z4: ='Financial Data'!C13 -> 0.25 | AA4: ='Financial Data'!C14 -> 0.25
A5: 10 | B5: Panneaux | C5: Puissance: | D5: =ROUNDUP((A5*465)/1000,2) -> 4.65 | F5: =SUM(F6:F15) -> 15043.172 | U5: ='Financial Data'!C9 -> 90 | AC5: =+SUM(AC6:AC15) -> 5381.5955 | AD5: =+SUM(AD6:AD15) -> 0 | AE5: =+SUM(AE6:AE15) -> 0 | AF5: =+SUM(AF6:AF15) -> 107.63191 | AG5: =+SUM(AG6:AG15) -> 192.12977 | AH5: =+SUM(AH6:AH15) -> 5681.3572 | AI5: =+SUM(AI6:AI15) -> 3120 | AJ5: =+SUM(AJ6:AJ15) -> 1200 | ... AS5: =+SUM(AS6:AS15) -> 15043.172 | AT5: =IF(F5=AS5,"Matching","Not Matching") -> Matching | AU5: =SUM(AC5:AG5) -> 5681.3572 | AV5: =AU5/AS5 -> 0.37767015 | AW5: =AI5 -> 3120 | AX5: =AW5/AS5 -> 0.20740306 | AY5: =AJ5 -> 1200 | AZ5: =AY5/AS5 -> 0.079770408 | BA5: =AK5+AM5 -> 2841.4758 | BB5: =BA5/AS5 -> 0.18888807 | BC5: =AN5+AO5 -> 2200.3393 | BD5: =BC5/AS5 -> 0.1462683 | BE5: =IF((AU5+AW5+AY5+BA5+BC5)=AS5,"Matching","Not Matching") -> Matching | BF5: =AQ5 -> 12842.833 | BG5: =BF5/AS5 -> 0.8537317 | BH5: =AR5 -> 2200.3393 | BI5: =BH5/AS5 -> 0.1462683 | BJ5: =IF((BH5+BF5)=AS5,"Matching","Not Matching") -> Matching | BK5: =AS5*1.081 -> 16261.669 | BL5: =ROUND(BK5,-1) -> 16260 | BM5: =D5*380 -> 1767 | BN5: =BK5-BM5 -> 14494.669 | BO5: =BK5/D5 -> 3497.1332
B7: ="Panneau solaire "&G7 -> Panneau solaire JINKO JKM455N-54HL4R-V | C7: =A5 -> 10 | D7: U | E7: =AB7 -> 180.51476 | F7: =C7*E7 -> 1805.1476 | G7: =IF($B4="Jinko 455W Non Full Black",'Technical Data'!B3,IF($B4="Jinko 465W Full Black",'Technical Data'!B4,IF($B4="Longi 485W Non Full Black",'Technical Data'!B5,IF($B4="Longi 485W Full Black",'Technical Data'!B6,IF($B4="Aiko 480W Non Full Black",'Technical Data'!B7,IF($B4="Aiko 485W Full Black",'Technical Data'!B8,IF(ISBLANK($B4)," "))))))) -> JINKO JKM455N-54HL4R-V | H7: =IF($B4="Jinko 455W Non Full Black",'Financial Data'!$C$25,IF($B4="Jinko 465W Full Black",'Financial Data'!$C$26,IF($B4="Longi 485W Non Full Black",'Financial Data'!$C$27,IF($B4="Longi 485W Full Black",'Financial Data'!$C$28,IF($B4="Aiko 480W Non Full Black",'Financial Data'!$C$29,IF($B4="Aiko 485W Full Black",'Financial Data'!$C$30,IF(ISBLANK($B4),'Technical Data'!#REF!))))))) -> 52.4 | I7: 0 | J7: =H7*$J$4 -> 1.572 | K7: 0 | L7: =H7*(1-$K7) -> 52.4 | M7: =I7*(1-$K7) -> 0 | N7: =J7*(1-$K7) -> 1.572 | O7: =(L7+M7+N7) -> 53.972 | P7: =O7*$P$4 -> 0 | Q7: =(O7+P7)*$Q$4 -> 0 | R7: =(O7+P7)*$R$4 -> 1.07944 | S7: =(O7+P7)*$S$4 -> 2.6986 | T7: =SUM(O7:S7) -> 57.75004 | U7: =1*$U$4 -> 65 | V7: 0 | W7: 0 | X7: =SUM(U7:W7) -> 65 | Y7: =$Y$4/(1-$Y$4)*(T7+X7+Z7+AA7) -> 27.077215 | Z7: =T7*$Z$4 -> 14.43751 | AA7: =X7*$AA$4 -> 16.25 | AB7: =T7+X7+Y7+Z7+AA7 -> 180.51476 | AC7: =O7*$C7 -> 539.72 | AD7: =P7*$C7 -> 0 | AE7: =Q7*$C7 -> 0 | AF7: =R7*$C7 -> 10.7944 | AG7: =S7*$C7 -> 26.986 | AH7: =T7*$C7 -> 577.5004 | AI7: =U7*$C7 -> 650 | AJ7: =V7*$C7 -> 0 | ... AO7: =AA7*$C7 -> 162.5 | AP7: =AM7+AK7 -> 270.77215 | AQ7: =AM7+AL7+AH7 -> 1498.2725 | AR7: =AO7+AN7 -> 306.8751 | AS7: =AH7+AL7+AM7+AO7+AN7 -> 1805.1476
B8: ="Onduleur Huawei "&G8 -> Onduleur Huawei SUN2000-6K-MAP0 | C8: 1 | D8: U | E8: =AB8 -> 2119.7012 | F8: =C8*E8 -> 2119.7012 | G8: ='Technical Data'!B12 -> SUN2000-6K-MAP0 | H8: ='Financial Data'!C33 -> 900.85 | I8: ='Financial Data'!$C$40 -> 251 | J8: =H8*$J$4 -> 27.0255 | K8: 0 | L8: =H8*(1-$K8) -> 900.85 | M8: =I8*(1-$K8) -> 251 | N8: =J8*(1-$K8) -> 27.0255 | O8: =(L8+M8+N8) -> 1178.8755 | P8: =O8*$P$4 -> 0 | Q8: =(O8+P8)*$Q$4 -> 0 | R8: =(O8+P8)*$R$4 -> 23.57751 | S8: =(O8+P8)*$S$4 -> 58.943775 | T8: =SUM(O8:S8) -> 1261.3968 | U8: =2*$U$5 -> 180 | V8: 0 | W8: 0 | X8: =SUM(U8:W8) -> 180 | Y8: =$Y$4/(1-$Y$4)*(T8+X8+Z8+AA8) -> 317.95517 | Z8: =T8*$Z$4 -> 315.3492 | AA8: =X8*$AA$4 -> 45 | AB8: =T8+X8+Y8+Z8+AA8 -> 2119.7012 | AC8: =O8*$C8 -> 1178.8755 | AD8: =P8*$C8 -> 0 | AE8: =Q8*$C8 -> 0 | AF8: =R8*$C8 -> 23.57751 | AG8: =S8*$C8 -> 58.943775 | AH8: =T8*$C8 -> 1261.3968 | AI8: =U8*$C8 -> 180 | AJ8: =V8*$C8 -> 0 | ... AO8: =AA8*$C8 -> 45 | AP8: =AM8+AK8 -> 317.95517 | AQ8: =AM8+AL8+AH8 -> 1759.352 | AR8: =AO8+AN8 -> 360.3492 | AS8: =AH8+AL8+AM8+AO8+AN8 -> 2119.7012
B9: Optimiseurs et accessoires | C9: 1 | D9: Forfait | E9: =AB9 -> 1043.4265 | F9: =C9*E9 -> 1043.4265 | H9: 300 | I9: ='Financial Data'!$C$41*C7 -> 270 | J9: =H9*$J$4 -> 9 | K9: 0 | L9: =H9*(1-$K9) -> 300 | M9: =I9*(1-$K9) -> 270 | N9: =J9*(1-$K9) -> 9 | O9: =(L9+M9+N9) -> 579 | P9: =O9*$P$4 -> 0 | Q9: =(O9+P9)*$Q$4 -> 0 | R9: =(O9+P9)*$R$4 -> 11.58 | S9: =(O9+P9)*$S$4 -> 28.95 | T9: =SUM(O9:S9) -> 619.53 | U9: =(C7/10)*$U$5 -> 90 | V9: 0 | W9: 0 | X9: =SUM(U9:W9) -> 90 | Y9: =$Y$4/(1-$Y$4)*(T9+X9+Z9+AA9) -> 156.51397 | Z9: =T9*$Z$4 -> 154.8825 | AA9: =X9*$AA$4 -> 22.5 | AB9: =T9+X9+Y9+Z9+AA9 -> 1043.4265 | AC9: =O9*$C9 -> 579 | AD9: =P9*$C9 -> 0 | AE9: =Q9*$C9 -> 0 | AF9: =R9*$C9 -> 11.58 | AG9: =S9*$C9 -> 28.95 | AH9: =T9*$C9 -> 619.53 | AI9: =U9*$C9 -> 90 | AJ9: =V9*$C9 -> 0 | ... AO9: =AA9*$C9 -> 22.5 | AP9: =AM9+AK9 -> 156.51397 | AQ9: =AM9+AL9+AH9 -> 866.04397 | AR9: =AO9+AN9 -> 177.3825 | AS9: =AH9+AL9+AM9+AO9+AN9 -> 1043.4265
B10: Système de montage sur tuile | C10: =A5 -> 10 | D10: U | E10: =AB10 -> 257.66176 | F10: =C10*E10 -> 2576.6176 | H10: 100 | I10: 0 | J10: =H10*$J$4 -> 3 | K10: 0 | L10: =H10*(1-$K10) -> 100 | M10: =I10*(1-$K10) -> 0 | N10: =J10*(1-$K10) -> 3 | O10: =(L10+M10+N10) -> 103 | P10: =O10*$P$4 -> 0 | Q10: =(O10+P10)*$Q$4 -> 0 | R10: =(O10+P10)*$R$4 -> 2.06 | S10: =(O10+P10)*$S$4 -> 5.15 | T10: =SUM(O10:S10) -> 110.21 | U10: =1*$U$4 -> 65 | V10: 0 | W10: 0 | X10: =SUM(U10:W10) -> 65 | Y10: =$Y$4/(1-$Y$4)*(T10+X10+Z10+AA10) -> 38.649265 | Z10: =T10*$Z$4 -> 27.5525 | AA10: =X10*$AA$4 -> 16.25 | AB10: =T10+X10+Y10+Z10+AA10 -> 257.66176 | AC10: =O10*$C10 -> 1030 | AD10: =P10*$C10 -> 0 | AE10: =Q10*$C10 -> 0 | AF10: =R10*$C10 -> 20.6 | AG10: =S10*$C10 -> 51.5 | AH10: =T10*$C10 -> 1102.1 | AI10: =U10*$C10 -> 650 | AJ10: =V10*$C10 -> 0 | ... AO10: =AA10*$C10 -> 162.5 | AP10: =AM10+AK10 -> 386.49265 | AQ10: =AM10+AL10+AH10 -> 2138.5926 | AR10: =AO10+AN10 -> 438.025 | AS10: =AH10+AL10+AM10+AO10+AN10 -> 2576.6176
B11: Raccordement AC | C11: 1 | D11: Forfait | E11: =AB11 -> 3089.7794 | F11: =C11*E11 -> 3089.7794 | H11: 500 | I11: 0 | J11: =H11*$J$4 -> 15 | K11: 0 | L11: =H11*(1-$K11) -> 500 | M11: =I11*(1-$K11) -> 0 | N11: =J11*(1-$K11) -> 15 | O11: =(L11+M11+N11) -> 515 | P11: =O11*$P$4 -> 0 | Q11: =(O11+P11)*$Q$4 -> 0 | R11: =(O11+P11)*$R$4 -> 10.3 | S11: =(O11+P11)*$S$4 -> 25.75 | T11: =SUM(O11:S11) -> 551.05 | U11: =5*$U$5+600+500 -> 1550 | V11: 0 | W11: 0 | X11: =SUM(U11:W11) -> 1550 | Y11: =$Y$4/(1-$Y$4)*(T11+X11+Z11+AA11) -> 463.46691 | Z11: =T11*$Z$4 -> 137.7625 | AA11: =X11*$AA$4 -> 387.5 | AB11: =T11+X11+Y11+Z11+AA11 -> 3089.7794 | AC11: =O11*$C11 -> 515 | AD11: =P11*$C11 -> 0 | AE11: =Q11*$C11 -> 0 | AF11: =R11*$C11 -> 10.3 | AG11: =S11*$C11 -> 25.75 | AH11: =T11*$C11 -> 551.05 | AI11: =U11*$C11 -> 1550 | AJ11: =V11*$C11 -> 0 | ... AO11: =AA11*$C11 -> 387.5 | AP11: =AM11+AK11 -> 463.46691 | AQ11: =AM11+AL11+AH11 -> 2564.5169 | AR11: =AO11+AN11 -> 525.2625 | AS11: =AH11+AL11+AM11+AO11+AN11 -> 3089.7794
B12: Echafaudage jusqu'à 6m de hauteur | C12: 1 | D12: Forfait | E12: =AB12 -> 2308.5 | F12: =C12*E12 -> 2308.5 | H12: 1300 | I12: 200 | J12: =H12*$J$4 -> 39 | K12: 0 | L12: =H12*(1-$K12) -> 1300 | M12: =I12*(1-$K12) -> 200 | N12: =J12*(1-$K12) -> 39 | O12: =(L12+M12+N12) -> 1539 | P12: =O12*$P$4 -> 0 | Q12: =(O12+P12)*$Q$4 -> 0 | R12: =(O12+P12)*$R$4 -> 30.78 | S12: 0 | T12: =SUM(O12:S12) -> 1569.78 | U12: 0 | V12: 0 | W12: 0 | X12: =SUM(U12:W12) -> 0 | Y12: =$Y$4/(1-$Y$4)*(T12+X12+Z12+AA12) -> 346.275 | Z12: =T12*$Z$4 -> 392.445 | AA12: =X12*$AA$4 -> 0 | AB12: =T12+X12+Y12+Z12+AA12 -> 2308.5 | AC12: =O12*$C12 -> 1539 | AD12: =P12*$C12 -> 0 | AE12: =Q12*$C12 -> 0 | AF12: =R12*$C12 -> 30.78 | AG12: =S12*$C12 -> 0 | AH12: =T12*$C12 -> 1569.78 | AI12: =U12*$C12 -> 0 | AJ12: =V12*$C12 -> 0 | ... AO12: =AA12*$C12 -> 0 | AP12: =AM12+AK12 -> 346.275 | AQ12: =AM12+AL12+AH12 -> 1916.055 | AR12: =AO12+AN12 -> 392.445 | AS12: =AH12+AL12+AM12+AO12+AN12 -> 2308.5
B13: Travaux administratifs | C13: 1 | D13: Forfait | E13: =AB13 -> 900 | F13: =C13*E13 -> 900 | H13: 0 | I13: 0 | J13: =H13*$J$4 -> 0 | K13: 0 | L13: =H13*(1-$K13) -> 0 | M13: =I13*(1-$K13) -> 0 | N13: =J13*(1-$K13) -> 0 | O13: =(L13+M13+N13) -> 0 | P13: =O13*$P$4 -> 0 | Q13: =(O13+P13)*$Q$4 -> 0 | R13: =(O13+P13)*$R$4 -> 0 | S13: 0 | T13: =SUM(O13:S13) -> 0 | U13: 0 | V13: 0 | W13: =$W$4 -> 900 | X13: =SUM(U13:W13) -> 900 | Y13: 0 | Z13: =T13*$Z$4 -> 0 | AA13: 0 | AB13: =T13+X13+Y13+Z13+AA13 -> 900 | AC13: =O13*$C13 -> 0 | AD13: =P13*$C13 -> 0 | AE13: =Q13*$C13 -> 0 | AF13: =R13*$C13 -> 0 | AG13: =S13*$C13 -> 0 | AH13: =T13*$C13 -> 0 | AI13: =U13*$C13 -> 0 | AJ13: =V13*$C13 -> 0 | ... AO13: =AA13*$C13 -> 0 | AP13: =AM13+AK13 -> 900 | AQ13: =AM13+AL13+AH13 -> 900 | AR13: =AO13+AN13 -> 0 | AS13: =AH13+AL13+AM13+AO13+AN13 -> 900
B14: Travaux électriques, contrôle et Pronovo | C14: 1 | D14: Forfait | E14: =AB14 -> 1200 | F14: =C14*E14 -> 1200 | H14: 0 | I14: 0 | J14: =H14*$J$4 -> 0 | K14: 0 | L14: =H14*(1-$K14) -> 0 | M14: =I14*(1-$K14) -> 0 | N14: =J14*(1-$K14) -> 0 | O14: =(L14+M14+N14) -> 0 | P14: =O14*$P$4 -> 0 | Q14: =(O14+P14)*$Q$4 -> 0 | R14: =(O14+P14)*$R$4 -> 0 | S14: 0 | T14: =SUM(O14:S14) -> 0 | U14: 0 | V14: =$V$4 -> 1200 | W14: 0 | X14: =SUM(U14:W14) -> 1200 | Y14: 0 | Z14: =T14*$Z$4 -> 0 | AA14: 0 | AB14: =T14+X14+Y14+Z14+AA14 -> 1200 | AC14: =O14*$C14 -> 0 | AD14: =P14*$C14 -> 0 | AE14: =Q14*$C14 -> 0 | AF14: =R14*$C14 -> 0 | AG14: =S14*$C14 -> 0 | AH14: =T14*$C14 -> 0 | AI14: =U14*$C14 -> 0 | AJ14: =V14*$C14 -> 1200 | ... AO14: =AA14*$C14 -> 0 | AP14: =AM14+AK14 -> 0 | AQ14: =AM14+AL14+AH14 -> 1200 | AR14: =AO14+AN14 -> 0 | AS14: =AH14+AL14+AM14+AO14+AN14 -> 1200
A16: 11 | B16: Panneaux | C16: Puissance: | D16: =ROUNDUP((A16*465)/1000,2) -> 5.12 | F16: =SUM(F17:F26) -> 15537.069 | AC16: =+SUM(AC17:AC26) -> 5565.5675 | AD16: =+SUM(AD17:AD26) -> 0 | AE16: =+SUM(AE17:AE26) -> 0 | AF16: =+SUM(AF17:AF26) -> 111.31135 | AG16: =+SUM(AG17:AG26) -> 201.32837 | AH16: =+SUM(AH17:AH26) -> 5878.2072 | AI16: =+SUM(AI17:AI26) -> 3259 | AJ16: =+SUM(AJ17:AJ26) -> 1200 | ... AS16: =+SUM(AS17:AS26) -> 15537.069 | AT16: =IF(F16=AS16,"Matching","Not Matching") -> Matching | AU16: =SUM(AC16:AG16) -> 5878.2072 | AV16: =AU16/AS16 -> 0.37833436 | AW16: =AI16 -> 3259 | AX16: =AW16/AS16 -> 0.20975642 | AY16: =AJ16 -> 1200 | AZ16: =AY16/AS16 -> 0.077234642 | BA16: =AK16+AM16 -> 2915.5604 | BB16: =BA16/AS16 -> 0.18765189 | BC16: =AN16+AO16 -> 2284.3018 | BD16: =BC16/AS16 -> 0.14702269 | BE16: =IF((AU16+AW16+AY16+BA16+BC16)=AS16,"Matching","Not Matching") -> Matching | BF16: =AQ16 -> 13252.768 | BG16: =BF16/AS16 -> 0.85297731 | BH16: =AR16 -> 2284.3018 | BI16: =BH16/AS16 -> 0.14702269 | BJ16: =IF((BH16+BF16)=AS16,"Matching","Not Matching") -> Matching | BK16: =AS16*1.081 -> 16795.572 | BL16: =ROUND(BK16,-1) -> 16800 | BM16: =D16*380 -> 1945.6 | BN16: =BK16-BM16 -> 14849.972 | BO16: =BK16/D16 -> 3280.3852
B18: ="Panneau solaire "&G18 -> Panneau solaire JINKO JKM455N-54HL4R-V | C18: =A16 -> 11 | D18: U | E18: =AB18 -> 180.51476 | F18: =C18*E18 -> 1985.6624 | G18: =$G$7 -> JINKO JKM455N-54HL4R-V | H18: =H7 -> 52.4 | I18: =I7 -> 0 | J18: =H18*$J$4 -> 1.572 | K18: 0 | L18: =H18*(1-$K18) -> 52.4 | M18: =I18*(1-$K18) -> 0 | N18: =J18*(1-$K18) -> 1.572 | O18: =(L18+M18+N18) -> 53.972 | P18: =O18*$P$4 -> 0 | Q18: =(O18+P18)*$Q$4 -> 0 | R18: =(O18+P18)*$R$4 -> 1.07944 | S18: =(O18+P18)*$S$4 -> 2.6986 | T18: =SUM(O18:S18) -> 57.75004 | U18: =1*$U$4 -> 65 | V18: =V7 -> 0 | W18: =W7 -> 0 | X18: =SUM(U18:W18) -> 65 | Y18: =$Y$4/(1-$Y$4)*(T18+X18+Z18+AA18) -> 27.077215 | Z18: =T18*$Z$4 -> 14.43751 | AA18: =X18*$AA$4 -> 16.25 | AB18: =T18+X18+Y18+Z18+AA18 -> 180.51476 | AC18: =O18*$C18 -> 593.692 | AD18: =P18*$C18 -> 0 | AE18: =Q18*$C18 -> 0 | AF18: =R18*$C18 -> 11.87384 | AG18: =S18*$C18 -> 29.6846 | AH18: =T18*$C18 -> 635.25044 | AI18: =U18*$C18 -> 715 | AJ18: =V18*$C18 -> 0 | ... AO18: =AA18*$C18 -> 178.75 | AP18: =AM18+AK18 -> 297.84936 | AQ18: =AM18+AL18+AH18 -> 1648.0998 | AR18: =AO18+AN18 -> 337.56261 | AS18: =AH18+AL18+AM18+AO18+AN18 -> 1985.6624
B19: ="Onduleur Huawei "&G19 -> Onduleur Huawei SUN2000-6K-MAP0 | C19: 1 | D19: U | E19: =AB19 -> 2119.7012 | F19: =C19*E19 -> 2119.7012 | G19: =$G$8 -> SUN2000-6K-MAP0 | H19: =H8 -> 900.85 | I19: ='Financial Data'!$C$40 -> 251 | J19: =H19*$J$4 -> 27.0255 | K19: 0 | L19: =H19*(1-$K19) -> 900.85 | M19: =I19*(1-$K19) -> 251 | N19: =J19*(1-$K19) -> 27.0255 | O19: =(L19+M19+N19) -> 1178.8755 | P19: =O19*$P$4 -> 0 | Q19: =(O19+P19)*$Q$4 -> 0 | R19: =(O19+P19)*$R$4 -> 23.57751 | S19: =(O19+P19)*$S$4 -> 58.943775 | T19: =SUM(O19:S19) -> 1261.3968 | U19: =2*$U$5 -> 180 | V19: =V8 -> 0 | W19: =W8 -> 0 | X19: =SUM(U19:W19) -> 180 | Y19: =$Y$4/(1-$Y$4)*(T19+X19+Z19+AA19) -> 317.95517 | Z19: =T19*$Z$4 -> 315.3492 | AA19: =X19*$AA$4 -> 45 | AB19: =T19+X19+Y19+Z19+AA19 -> 2119.7012 | AC19: =O19*$C19 -> 1178.8755 | AD19: =P19*$C19 -> 0 | AE19: =Q19*$C19 -> 0 | AF19: =R19*$C19 -> 23.57751 | AG19: =S19*$C19 -> 58.943775 | AH19: =T19*$C19 -> 1261.3968 | AI19: =U19*$C19 -> 180 | AJ19: =V19*$C19 -> 0 | ... AO19: =AA19*$C19 -> 45 | AP19: =AM19+AK19 -> 317.95517 | AQ19: =AM19+AL19+AH19 -> 1759.352 | AR19: =AO19+AN19 -> 360.3492 | AS19: =AH19+AL19+AM19+AO19+AN19 -> 2119.7012
B20: Optimiseurs et accessoires | C20: 1 | D20: Forfait | E20: =AB20 -> 1099.1471 | F20: =C20*E20 -> 1099.1471 | H20: =H9 -> 300 | I20: ='Financial Data'!$C$41*C18 -> 297 | J20: =H20*$J$4 -> 9 | K20: 0 | L20: =H20*(1-$K20) -> 300 | M20: =I20*(1-$K20) -> 297 | N20: =J20*(1-$K20) -> 9 | O20: =(L20+M20+N20) -> 606 | P20: =O20*$P$4 -> 0 | Q20: =(O20+P20)*$Q$4 -> 0 | R20: =(O20+P20)*$R$4 -> 12.12 | S20: =(O20+P20)*$S$4 -> 30.3 | T20: =SUM(O20:S20) -> 648.42 | U20: =(C18/10)*$U$5 -> 99 | V20: =V9 -> 0 | W20: =W9 -> 0 | X20: =SUM(U20:W20) -> 99 | Y20: =$Y$4/(1-$Y$4)*(T20+X20+Z20+AA20) -> 164.87206 | Z20: =T20*$Z$4 -> 162.105 | AA20: =X20*$AA$4 -> 24.75 | AB20: =T20+X20+Y20+Z20+AA20 -> 1099.1471 | AC20: =O20*$C20 -> 606 | AD20: =P20*$C20 -> 0 | AE20: =Q20*$C20 -> 0 | AF20: =R20*$C20 -> 12.12 | AG20: =S20*$C20 -> 30.3 | AH20: =T20*$C20 -> 648.42 | AI20: =U20*$C20 -> 99 | AJ20: =V20*$C20 -> 0 | ... AO20: =AA20*$C20 -> 24.75 | AP20: =AM20+AK20 -> 164.87206 | AQ20: =AM20+AL20+AH20 -> 912.29206 | AR20: =AO20+AN20 -> 186.855 | AS20: =AH20+AL20+AM20+AO20+AN20 -> 1099.1471
B21: Système de montage sur tuile | C21: =A16 -> 11 | D21: U | E21: =AB21 -> 257.66176 | F21: =C21*E21 -> 2834.2794 | H21: =H10 -> 100 | I21: =I10 -> 0 | J21: =H21*$J$4 -> 3 | K21: 0 | L21: =H21*(1-$K21) -> 100 | M21: =I21*(1-$K21) -> 0 | N21: =J21*(1-$K21) -> 3 | O21: =(L21+M21+N21) -> 103 | P21: =O21*$P$4 -> 0 | Q21: =(O21+P21)*$Q$4 -> 0 | R21: =(O21+P21)*$R$4 -> 2.06 | S21: =(O21+P21)*$S$4 -> 5.15 | T21: =SUM(O21:S21) -> 110.21 | U21: =1*$U$4 -> 65 | V21: =V10 -> 0 | W21: =W10 -> 0 | X21: =SUM(U21:W21) -> 65 | Y21: =$Y$4/(1-$Y$4)*(T21+X21+Z21+AA21) -> 38.649265 | Z21: =T21*$Z$4 -> 27.5525 | AA21: =X21*$AA$4 -> 16.25 | AB21: =T21+X21+Y21+Z21+AA21 -> 257.66176 | AC21: =O21*$C21 -> 1133 | AD21: =P21*$C21 -> 0 | AE21: =Q21*$C21 -> 0 | AF21: =R21*$C21 -> 22.66 | AG21: =S21*$C21 -> 56.65 | AH21: =T21*$C21 -> 1212.31 | AI21: =U21*$C21 -> 715 | AJ21: =V21*$C21 -> 0 | ... AO21: =AA21*$C21 -> 178.75 | AP21: =AM21+AK21 -> 425.14191 | AQ21: =AM21+AL21+AH21 -> 2352.4519 | AR21: =AO21+AN21 -> 481.8275 | AS21: =AH21+AL21+AM21+AO21+AN21 -> 2834.2794
B22: Raccordement AC | C22: 1 | D22: Forfait | E22: =AB22 -> 3089.7794 | F22: =C22*E22 -> 3089.7794 | H22: =H11 -> 500 | I22: =I11 -> 0 | J22: =H22*$J$4 -> 15 | K22: 0 | L22: =H22*(1-$K22) -> 500 | M22: =I22*(1-$K22) -> 0 | N22: =J22*(1-$K22) -> 15 | O22: =(L22+M22+N22) -> 515 | P22: =O22*$P$4 -> 0 | Q22: =(O22+P22)*$Q$4 -> 0 | R22: =(O22+P22)*$R$4 -> 10.3 | S22: =(O22+P22)*$S$4 -> 25.75 | T22: =SUM(O22:S22) -> 551.05 | U22: =5*$U$5+600+500 -> 1550 | V22: =V11 -> 0 | W22: =W11 -> 0 | X22: =SUM(U22:W22) -> 1550 | Y22: =$Y$4/(1-$Y$4)*(T22+X22+Z22+AA22) -> 463.46691 | Z22: =T22*$Z$4 -> 137.7625 | AA22: =X22*$AA$4 -> 387.5 | AB22: =T22+X22+Y22+Z22+AA22 -> 3089.7794 | AC22: =O22*$C22 -> 515 | AD22: =P22*$C22 -> 0 | AE22: =Q22*$C22 -> 0 | AF22: =R22*$C22 -> 10.3 | AG22: =S22*$C22 -> 25.75 | AH22: =T22*$C22 -> 551.05 | AI22: =U22*$C22 -> 1550 | AJ22: =V22*$C22 -> 0 | ... AO22: =AA22*$C22 -> 387.5 | AP22: =AM22+AK22 -> 463.46691 | AQ22: =AM22+AL22+AH22 -> 2564.5169 | AR22: =AO22+AN22 -> 525.2625 | AS22: =AH22+AL22+AM22+AO22+AN22 -> 3089.7794
B23: Echafaudage jusqu'à 6m de hauteur | C23: 1 | D23: Forfait | E23: =AB23 -> 2308.5 | F23: =C23*E23 -> 2308.5 | H23: =H12 -> 1300 | I23: =I12 -> 200 | J23: =H23*$J$4 -> 39 | K23: 0 | L23: =H23*(1-$K23) -> 1300 | M23: =I23*(1-$K23) -> 200 | N23: =J23*(1-$K23) -> 39 | O23: =(L23+M23+N23) -> 1539 | P23: =O23*$P$4 -> 0 | Q23: =(O23+P23)*$Q$4 -> 0 | R23: =(O23+P23)*$R$4 -> 30.78 | S23: 0 | T23: =SUM(O23:S23) -> 1569.78 | U23: 0 | V23: =V12 -> 0 | W23: =W12 -> 0 | X23: =SUM(U23:W23) -> 0 | Y23: =$Y$4/(1-$Y$4)*(T23+X23+Z23+AA23) -> 346.275 | Z23: =T23*$Z$4 -> 392.445 | AA23: =X23*$AA$4 -> 0 | AB23: =T23+X23+Y23+Z23+AA23 -> 2308.5 | AC23: =O23*$C23 -> 1539 | AD23: =P23*$C23 -> 0 | AE23: =Q23*$C23 -> 0 | AF23: =R23*$C23 -> 30.78 | AG23: =S23*$C23 -> 0 | AH23: =T23*$C23 -> 1569.78 | AI23: =U23*$C23 -> 0 | AJ23: =V23*$C23 -> 0 | ... AO23: =AA23*$C23 -> 0 | AP23: =AM23+AK23 -> 346.275 | AQ23: =AM23+AL23+AH23 -> 1916.055 | AR23: =AO23+AN23 -> 392.445 | AS23: =AH23+AL23+AM23+AO23+AN23 -> 2308.5
B24: Travaux administratifs | C24: 1 | D24: Forfait | E24: =AB24 -> 900 | F24: =C24*E24 -> 900 | H24: 0 | I24: 0 | J24: =H24*$J$4 -> 0 | K24: 0 | L24: =H24*(1-$K24) -> 0 | M24: =I24*(1-$K24) -> 0 | N24: =J24*(1-$K24) -> 0 | O24: =(L24+M24+N24) -> 0 | P24: =O24*$P$4 -> 0 | Q24: =(O24+P24)*$Q$4 -> 0 | R24: =(O24+P24)*$R$4 -> 0 | S24: 0 | T24: =SUM(O24:S24) -> 0 | U24: 0 | V24: =V13 -> 0 | W24: =W13 -> 900 | X24: =SUM(U24:W24) -> 900 | Y24: 0 | Z24: =T24*$Z$4 -> 0 | AA24: 0 | AB24: =T24+X24+Y24+Z24+AA24 -> 900 | AC24: =O24*$C24 -> 0 | AD24: =P24*$C24 -> 0 | AE24: =Q24*$C24 -> 0 | AF24: =R24*$C24 -> 0 | AG24: =S24*$C24 -> 0 | AH24: =T24*$C24 -> 0 | AI24: =U24*$C24 -> 0 | AJ24: =V24*$C24 -> 0 | ... AO24: =AA24*$C24 -> 0 | AP24: =AM24+AK24 -> 900 | AQ24: =AM24+AL24+AH24 -> 900 | AR24: =AO24+AN24 -> 0 | AS24: =AH24+AL24+AM24+AO24+AN24 -> 900
B25: Travaux électriques, contrôle et Pronovo | C25: 1 | D25: Forfait | E25: =AB25 -> 1200 | F25: =C25*E25 -> 1200 | H25: 0 | I25: 0 | J25: =H25*$J$4 -> 0 | K25: 0 | L25: =H25*(1-$K25) -> 0 | M25: =I25*(1-$K25) -> 0 | N25: =J25*(1-$K25) -> 0 | O25: =(L25+M25+N25) -> 0 | P25: =O25*$P$4 -> 0 | Q25: =(O25+P25)*$Q$4 -> 0 | R25: =(O25+P25)*$R$4 -> 0 | S25: 0 | T25: =SUM(O25:S25) -> 0 | U25: 0 | V25: =V14 -> 1200 | W25: =W14 -> 0 | X25: =SUM(U25:W25) -> 1200 | Y25: 0 | Z25: =T25*$Z$4 -> 0 | AA25: 0 | AB25: =T25+X25+Y25+Z25+AA25 -> 1200 | AC25: =O25*$C25 -> 0 | AD25: =P25*$C25 -> 0 | AE25: =Q25*$C25 -> 0 | AF25: =R25*$C25 -> 0 | AG25: =S25*$C25 -> 0 | AH25: =T25*$C25 -> 0 | AI25: =U25*$C25 -> 0 | AJ25: =V25*$C25 -> 1200 | ... AO25: =AA25*$C25 -> 0 | AP25: =AM25+AK25 -> 0 | AQ25: =AM25+AL25+AH25 -> 1200 | AR25: =AO25+AN25 -> 0 | AS25: =AH25+AL25+AM25+AO25+AN25 -> 1200
A27: 12 | B27: Panneaux | C27: Puissance: | D27: =ROUNDUP((A27*465)/1000,2) -> 5.58 | F27: =SUM(F28:F37) -> 16030.967 | AC27: =+SUM(AC28:AC37) -> 5749.5395 | AD27: =+SUM(AD28:AD37) -> 0 | AE27: =+SUM(AE28:AE37) -> 0 | AF27: =+SUM(AF28:AF37) -> 114.99079 | AG27: =+SUM(AG28:AG37) -> 210.52698 | AH27: =+SUM(AH28:AH37) -> 6075.0573 | AI27: =+SUM(AI28:AI37) -> 3398 | AJ27: =+SUM(AJ28:AJ37) -> 1200 | ... AS27: =+SUM(AS28:AS37) -> 16030.967 | AT27: =IF(F27=AS27,"Matching","Not Matching") -> Matching | AU27: =SUM(AC27:AG27) -> 6075.0573 | AV27: =AU27/AS27 -> 0.37895764 | AW27: =AI27 -> 3398 | AX27: =AW27/AS27 -> 0.21196476 | AY27: =AJ27 -> 1200 | AZ27: =AY27/AS27 -> 0.074855125 | BA27: =AK27+AM27 -> 2989.645 | BB27: =BA27/AS27 -> 0.18649187 | BC27: =AN27+AO27 -> 2368.2643 | BD27: =BC27/AS27 -> 0.1477306 | BE27: =IF((AU27+AW27+AY27+BA27+BC27)=AS27,"Matching","Not Matching") -> Matching | BF27: =AQ27 -> 13662.702 | BG27: =BF27/AS27 -> 0.8522694 | BH27: =AR27 -> 2368.2643 | BI27: =BH27/AS27 -> 0.1477306 | BJ27: =IF((BH27+BF27)=AS27,"Matching","Not Matching") -> Matching | BK27: =AS27*1.081 -> 17329.475 | BL27: =ROUND(BK27,-1) -> 17330 | BM27: =D27*380 -> 2120.4 | BN27: =BK27-BM27 -> 15209.075 | BO27: =BK27/D27 -> 3105.6407
B29: ="Panneau solaire "&G29 -> Panneau solaire JINKO JKM455N-54HL4R-V | C29: =A27 -> 12 | D29: U | E29: =AB29 -> 180.51476 | F29: =C29*E29 -> 2166.1772 | G29: =$G$7 -> JINKO JKM455N-54HL4R-V | H29: =H7 -> 52.4 | I29: =I7 -> 0 | J29: =H29*$J$4 -> 1.572 | K29: 0 | L29: =H29*(1-$K29) -> 52.4 | M29: =I29*(1-$K29) -> 0 | N29: =J29*(1-$K29) -> 1.572 | O29: =(L29+M29+N29) -> 53.972 | P29: =O29*$P$4 -> 0 | Q29: =(O29+P29)*$Q$4 -> 0 | R29: =(O29+P29)*$R$4 -> 1.07944 | S29: =(O29+P29)*$S$4 -> 2.6986 | T29: =SUM(O29:S29) -> 57.75004 | U29: =1*$U$4 -> 65 | V29: =V18 -> 0 | W29: =W18 -> 0 | X29: =SUM(U29:W29) -> 65 | Y29: =$Y$4/(1-$Y$4)*(T29+X29+Z29+AA29) -> 27.077215 | Z29: =T29*$Z$4 -> 14.43751 | AA29: =X29*$AA$4 -> 16.25 | AB29: =T29+X29+Y29+Z29+AA29 -> 180.51476 | AC29: =O29*$C29 -> 647.664 | AD29: =P29*$C29 -> 0 | AE29: =Q29*$C29 -> 0 | AF29: =R29*$C29 -> 12.95328 | AG29: =S29*$C29 -> 32.3832 | AH29: =T29*$C29 -> 693.00048 | AI29: =U29*$C29 -> 780 | AJ29: =V29*$C29 -> 0 | ... AO29: =AA29*$C29 -> 195 | AP29: =AM29+AK29 -> 324.92658 | AQ29: =AM29+AL29+AH29 -> 1797.9271 | AR29: =AO29+AN29 -> 368.25012 | AS29: =AH29+AL29+AM29+AO29+AN29 -> 2166.1772
B30: ="Onduleur Huawei "&G30 -> Onduleur Huawei SUN2000-6K-MAP0 | C30: 1 | D30: U | E30: =AB30 -> 2119.7012 | F30: =C30*E30 -> 2119.7012 | G30: =$G$8 -> SUN2000-6K-MAP0 | H30: =H8 -> 900.85 | I30: ='Financial Data'!$C$40 -> 251 | J30: =H30*$J$4 -> 27.0255 | K30: 0 | L30: =H30*(1-$K30) -> 900.85 | M30: =I30*(1-$K30) -> 251 | N30: =J30*(1-$K30) -> 27.0255 | O30: =(L30+M30+N30) -> 1178.8755 | P30: =O30*$P$4 -> 0 | Q30: =(O30+P30)*$Q$4 -> 0 | R30: =(O30+P30)*$R$4 -> 23.57751 | S30: =(O30+P30)*$S$4 -> 58.943775 | T30: =SUM(O30:S30) -> 1261.3968 | U30: =2*$U$5 -> 180 | V30: =V19 -> 0 | W30: =W19 -> 0 | X30: =SUM(U30:W30) -> 180 | Y30: =$Y$4/(1-$Y$4)*(T30+X30+Z30+AA30) -> 317.95517 | Z30: =T30*$Z$4 -> 315.3492 | AA30: =X30*$AA$4 -> 45 | AB30: =T30+X30+Y30+Z30+AA30 -> 2119.7012 | AC30: =O30*$C30 -> 1178.8755 | AD30: =P30*$C30 -> 0 | AE30: =Q30*$C30 -> 0 | AF30: =R30*$C30 -> 23.57751 | AG30: =S30*$C30 -> 58.943775 | AH30: =T30*$C30 -> 1261.3968 | AI30: =U30*$C30 -> 180 | AJ30: =V30*$C30 -> 0 | ... AO30: =AA30*$C30 -> 45 | AP30: =AM30+AK30 -> 317.95517 | AQ30: =AM30+AL30+AH30 -> 1759.352 | AR30: =AO30+AN30 -> 360.3492 | AS30: =AH30+AL30+AM30+AO30+AN30 -> 2119.7012
B31: Optimiseurs et accessoires | C31: 1 | D31: Forfait | E31: =AB31 -> 1154.8676 | F31: =C31*E31 -> 1154.8676 | H31: =H9 -> 300 | I31: ='Financial Data'!$C$41*C29 -> 324 | J31: =H31*$J$4 -> 9 | K31: 0 | L31: =H31*(1-$K31) -> 300 | M31: =I31*(1-$K31) -> 324 | N31: =J31*(1-$K31) -> 9 | O31: =(L31+M31+N31) -> 633 | P31: =O31*$P$4 -> 0 | Q31: =(O31+P31)*$Q$4 -> 0 | R31: =(O31+P31)*$R$4 -> 12.66 | S31: =(O31+P31)*$S$4 -> 31.65 | T31: =SUM(O31:S31) -> 677.31 | U31: =(C29/10)*$U$5 -> 108 | V31: =V20 -> 0 | W31: =W20 -> 0 | X31: =SUM(U31:W31) -> 108 | Y31: =$Y$4/(1-$Y$4)*(T31+X31+Z31+AA31) -> 173.23015 | Z31: =T31*$Z$4 -> 169.3275 | AA31: =X31*$AA$4 -> 27 | AB31: =T31+X31+Y31+Z31+AA31 -> 1154.8676 | AC31: =O31*$C31 -> 633 | AD31: =P31*$C31 -> 0 | AE31: =Q31*$C31 -> 0 | AF31: =R31*$C31 -> 12.66 | AG31: =S31*$C31 -> 31.65 | AH31: =T31*$C31 -> 677.31 | AI31: =U31*$C31 -> 108 | AJ31: =V31*$C31 -> 0 | ... AO31: =AA31*$C31 -> 27 | AP31: =AM31+AK31 -> 173.23015 | AQ31: =AM31+AL31+AH31 -> 958.54015 | AR31: =AO31+AN31 -> 196.3275 | AS31: =AH31+AL31+AM31+AO31+AN31 -> 1154.8676
B32: Système de montage sur tuile | C32: =A27 -> 12 | D32: U | E32: =AB32 -> 257.66176 | F32: =C32*E32 -> 3091.9412 | H32: =H10 -> 100 | I32: =I10 -> 0 | J32: =H32*$J$4 -> 3 | K32: 0 | L32: =H32*(1-$K32) -> 100 | M32: =I32*(1-$K32) -> 0 | N32: =J32*(1-$K32) -> 3 | O32: =(L32+M32+N32) -> 103 | P32: =O32*$P$4 -> 0 | Q32: =(O32+P32)*$Q$4 -> 0 | R32: =(O32+P32)*$R$4 -> 2.06 | S32: =(O32+P32)*$S$4 -> 5.15 | T32: =SUM(O32:S32) -> 110.21 | U32: =1*$U$4 -> 65 | V32: =V21 -> 0 | W32: =W21 -> 0 | X32: =SUM(U32:W32) -> 65 | Y32: =$Y$4/(1-$Y$4)*(T32+X32+Z32+AA32) -> 38.649265 | Z32: =T32*$Z$4 -> 27.5525 | AA32: =X32*$AA$4 -> 16.25 | AB32: =T32+X32+Y32+Z32+AA32 -> 257.66176 | AC32: =O32*$C32 -> 1236 | AD32: =P32*$C32 -> 0 | AE32: =Q32*$C32 -> 0 | AF32: =R32*$C32 -> 24.72 | AG32: =S32*$C32 -> 61.8 | AH32: =T32*$C32 -> 1322.52 | AI32: =U32*$C32 -> 780 | AJ32: =V32*$C32 -> 0 | ... AO32: =AA32*$C32 -> 195 | AP32: =AM32+AK32 -> 463.79118 | AQ32: =AM32+AL32+AH32 -> 2566.3112 | AR32: =AO32+AN32 -> 525.63 | AS32: =AH32+AL32+AM32+AO32+AN32 -> 3091.9412
B33: Raccordement AC | C33: 1 | D33: Forfait | E33: =AB33 -> 3089.7794 | F33: =C33*E33 -> 3089.7794 | H33: =H11 -> 500 | I33: =I11 -> 0 | J33: =H33*$J$4 -> 15 | K33: 0 | L33: =H33*(1-$K33) -> 500 | M33: =I33*(1-$K33) -> 0 | N33: =J33*(1-$K33) -> 15 | O33: =(L33+M33+N33) -> 515 | P33: =O33*$P$4 -> 0 | Q33: =(O33+P33)*$Q$4 -> 0 | R33: =(O33+P33)*$R$4 -> 10.3 | S33: =(O33+P33)*$S$4 -> 25.75 | T33: =SUM(O33:S33) -> 551.05 | U33: =5*$U$5+600+500 -> 1550 | V33: =V22 -> 0 | W33: =W22 -> 0 | X33: =SUM(U33:W33) -> 1550 | Y33: =$Y$4/(1-$Y$4)*(T33+X33+Z33+AA33) -> 463.46691 | Z33: =T33*$Z$4 -> 137.7625 | AA33: =X33*$AA$4 -> 387.5 | AB33: =T33+X33+Y33+Z33+AA33 -> 3089.7794 | AC33: =O33*$C33 -> 515 | AD33: =P33*$C33 -> 0 | AE33: =Q33*$C33 -> 0 | AF33: =R33*$C33 -> 10.3 | AG33: =S33*$C33 -> 25.75 | AH33: =T33*$C33 -> 551.05 | AI33: =U33*$C33 -> 1550 | AJ33: =V33*$C33 -> 0 | ... AO33: =AA33*$C33 -> 387.5 | AP33: =AM33+AK33 -> 463.46691 | AQ33: =AM33+AL33+AH33 -> 2564.5169 | AR33: =AO33+AN33 -> 525.2625 | AS33: =AH33+AL33+AM33+AO33+AN33 -> 3089.7794
B34: Echafaudage jusqu'à 6m de hauteur | C34: 1 | D34: Forfait | E34: =AB34 -> 2308.5 | F34: =C34*E34 -> 2308.5 | H34: =H12 -> 1300 | I34: =I12 -> 200 | J34: =H34*$J$4 -> 39 | K34: 0 | L34: =H34*(1-$K34) -> 1300 | M34: =I34*(1-$K34) -> 200 | N34: =J34*(1-$K34) -> 39 | O34: =(L34+M34+N34) -> 1539 | P34: =O34*$P$4 -> 0 | Q34: =(O34+P34)*$Q$4 -> 0 | R34: =(O34+P34)*$R$4 -> 30.78 | S34: 0 | T34: =SUM(O34:S34) -> 1569.78 | U34: 0 | V34: =V23 -> 0 | W34: =W23 -> 0 | X34: =SUM(U34:W34) -> 0 | Y34: =$Y$4/(1-$Y$4)*(T34+X34+Z34+AA34) -> 346.275 | Z34: =T34*$Z$4 -> 392.445 | AA34: =X34*$AA$4 -> 0 | AB34: =T34+X34+Y34+Z34+AA34 -> 2308.5 | AC34: =O34*$C34 -> 1539 | AD34: =P34*$C34 -> 0 | AE34: =Q34*$C34 -> 0 | AF34: =R34*$C34 -> 30.78 | AG34: =S34*$C34 -> 0 | AH34: =T34*$C34 -> 1569.78 | AI34: =U34*$C34 -> 0 | AJ34: =V34*$C34 -> 0 | ... AO34: =AA34*$C34 -> 0 | AP34: =AM34+AK34 -> 346.275 | AQ34: =AM34+AL34+AH34 -> 1916.055 | AR34: =AO34+AN34 -> 392.445 | AS34: =AH34+AL34+AM34+AO34+AN34 -> 2308.5
B35: Travaux administratifs | C35: 1 | D35: Forfait | E35: =AB35 -> 900 | F35: =C35*E35 -> 900 | H35: 0 | I35: 0 | J35: =H35*$J$4 -> 0 | K35: 0 | L35: =H35*(1-$K35) -> 0 | M35: =I35*(1-$K35) -> 0 | N35: =J35*(1-$K35) -> 0 | O35: =(L35+M35+N35) -> 0 | P35: =O35*$P$4 -> 0 | Q35: =(O35+P35)*$Q$4 -> 0 | R35: =(O35+P35)*$R$4 -> 0 | S35: 0 | T35: =SUM(O35:S35) -> 0 | U35: 0 | V35: =V24 -> 0 | W35: =W24 -> 900 | X35: =SUM(U35:W35) -> 900 | Y35: 0 | Z35: =T35*$Z$4 -> 0 | AA35: 0 | AB35: =T35+X35+Y35+Z35+AA35 -> 900 | AC35: =O35*$C35 -> 0 | AD35: =P35*$C35 -> 0 | AE35: =Q35*$C35 -> 0 | AF35: =R35*$C35 -> 0 | AG35: =S35*$C35 -> 0 | AH35: =T35*$C35 -> 0 | AI35: =U35*$C35 -> 0 | AJ35: =V35*$C35 -> 0 | ... AO35: =AA35*$C35 -> 0 | AP35: =AM35+AK35 -> 900 | AQ35: =AM35+AL35+AH35 -> 900 | AR35: =AO35+AN35 -> 0 | AS35: =AH35+AL35+AM35+AO35+AN35 -> 900
B36: Travaux électriques, contrôle et Pronovo | C36: 1 | D36: Forfait | E36: =AB36 -> 1200 | F36: =C36*E36 -> 1200 | H36: 0 | I36: 0 | J36: =H36*$J$4 -> 0 | K36: 0 | L36: =H36*(1-$K36) -> 0 | M36: =I36*(1-$K36) -> 0 | N36: =J36*(1-$K36) -> 0 | O36: =(L36+M36+N36) -> 0 | P36: =O36*$P$4 -> 0 | Q36: =(O36+P36)*$Q$4 -> 0 | R36: =(O36+P36)*$R$4 -> 0 | S36: 0 | T36: =SUM(O36:S36) -> 0 | U36: 0 | V36: =V25 -> 1200 | W36: =W25 -> 0 | X36: =SUM(U36:W36) -> 1200 | Y36: 0 | Z36: =T36*$Z$4 -> 0 | AA36: 0 | AB36: =T36+X36+Y36+Z36+AA36 -> 1200 | AC36: =O36*$C36 -> 0 | AD36: =P36*$C36 -> 0 | AE36: =Q36*$C36 -> 0 | AF36: =R36*$C36 -> 0 | AG36: =S36*$C36 -> 0 | AH36: =T36*$C36 -> 0 | AI36: =U36*$C36 -> 0 | AJ36: =V36*$C36 -> 1200 | ... AO36: =AA36*$C36 -> 0 | AP36: =AM36+AK36 -> 0 | AQ36: =AM36+AL36+AH36 -> 1200 | AR36: =AO36+AN36 -> 0 | AS36: =AH36+AL36+AM36+AO36+AN36 -> 1200
A38: 13 | B38: Panneaux | C38: Puissance: | D38: =ROUNDUP((A38*465)/1000,2) -> 6.05 | F38: =SUM(F39:F48) -> 16524.864 | AC38: =+SUM(AC39:AC48) -> 5933.5115 | AD38: =+SUM(AD39:AD48) -> 0 | AE38: =+SUM(AE39:AE48) -> 0 | AF38: =+SUM(AF39:AF48) -> 118.67023 | AG38: =+SUM(AG39:AG48) -> 219.72557 | AH38: =+SUM(AH39:AH48) -> 6271.9073 | AI38: =+SUM(AI39:AI48) -> 3537 | AJ38: =+SUM(AJ39:AJ48) -> 1200 | ... AS38: =+SUM(AS39:AS48) -> 16524.864 | AT38: =IF(F38=AS38,"Matching","Not Matching") -> Matching | AU38: =SUM(AC38:AG38) -> 6271.9073 | AV38: =AU38/AS38 -> 0.37954366 | AW38: =AI38 -> 3537 | AX38: =AW38/AS38 -> 0.2140411 | AY38: =AJ38 -> 1200 | AZ38: =AY38/AS38 -> 0.072617846 | BA38: =AK38+AM38 -> 3063.7296 | BB38: =BA38/AS38 -> 0.1854012 | BC38: =AN38+AO38 -> 2452.2268 | BD38: =BC38/AS38 -> 0.14839619 | BE38: =IF((AU38+AW38+AY38+BA38+BC38)=AS38,"Matching","Not Matching") -> Matching | BF38: =AQ38 -> 14072.637 | BG38: =BF38/AS38 -> 0.85160381 | BH38: =AR38 -> 2452.2268 | BI38: =BH38/AS38 -> 0.14839619 | BJ38: =IF((BH38+BF38)=AS38,"Matching","Not Matching") -> Matching | BK38: =AS38*1.081 -> 17863.378 | BL38: =ROUND(BK38,-1) -> 17860 | BM38: =D38*380 -> 2299 | BN38: =BK38-BM38 -> 15564.378 | BO38: =BK38/D38 -> 2952.6244
B40: ="Panneau solaire "&G40 -> Panneau solaire JINKO JKM455N-54HL4R-V | C40: =A38 -> 13 | D40: U | E40: =AB40 -> 180.51476 | F40: =C40*E40 -> 2346.6919 | G40: =$G$7 -> JINKO JKM455N-54HL4R-V | H40: =H7 -> 52.4 | I40: =I7 -> 0 | J40: =H40*$J$4 -> 1.572 | K40: 0 | L40: =H40*(1-$K40) -> 52.4 | M40: =I40*(1-$K40) -> 0 | N40: =J40*(1-$K40) -> 1.572 | O40: =(L40+M40+N40) -> 53.972 | P40: =O40*$P$4 -> 0 | Q40: =(O40+P40)*$Q$4 -> 0 | R40: =(O40+P40)*$R$4 -> 1.07944 | S40: =(O40+P40)*$S$4 -> 2.6986 | T40: =SUM(O40:S40) -> 57.75004 | U40: =1*$U$4 -> 65 | V40: =V29 -> 0 | W40: =W29 -> 0 | X40: =SUM(U40:W40) -> 65 | Y40: =$Y$4/(1-$Y$4)*(T40+X40+Z40+AA40) -> 27.077215 | Z40: =T40*$Z$4 -> 14.43751 | AA40: =X40*$AA$4 -> 16.25 | AB40: =T40+X40+Y40+Z40+AA40 -> 180.51476 | AC40: =O40*$C40 -> 701.636 | AD40: =P40*$C40 -> 0 | AE40: =Q40*$C40 -> 0 | AF40: =R40*$C40 -> 14.03272 | AG40: =S40*$C40 -> 35.0818 | AH40: =T40*$C40 -> 750.75052 | AI40: =U40*$C40 -> 845 | AJ40: =V40*$C40 -> 0 | ... AO40: =AA40*$C40 -> 211.25 | AP40: =AM40+AK40 -> 352.00379 | AQ40: =AM40+AL40+AH40 -> 1947.7543 | AR40: =AO40+AN40 -> 398.93763 | AS40: =AH40+AL40+AM40+AO40+AN40 -> 2346.6919
B41: ="Onduleur Huawei "&G41 -> Onduleur Huawei SUN2000-6K-MAP0 | C41: 1 | D41: U | E41: =AB41 -> 2119.7012 | F41: =C41*E41 -> 2119.7012 | G41: =$G$8 -> SUN2000-6K-MAP0 | H41: =H8 -> 900.85 | I41: ='Financial Data'!$C$40 -> 251 | J41: =H41*$J$4 -> 27.0255 | K41: 0 | L41: =H41*(1-$K41) -> 900.85 | M41: =I41*(1-$K41) -> 251 | N41: =J41*(1-$K41) -> 27.0255 | O41: =(L41+M41+N41) -> 1178.8755 | P41: =O41*$P$4 -> 0 | Q41: =(O41+P41)*$Q$4 -> 0 | R41: =(O41+P41)*$R$4 -> 23.57751 | S41: =(O41+P41)*$S$4 -> 58.943775 | T41: =SUM(O41:S41) -> 1261.3968 | U41: =2*$U$5 -> 180 | V41: =V30 -> 0 | W41: =W30 -> 0 | X41: =SUM(U41:W41) -> 180 | Y41: =$Y$4/(1-$Y$4)*(T41+X41+Z41+AA41) -> 317.95517 | Z41: =T41*$Z$4 -> 315.3492 | AA41: =X41*$AA$4 -> 45 | AB41: =T41+X41+Y41+Z41+AA41 -> 2119.7012 | AC41: =O41*$C41 -> 1178.8755 | AD41: =P41*$C41 -> 0 | AE41: =Q41*$C41 -> 0 | AF41: =R41*$C41 -> 23.57751 | AG41: =S41*$C41 -> 58.943775 | AH41: =T41*$C41 -> 1261.3968 | AI41: =U41*$C41 -> 180 | AJ41: =V41*$C41 -> 0 | ... AO41: =AA41*$C41 -> 45 | AP41: =AM41+AK41 -> 317.95517 | AQ41: =AM41+AL41+AH41 -> 1759.352 | AR41: =AO41+AN41 -> 360.3492 | AS41: =AH41+AL41+AM41+AO41+AN41 -> 2119.7012
B42: Optimiseurs et accessoires | C42: 1 | D42: Forfait | E42: =AB42 -> 1210.5882 | F42: =C42*E42 -> 1210.5882 | H42: =H9 -> 300 | I42: ='Financial Data'!$C$41*C40 -> 351 | J42: =H42*$J$4 -> 9 | K42: 0 | L42: =H42*(1-$K42) -> 300 | M42: =I42*(1-$K42) -> 351 | N42: =J42*(1-$K42) -> 9 | O42: =(L42+M42+N42) -> 660 | P42: =O42*$P$4 -> 0 | Q42: =(O42+P42)*$Q$4 -> 0 | R42: =(O42+P42)*$R$4 -> 13.2 | S42: =(O42+P42)*$S$4 -> 33 | T42: =SUM(O42:S42) -> 706.2 | U42: =(C40/10)*$U$5 -> 117 | V42: =V31 -> 0 | W42: =W31 -> 0 | X42: =SUM(U42:W42) -> 117 | Y42: =$Y$4/(1-$Y$4)*(T42+X42+Z42+AA42) -> 181.58824 | Z42: =T42*$Z$4 -> 176.55 | AA42: =X42*$AA$4 -> 29.25 | AB42: =T42+X42+Y42+Z42+AA42 -> 1210.5882 | AC42: =O42*$C42 -> 660 | AD42: =P42*$C42 -> 0 | AE42: =Q42*$C42 -> 0 | AF42: =R42*$C42 -> 13.2 | AG42: =S42*$C42 -> 33 | AH42: =T42*$C42 -> 706.2 | AI42: =U42*$C42 -> 117 | AJ42: =V42*$C42 -> 0 | ... AO42: =AA42*$C42 -> 29.25 | AP42: =AM42+AK42 -> 181.58824 | AQ42: =AM42+AL42+AH42 -> 1004.7882 | AR42: =AO42+AN42 -> 205.8 | AS42: =AH42+AL42+AM42+AO42+AN42 -> 1210.5882
B43: Système de montage sur tuile | C43: =A38 -> 13 | D43: U | E43: =AB43 -> 257.66176 | F43: =C43*E43 -> 3349.6029 | H43: =H10 -> 100 | I43: =I10 -> 0 | J43: =H43*$J$4 -> 3 | K43: 0 | L43: =H43*(1-$K43) -> 100 | M43: =I43*(1-$K43) -> 0 | N43: =J43*(1-$K43) -> 3 | O43: =(L43+M43+N43) -> 103 | P43: =O43*$P$4 -> 0 | Q43: =(O43+P43)*$Q$4 -> 0 | R43: =(O43+P43)*$R$4 -> 2.06 | S43: =(O43+P43)*$S$4 -> 5.15 | T43: =SUM(O43:S43) -> 110.21 | U43: =1*$U$4 -> 65 | V43: =V32 -> 0 | W43: =W32 -> 0 | X43: =SUM(U43:W43) -> 65 | Y43: =$Y$4/(1-$Y$4)*(T43+X43+Z43+AA43) -> 38.649265 | Z43: =T43*$Z$4 -> 27.5525 | AA43: =X43*$AA$4 -> 16.25 | AB43: =T43+X43+Y43+Z43+AA43 -> 257.66176 | AC43: =O43*$C43 -> 1339 | AD43: =P43*$C43 -> 0 | AE43: =Q43*$C43 -> 0 | AF43: =R43*$C43 -> 26.78 | AG43: =S43*$C43 -> 66.95 | AH43: =T43*$C43 -> 1432.73 | AI43: =U43*$C43 -> 845 | AJ43: =V43*$C43 -> 0 | ... AO43: =AA43*$C43 -> 211.25 | AP43: =AM43+AK43 -> 502.44044 | AQ43: =AM43+AL43+AH43 -> 2780.1704 | AR43: =AO43+AN43 -> 569.4325 | AS43: =AH43+AL43+AM43+AO43+AN43 -> 3349.6029
B44: Raccordement AC | C44: 1 | D44: Forfait | E44: =AB44 -> 3089.7794 | F44: =C44*E44 -> 3089.7794 | H44: =H11 -> 500 | I44: =I11 -> 0 | J44: =H44*$J$4 -> 15 | K44: 0 | L44: =H44*(1-$K44) -> 500 | M44: =I44*(1-$K44) -> 0 | N44: =J44*(1-$K44) -> 15 | O44: =(L44+M44+N44) -> 515 | P44: =O44*$P$4 -> 0 | Q44: =(O44+P44)*$Q$4 -> 0 | R44: =(O44+P44)*$R$4 -> 10.3 | S44: =(O44+P44)*$S$4 -> 25.75 | T44: =SUM(O44:S44) -> 551.05 | U44: =5*$U$5+600+500 -> 1550 | V44: =V33 -> 0 | W44: =W33 -> 0 | X44: =SUM(U44:W44) -> 1550 | Y44: =$Y$4/(1-$Y$4)*(T44+X44+Z44+AA44) -> 463.46691 | Z44: =T44*$Z$4 -> 137.7625 | AA44: =X44*$AA$4 -> 387.5 | AB44: =T44+X44+Y44+Z44+AA44 -> 3089.7794 | AC44: =O44*$C44 -> 515 | AD44: =P44*$C44 -> 0 | AE44: =Q44*$C44 -> 0 | AF44: =R44*$C44 -> 10.3 | AG44: =S44*$C44 -> 25.75 | AH44: =T44*$C44 -> 551.05 | AI44: =U44*$C44 -> 1550 | AJ44: =V44*$C44 -> 0 | ... AO44: =AA44*$C44 -> 387.5 | AP44: =AM44+AK44 -> 463.46691 | AQ44: =AM44+AL44+AH44 -> 2564.5169 | AR44: =AO44+AN44 -> 525.2625 | AS44: =AH44+AL44+AM44+AO44+AN44 -> 3089.7794
B45: Echafaudage jusqu'à 6m de hauteur | C45: 1 | D45: Forfait | E45: =AB45 -> 2308.5 | F45: =C45*E45 -> 2308.5 | H45: =H12 -> 1300 | I45: =I12 -> 200 | J45: =H45*$J$4 -> 39 | K45: 0 | L45: =H45*(1-$K45) -> 1300 | M45: =I45*(1-$K45) -> 200 | N45: =J45*(1-$K45) -> 39 | O45: =(L45+M45+N45) -> 1539 | P45: =O45*$P$4 -> 0 | Q45: =(O45+P45)*$Q$4 -> 0 | R45: =(O45+P45)*$R$4 -> 30.78 | S45: 0 | T45: =SUM(O45:S45) -> 1569.78 | U45: 0 | V45: =V34 -> 0 | W45: =W34 -> 0 | X45: =SUM(U45:W45) -> 0 | Y45: =$Y$4/(1-$Y$4)*(T45+X45+Z45+AA45) -> 346.275 | Z45: =T45*$Z$4 -> 392.445 | AA45: =X45*$AA$4 -> 0 | AB45: =T45+X45+Y45+Z45+AA45 -> 2308.5 | AC45: =O45*$C45 -> 1539 | AD45: =P45*$C45 -> 0 | AE45: =Q45*$C45 -> 0 | AF45: =R45*$C45 -> 30.78 | AG45: =S45*$C45 -> 0 | AH45: =T45*$C45 -> 1569.78 | AI45: =U45*$C45 -> 0 | AJ45: =V45*$C45 -> 0 | ... AO45: =AA45*$C45 -> 0 | AP45: =AM45+AK45 -> 346.275 | AQ45: =AM45+AL45+AH45 -> 1916.055 | AR45: =AO45+AN45 -> 392.445 | AS45: =AH45+AL45+AM45+AO45+AN45 -> 2308.5
B46: Travaux administratifs | C46: 1 | D46: Forfait | E46: =AB46 -> 900 | F46: =C46*E46 -> 900 | H46: 0 | I46: 0 | J46: =H46*$J$4 -> 0 | K46: 0 | L46: =H46*(1-$K46) -> 0 | M46: =I46*(1-$K46) -> 0 | N46: =J46*(1-$K46) -> 0 | O46: =(L46+M46+N46) -> 0 | P46: =O46*$P$4 -> 0 | Q46: =(O46+P46)*$Q$4 -> 0 | R46: =(O46+P46)*$R$4 -> 0 | S46: 0 | T46: =SUM(O46:S46) -> 0 | U46: 0 | V46: =V35 -> 0 | W46: =W35 -> 900 | X46: =SUM(U46:W46) -> 900 | Y46: 0 | Z46: =T46*$Z$4 -> 0 | AA46: 0 | AB46: =T46+X46+Y46+Z46+AA46 -> 900 | AC46: =O46*$C46 -> 0 | AD46: =P46*$C46 -> 0 | AE46: =Q46*$C46 -> 0 | AF46: =R46*$C46 -> 0 | AG46: =S46*$C46 -> 0 | AH46: =T46*$C46 -> 0 | AI46: =U46*$C46 -> 0 | AJ46: =V46*$C46 -> 0 | ... AO46: =AA46*$C46 -> 0 | AP46: =AM46+AK46 -> 900 | AQ46: =AM46+AL46+AH46 -> 900 | AR46: =AO46+AN46 -> 0 | AS46: =AH46+AL46+AM46+AO46+AN46 -> 900
B47: Travaux électriques, contrôle et Pronovo | C47: 1 | D47: Forfait | E47: =AB47 -> 1200 | F47: =C47*E47 -> 1200 | H47: 0 | I47: 0 | J47: =H47*$J$4 -> 0 | K47: 0 | L47: =H47*(1-$K47) -> 0 | M47: =I47*(1-$K47) -> 0 | N47: =J47*(1-$K47) -> 0 | O47: =(L47+M47+N47) -> 0 | P47: =O47*$P$4 -> 0 | Q47: =(O47+P47)*$Q$4 -> 0 | R47: =(O47+P47)*$R$4 -> 0 | S47: 0 | T47: =SUM(O47:S47) -> 0 | U47: 0 | V47: =V36 -> 1200 | W47: =W36 -> 0 | X47: =SUM(U47:W47) -> 1200 | Y47: 0 | Z47: =T47*$Z$4 -> 0 | AA47: 0 | AB47: =T47+X47+Y47+Z47+AA47 -> 1200 | AC47: =O47*$C47 -> 0 | AD47: =P47*$C47 -> 0 | AE47: =Q47*$C47 -> 0 | AF47: =R47*$C47 -> 0 | AG47: =S47*$C47 -> 0 | AH47: =T47*$C47 -> 0 | AI47: =U47*$C47 -> 0 | AJ47: =V47*$C47 -> 1200 | ... AO47: =AA47*$C47 -> 0 | AP47: =AM47+AK47 -> 0 | AQ47: =AM47+AL47+AH47 -> 1200 | AR47: =AO47+AN47 -> 0 | AS47: =AH47+AL47+AM47+AO47+AN47 -> 1200
A49: 14 | B49: Panneaux | C49: Puissance: | D49: =ROUNDUP((A49*465)/1000,2) -> 6.51 | F49: =SUM(F50:F59) -> 17018.761 | AC49: =+SUM(AC50:AC59) -> 6117.4835 | AD49: =+SUM(AD50:AD59) -> 0 | AE49: =+SUM(AE50:AE59) -> 0 | AF49: =+SUM(AF50:AF59) -> 122.34967 | AG49: =+SUM(AG50:AG59) -> 228.92417 | AH49: =+SUM(AH50:AH59) -> 6468.7573 | AI49: =+SUM(AI50:AI59) -> 3676 | AJ49: =+SUM(AJ50:AJ59) -> 1200 | ... AS49: =+SUM(AS50:AS59) -> 17018.761 | AT49: =IF(F49=AS49,"Matching","Not Matching") -> Matching | AU49: =SUM(AC49:AG49) -> 6468.7573 | AV49: =AU49/AS49 -> 0.38009567 | AW49: =AI49 -> 3676 | AX49: =AW49/AS49 -> 0.21599692 | AY49: =AJ49 -> 1200 | AZ49: =AY49/AS49 -> 0.070510422 | BA49: =AK49+AM49 -> 3137.8141 | BB49: =BA49/AS49 -> 0.18437383 | BC49: =AN49+AO49 -> 2536.1893 | BD49: =BC49/AS49 -> 0.14902315 | BE49: =IF((AU49+AW49+AY49+BA49+BC49)=AS49,"Matching","Not Matching") -> Matching | BF49: =AQ49 -> 14482.571 | BG49: =BF49/AS49 -> 0.85097685 | BH49: =AR49 -> 2536.1893 | BI49: =BH49/AS49 -> 0.14902315 | BJ49: =IF((BH49+BF49)=AS49,"Matching","Not Matching") -> Matching | BK49: =AS49*1.081 -> 18397.28 | BL49: =ROUND(BK49,-1) -> 18400 | BM49: =D49*380 -> 2473.8 | BN49: =BK49-BM49 -> 15923.48 | BO49: =BK49/D49 -> 2826.0031
B51: ="Panneau solaire "&G51 -> Panneau solaire JINKO JKM455N-54HL4R-V | C51: =A49 -> 14 | D51: U | E51: =AB51 -> 180.51476 | F51: =C51*E51 -> 2527.2067 | G51: =$G$7 -> JINKO JKM455N-54HL4R-V | H51: =H7 -> 52.4 | I51: =I7 -> 0 | J51: =H51*$J$4 -> 1.572 | K51: 0 | L51: =H51*(1-$K51) -> 52.4 | M51: =I51*(1-$K51) -> 0 | N51: =J51*(1-$K51) -> 1.572 | O51: =(L51+M51+N51) -> 53.972 | P51: =O51*$P$4 -> 0 | Q51: =(O51+P51)*$Q$4 -> 0 | R51: =(O51+P51)*$R$4 -> 1.07944 | S51: =(O51+P51)*$S$4 -> 2.6986 | T51: =SUM(O51:S51) -> 57.75004 | U51: =1*$U$4 -> 65 | V51: =V40 -> 0 | W51: =W40 -> 0 | X51: =SUM(U51:W51) -> 65 | Y51: =$Y$4/(1-$Y$4)*(T51+X51+Z51+AA51) -> 27.077215 | Z51: =T51*$Z$4 -> 14.43751 | AA51: =X51*$AA$4 -> 16.25 | AB51: =T51+X51+Y51+Z51+AA51 -> 180.51476 | AC51: =O51*$C51 -> 755.608 | AD51: =P51*$C51 -> 0 | AE51: =Q51*$C51 -> 0 | AF51: =R51*$C51 -> 15.11216 | AG51: =S51*$C51 -> 37.7804 | AH51: =T51*$C51 -> 808.50056 | AI51: =U51*$C51 -> 910 | AJ51: =V51*$C51 -> 0 | ... AO51: =AA51*$C51 -> 227.5 | AP51: =AM51+AK51 -> 379.08101 | AQ51: =AM51+AL51+AH51 -> 2097.5816 | AR51: =AO51+AN51 -> 429.62514 | AS51: =AH51+AL51+AM51+AO51+AN51 -> 2527.2067
B52: ="Onduleur Huawei "&G52 -> Onduleur Huawei SUN2000-6K-MAP0 | C52: 1 | D52: U | E52: =AB52 -> 2119.7012 | F52: =C52*E52 -> 2119.7012 | G52: =$G$8 -> SUN2000-6K-MAP0 | H52: =H8 -> 900.85 | I52: ='Financial Data'!$C$40 -> 251 | J52: =H52*$J$4 -> 27.0255 | K52: 0 | L52: =H52*(1-$K52) -> 900.85 | M52: =I52*(1-$K52) -> 251 | N52: =J52*(1-$K52) -> 27.0255 | O52: =(L52+M52+N52) -> 1178.8755 | P52: =O52*$P$4 -> 0 | Q52: =(O52+P52)*$Q$4 -> 0 | R52: =(O52+P52)*$R$4 -> 23.57751 | S52: =(O52+P52)*$S$4 -> 58.943775 | T52: =SUM(O52:S52) -> 1261.3968 | U52: =2*$U$5 -> 180 | V52: =V41 -> 0 | W52: =W41 -> 0 | X52: =SUM(U52:W52) -> 180 | Y52: =$Y$4/(1-$Y$4)*(T52+X52+Z52+AA52) -> 317.95517 | Z52: =T52*$Z$4 -> 315.3492 | AA52: =X52*$AA$4 -> 45 | AB52: =T52+X52+Y52+Z52+AA52 -> 2119.7012 | AC52: =O52*$C52 -> 1178.8755 | AD52: =P52*$C52 -> 0 | AE52: =Q52*$C52 -> 0 | AF52: =R52*$C52 -> 23.57751 | AG52: =S52*$C52 -> 58.943775 | AH52: =T52*$C52 -> 1261.3968 | AI52: =U52*$C52 -> 180 | AJ52: =V52*$C52 -> 0 | ... AO52: =AA52*$C52 -> 45 | AP52: =AM52+AK52 -> 317.95517 | AQ52: =AM52+AL52+AH52 -> 1759.352 | AR52: =AO52+AN52 -> 360.3492 | AS52: =AH52+AL52+AM52+AO52+AN52 -> 2119.7012
B53: Optimiseurs et accessoires | C53: 1 | D53: Forfait | E53: =AB53 -> 1266.3088 | F53: =C53*E53 -> 1266.3088 | H53: =H9 -> 300 | I53: ='Financial Data'!$C$41*C51 -> 378 | J53: =H53*$J$4 -> 9 | K53: 0 | L53: =H53*(1-$K53) -> 300 | M53: =I53*(1-$K53) -> 378 | N53: =J53*(1-$K53) -> 9 | O53: =(L53+M53+N53) -> 687 | P53: =O53*$P$4 -> 0 | Q53: =(O53+P53)*$Q$4 -> 0 | R53: =(O53+P53)*$R$4 -> 13.74 | S53: =(O53+P53)*$S$4 -> 34.35 | T53: =SUM(O53:S53) -> 735.09 | U53: =(C51/10)*$U$5 -> 126 | V53: =V42 -> 0 | W53: =W42 -> 0 | X53: =SUM(U53:W53) -> 126 | Y53: =$Y$4/(1-$Y$4)*(T53+X53+Z53+AA53) -> 189.94632 | Z53: =T53*$Z$4 -> 183.7725 | AA53: =X53*$AA$4 -> 31.5 | AB53: =T53+X53+Y53+Z53+AA53 -> 1266.3088 | AC53: =O53*$C53 -> 687 | AD53: =P53*$C53 -> 0 | AE53: =Q53*$C53 -> 0 | AF53: =R53*$C53 -> 13.74 | AG53: =S53*$C53 -> 34.35 | AH53: =T53*$C53 -> 735.09 | AI53: =U53*$C53 -> 126 | AJ53: =V53*$C53 -> 0 | ... AO53: =AA53*$C53 -> 31.5 | AP53: =AM53+AK53 -> 189.94632 | AQ53: =AM53+AL53+AH53 -> 1051.0363 | AR53: =AO53+AN53 -> 215.2725 | AS53: =AH53+AL53+AM53+AO53+AN53 -> 1266.3088
B54: Système de montage sur tuile | C54: =A49 -> 14 | D54: U | E54: =AB54 -> 257.66176 | F54: =C54*E54 -> 3607.2647 | H54: =H10 -> 100 | I54: =I10 -> 0 | J54: =H54*$J$4 -> 3 | K54: 0 | L54: =H54*(1-$K54) -> 100 | M54: =I54*(1-$K54) -> 0 | N54: =J54*(1-$K54) -> 3 | O54: =(L54+M54+N54) -> 103 | P54: =O54*$P$4 -> 0 | Q54: =(O54+P54)*$Q$4 -> 0 | R54: =(O54+P54)*$R$4 -> 2.06 | S54: =(O54+P54)*$S$4 -> 5.15 | T54: =SUM(O54:S54) -> 110.21 | U54: =1*$U$4 -> 65 | V54: =V43 -> 0 | W54: =W43 -> 0 | X54: =SUM(U54:W54) -> 65 | Y54: =$Y$4/(1-$Y$4)*(T54+X54+Z54+AA54) -> 38.649265 | Z54: =T54*$Z$4 -> 27.5525 | AA54: =X54*$AA$4 -> 16.25 | AB54: =T54+X54+Y54+Z54+AA54 -> 257.66176 | AC54: =O54*$C54 -> 1442 | AD54: =P54*$C54 -> 0 | AE54: =Q54*$C54 -> 0 | AF54: =R54*$C54 -> 28.84 | AG54: =S54*$C54 -> 72.1 | AH54: =T54*$C54 -> 1542.94 | AI54: =U54*$C54 -> 910 | AJ54: =V54*$C54 -> 0 | ... AO54: =AA54*$C54 -> 227.5 | AP54: =AM54+AK54 -> 541.08971 | AQ54: =AM54+AL54+AH54 -> 2994.0297 | AR54: =AO54+AN54 -> 613.235 | AS54: =AH54+AL54+AM54+AO54+AN54 -> 3607.2647
B55: Raccordement AC | C55: 1 | D55: Forfait | E55: =AB55 -> 3089.7794 | F55: =C55*E55 -> 3089.7794 | H55: =H11 -> 500 | I55: =I11 -> 0 | J55: =H55*$J$4 -> 15 | K55: 0 | L55: =H55*(1-$K55) -> 500 | M55: =I55*(1-$K55) -> 0 | N55: =J55*(1-$K55) -> 15 | O55: =(L55+M55+N55) -> 515 | P55: =O55*$P$4 -> 0 | Q55: =(O55+P55)*$Q$4 -> 0 | R55: =(O55+P55)*$R$4 -> 10.3 | S55: =(O55+P55)*$S$4 -> 25.75 | T55: =SUM(O55:S55) -> 551.05 | U55: =5*$U$5+600+500 -> 1550 | V55: =V44 -> 0 | W55: =W44 -> 0 | X55: =SUM(U55:W55) -> 1550 | Y55: =$Y$4/(1-$Y$4)*(T55+X55+Z55+AA55) -> 463.46691 | Z55: =T55*$Z$4 -> 137.7625 | AA55: =X55*$AA$4 -> 387.5 | AB55: =T55+X55+Y55+Z55+AA55 -> 3089.7794 | AC55: =O55*$C55 -> 515 | AD55: =P55*$C55 -> 0 | AE55: =Q55*$C55 -> 0 | AF55: =R55*$C55 -> 10.3 | AG55: =S55*$C55 -> 25.75 | AH55: =T55*$C55 -> 551.05 | AI55: =U55*$C55 -> 1550 | AJ55: =V55*$C55 -> 0 | ... AO55: =AA55*$C55 -> 387.5 | AP55: =AM55+AK55 -> 463.46691 | AQ55: =AM55+AL55+AH55 -> 2564.5169 | AR55: =AO55+AN55 -> 525.2625 | AS55: =AH55+AL55+AM55+AO55+AN55 -> 3089.7794
B56: Echafaudage jusqu'à 6m de hauteur | C56: 1 | D56: Forfait | E56: =AB56 -> 2308.5 | F56: =C56*E56 -> 2308.5 | H56: =H12 -> 1300 | I56: =I12 -> 200 | J56: =H56*$J$4 -> 39 | K56: 0 | L56: =H56*(1-$K56) -> 1300 | M56: =I56*(1-$K56) -> 200 | N56: =J56*(1-$K56) -> 39 | O56: =(L56+M56+N56) -> 1539 | P56: =O56*$P$4 -> 0 | Q56: =(O56+P56)*$Q$4 -> 0 | R56: =(O56+P56)*$R$4 -> 30.78 | S56: 0 | T56: =SUM(O56:S56) -> 1569.78 | U56: 0 | V56: =V45 -> 0 | W56: =W45 -> 0 | X56: =SUM(U56:W56) -> 0 | Y56: =$Y$4/(1-$Y$4)*(T56+X56+Z56+AA56) -> 346.275 | Z56: =T56*$Z$4 -> 392.445 | AA56: =X56*$AA$4 -> 0 | AB56: =T56+X56+Y56+Z56+AA56 -> 2308.5 | AC56: =O56*$C56 -> 1539 | AD56: =P56*$C56 -> 0 | AE56: =Q56*$C56 -> 0 | AF56: =R56*$C56 -> 30.78 | AG56: =S56*$C56 -> 0 | AH56: =T56*$C56 -> 1569.78 | AI56: =U56*$C56 -> 0 | AJ56: =V56*$C56 -> 0 | ... AO56: =AA56*$C56 -> 0 | AP56: =AM56+AK56 -> 346.275 | AQ56: =AM56+AL56+AH56 -> 1916.055 | AR56: =AO56+AN56 -> 392.445 | AS56: =AH56+AL56+AM56+AO56+AN56 -> 2308.5
B57: Travaux administratifs | C57: 1 | D57: Forfait | E57: =AB57 -> 900 | F57: =C57*E57 -> 900 | H57: 0 | I57: 0 | J57: =H57*$J$4 -> 0 | K57: 0 | L57: =H57*(1-$K57) -> 0 | M57: =I57*(1-$K57) -> 0 | N57: =J57*(1-$K57) -> 0 | O57: =(L57+M57+N57) -> 0 | P57: =O57*$P$4 -> 0 | Q57: =(O57+P57)*$Q$4 -> 0 | R57: =(O57+P57)*$R$4 -> 0 | S57: 0 | T57: =SUM(O57:S57) -> 0 | U57: 0 | V57: =V46 -> 0 | W57: =W46 -> 900 | X57: =SUM(U57:W57) -> 900 | Y57: 0 | Z57: =T57*$Z$4 -> 0 | AA57: 0 | AB57: =T57+X57+Y57+Z57+AA57 -> 900 | AC57: =O57*$C57 -> 0 | AD57: =P57*$C57 -> 0 | AE57: =Q57*$C57 -> 0 | AF57: =R57*$C57 -> 0 | AG57: =S57*$C57 -> 0 | AH57: =T57*$C57 -> 0 | AI57: =U57*$C57 -> 0 | AJ57: =V57*$C57 -> 0 | ... AO57: =AA57*$C57 -> 0 | AP57: =AM57+AK57 -> 900 | AQ57: =AM57+AL57+AH57 -> 900 | AR57: =AO57+AN57 -> 0 | AS57: =AH57+AL57+AM57+AO57+AN57 -> 900
B58: Travaux électriques, contrôle et Pronovo | C58: 1 | D58: Forfait | E58: =AB58 -> 1200 | F58: =C58*E58 -> 1200 | H58: 0 | I58: 0 | J58: =H58*$J$4 -> 0 | K58: 0 | L58: =H58*(1-$K58) -> 0 | M58: =I58*(1-$K58) -> 0 | N58: =J58*(1-$K58) -> 0 | O58: =(L58+M58+N58) -> 0 | P58: =O58*$P$4 -> 0 | Q58: =(O58+P58)*$Q$4 -> 0 | R58: =(O58+P58)*$R$4 -> 0 | S58: 0 | T58: =SUM(O58:S58) -> 0 | U58: 0 | V58: =V47 -> 1200 | W58: =W47 -> 0 | X58: =SUM(U58:W58) -> 1200 | Y58: 0 | Z58: =T58*$Z$4 -> 0 | AA58: 0 | AB58: =T58+X58+Y58+Z58+AA58 -> 1200 | AC58: =O58*$C58 -> 0 | AD58: =P58*$C58 -> 0 | AE58: =Q58*$C58 -> 0 | AF58: =R58*$C58 -> 0 | AG58: =S58*$C58 -> 0 | AH58: =T58*$C58 -> 0 | AI58: =U58*$C58 -> 0 | AJ58: =V58*$C58 -> 1200 | ... AO58: =AA58*$C58 -> 0 | AP58: =AM58+AK58 -> 0 | AQ58: =AM58+AL58+AH58 -> 1200 | AR58: =AO58+AN58 -> 0 | AS58: =AH58+AL58+AM58+AO58+AN58 -> 1200
A60: 15 | B60: Panneaux | C60: Puissance: | D60: =ROUNDUP((A60*465)/1000,2) -> 6.98 | F60: =SUM(F61:F70) -> 17512.658 | AC60: =+SUM(AC61:AC70) -> 6301.4555 | AD60: =+SUM(AD61:AD70) -> 0 | AE60: =+SUM(AE61:AE70) -> 0 | AF60: =+SUM(AF61:AF70) -> 126.02911 | AG60: =+SUM(AG61:AG70) -> 238.12277 | AH60: =+SUM(AH61:AH70) -> 6665.6074 | AI60: =+SUM(AI61:AI70) -> 3815 | AJ60: =+SUM(AJ61:AJ70) -> 1200 | ... AS60: =+SUM(AS61:AS70) -> 17512.658 | AT60: =IF(F60=AS60,"Matching","Not Matching") -> Matching | AU60: =SUM(AC60:AG60) -> 6665.6074 | AV60: =AU60/AS60 -> 0.38061655 | AW60: =AI60 -> 3815 | AX60: =AW60/AS60 -> 0.21784243 | AY60: =AJ60 -> 1200 | AZ60: =AY60/AS60 -> 0.068521866 | BA60: =AK60+AM60 -> 3211.8987 | BB60: =BA60/AS60 -> 0.18340441 | BC60: =AN60+AO60 -> 2620.1518 | BD60: =BC60/AS60 -> 0.14961474 | BE60: =IF((AU60+AW60+AY60+BA60+BC60)=AS60,"Matching","Not Matching") -> Matching | BF60: =AQ60 -> 14892.506 | BG60: =BF60/AS60 -> 0.85038526 | BH60: =AR60 -> 2620.1518 | BI60: =BH60/AS60 -> 0.14961474 | BJ60: =IF((BH60+BF60)=AS60,"Matching","Not Matching") -> Matching | BK60: =AS60*1.081 -> 18931.183 | BL60: =ROUND(BK60,-1) -> 18930 | BM60: =D60*380 -> 2652.4 | BN60: =BK60-BM60 -> 16278.783 | BO60: =BK60/D60 -> 2712.2039
B62: ="Panneau solaire "&G62 -> Panneau solaire JINKO JKM455N-54HL4R-V | C62: =A60 -> 15 | D62: U | E62: =AB62 -> 180.51476 | F62: =C62*E62 -> 2707.7215 | G62: =$G$7 -> JINKO JKM455N-54HL4R-V | H62: =H7 -> 52.4 | I62: =I7 -> 0 | J62: =H62*$J$4 -> 1.572 | K62: 0 | L62: =H62*(1-$K62) -> 52.4 | M62: =I62*(1-$K62) -> 0 | N62: =J62*(1-$K62) -> 1.572 | O62: =(L62+M62+N62) -> 53.972 | P62: =O62*$P$4 -> 0 | Q62: =(O62+P62)*$Q$4 -> 0 | R62: =(O62+P62)*$R$4 -> 1.07944 | S62: =(O62+P62)*$S$4 -> 2.6986 | T62: =SUM(O62:S62) -> 57.75004 | U62: =1*$U$4 -> 65 | V62: =V51 -> 0 | W62: =W51 -> 0 | X62: =SUM(U62:W62) -> 65 | Y62: =$Y$4/(1-$Y$4)*(T62+X62+Z62+AA62) -> 27.077215 | Z62: =T62*$Z$4 -> 14.43751 | AA62: =X62*$AA$4 -> 16.25 | AB62: =T62+X62+Y62+Z62+AA62 -> 180.51476 | AC62: =O62*$C62 -> 809.58 | AD62: =P62*$C62 -> 0 | AE62: =Q62*$C62 -> 0 | AF62: =R62*$C62 -> 16.1916 | AG62: =S62*$C62 -> 40.479 | AH62: =T62*$C62 -> 866.2506 | AI62: =U62*$C62 -> 975 | AJ62: =V62*$C62 -> 0 | ... AO62: =AA62*$C62 -> 243.75 | AP62: =AM62+AK62 -> 406.15822 | AQ62: =AM62+AL62+AH62 -> 2247.4088 | AR62: =AO62+AN62 -> 460.31265 | AS62: =AH62+AL62+AM62+AO62+AN62 -> 2707.7215
B63: ="Onduleur Huawei "&G63 -> Onduleur Huawei SUN2000-6K-MAP0 | C63: 1 | D63: U | E63: =AB63 -> 2119.7012 | F63: =C63*E63 -> 2119.7012 | G63: =$G$8 -> SUN2000-6K-MAP0 | H63: =H8 -> 900.85 | I63: ='Financial Data'!$C$40 -> 251 | J63: =H63*$J$4 -> 27.0255 | K63: 0 | L63: =H63*(1-$K63) -> 900.85 | M63: =I63*(1-$K63) -> 251 | N63: =J63*(1-$K63) -> 27.0255 | O63: =(L63+M63+N63) -> 1178.8755 | P63: =O63*$P$4 -> 0 | Q63: =(O63+P63)*$Q$4 -> 0 | R63: =(O63+P63)*$R$4 -> 23.57751 | S63: =(O63+P63)*$S$4 -> 58.943775 | T63: =SUM(O63:S63) -> 1261.3968 | U63: =2*$U$5 -> 180 | V63: =V52 -> 0 | W63: =W52 -> 0 | X63: =SUM(U63:W63) -> 180 | Y63: =$Y$4/(1-$Y$4)*(T63+X63+Z63+AA63) -> 317.95517 | Z63: =T63*$Z$4 -> 315.3492 | AA63: =X63*$AA$4 -> 45 | AB63: =T63+X63+Y63+Z63+AA63 -> 2119.7012 | AC63: =O63*$C63 -> 1178.8755 | AD63: =P63*$C63 -> 0 | AE63: =Q63*$C63 -> 0 | AF63: =R63*$C63 -> 23.57751 | AG63: =S63*$C63 -> 58.943775 | AH63: =T63*$C63 -> 1261.3968 | AI63: =U63*$C63 -> 180 | AJ63: =V63*$C63 -> 0 | ... AO63: =AA63*$C63 -> 45 | AP63: =AM63+AK63 -> 317.95517 | AQ63: =AM63+AL63+AH63 -> 1759.352 | AR63: =AO63+AN63 -> 360.3492 | AS63: =AH63+AL63+AM63+AO63+AN63 -> 2119.7012
B64: Optimiseurs et accessoires | C64: 1 | D64: Forfait | E64: =AB64 -> 1322.0294 | F64: =C64*E64 -> 1322.0294 | H64: =H9 -> 300 | I64: ='Financial Data'!$C$41*C62 -> 405 | J64: =H64*$J$4 -> 9 | K64: 0 | L64: =H64*(1-$K64) -> 300 | M64: =I64*(1-$K64) -> 405 | N64: =J64*(1-$K64) -> 9 | O64: =(L64+M64+N64) -> 714 | P64: =O64*$P$4 -> 0 | Q64: =(O64+P64)*$Q$4 -> 0 | R64: =(O64+P64)*$R$4 -> 14.28 | S64: =(O64+P64)*$S$4 -> 35.7 | T64: =SUM(O64:S64) -> 763.98 | U64: =(C62/10)*$U$5 -> 135 | V64: =V53 -> 0 | W64: =W53 -> 0 | X64: =SUM(U64:W64) -> 135 | Y64: =$Y$4/(1-$Y$4)*(T64+X64+Z64+AA64) -> 198.30441 | Z64: =T64*$Z$4 -> 190.995 | AA64: =X64*$AA$4 -> 33.75 | AB64: =T64+X64+Y64+Z64+AA64 -> 1322.0294 | AC64: =O64*$C64 -> 714 | AD64: =P64*$C64 -> 0 | AE64: =Q64*$C64 -> 0 | AF64: =R64*$C64 -> 14.28 | AG64: =S64*$C64 -> 35.7 | AH64: =T64*$C64 -> 763.98 | AI64: =U64*$C64 -> 135 | AJ64: =V64*$C64 -> 0 | ... AO64: =AA64*$C64 -> 33.75 | AP64: =AM64+AK64 -> 198.30441 | AQ64: =AM64+AL64+AH64 -> 1097.2844 | AR64: =AO64+AN64 -> 224.745 | AS64: =AH64+AL64+AM64+AO64+AN64 -> 1322.0294
B65: Système de montage sur tuile | C65: =A60 -> 15 | D65: U | E65: =AB65 -> 257.66176 | F65: =C65*E65 -> 3864.9265 | H65: =H10 -> 100 | I65: =I10 -> 0 | J65: =H65*$J$4 -> 3 | K65: 0 | L65: =H65*(1-$K65) -> 100 | M65: =I65*(1-$K65) -> 0 | N65: =J65*(1-$K65) -> 3 | O65: =(L65+M65+N65) -> 103 | P65: =O65*$P$4 -> 0 | Q65: =(O65+P65)*$Q$4 -> 0 | R65: =(O65+P65)*$R$4 -> 2.06 | S65: =(O65+P65)*$S$4 -> 5.15 | T65: =SUM(O65:S65) -> 110.21 | U65: =1*$U$4 -> 65 | V65: =V54 -> 0 | W65: =W54 -> 0 | X65: =SUM(U65:W65) -> 65 | Y65: =$Y$4/(1-$Y$4)*(T65+X65+Z65+AA65) -> 38.649265 | Z65: =T65*$Z$4 -> 27.5525 | AA65: =X65*$AA$4 -> 16.25 | AB65: =T65+X65+Y65+Z65+AA65 -> 257.66176 | AC65: =O65*$C65 -> 1545 | AD65: =P65*$C65 -> 0 | AE65: =Q65*$C65 -> 0 | AF65: =R65*$C65 -> 30.9 | AG65: =S65*$C65 -> 77.25 | AH65: =T65*$C65 -> 1653.15 | AI65: =U65*$C65 -> 975 | AJ65: =V65*$C65 -> 0 | ... AO65: =AA65*$C65 -> 243.75 | AP65: =AM65+AK65 -> 579.73897 | AQ65: =AM65+AL65+AH65 -> 3207.889 | AR65: =AO65+AN65 -> 657.0375 | AS65: =AH65+AL65+AM65+AO65+AN65 -> 3864.9265
B66: Raccordement AC | C66: 1 | D66: Forfait | E66: =AB66 -> 3089.7794 | F66: =C66*E66 -> 3089.7794 | H66: =H11 -> 500 | I66: =I11 -> 0 | J66: =H66*$J$4 -> 15 | K66: 0 | L66: =H66*(1-$K66) -> 500 | M66: =I66*(1-$K66) -> 0 | N66: =J66*(1-$K66) -> 15 | O66: =(L66+M66+N66) -> 515 | P66: =O66*$P$4 -> 0 | Q66: =(O66+P66)*$Q$4 -> 0 | R66: =(O66+P66)*$R$4 -> 10.3 | S66: =(O66+P66)*$S$4 -> 25.75 | T66: =SUM(O66:S66) -> 551.05 | U66: =5*$U$5+600+500 -> 1550 | V66: =V55 -> 0 | W66: =W55 -> 0 | X66: =SUM(U66:W66) -> 1550 | Y66: =$Y$4/(1-$Y$4)*(T66+X66+Z66+AA66) -> 463.46691 | Z66: =T66*$Z$4 -> 137.7625 | AA66: =X66*$AA$4 -> 387.5 | AB66: =T66+X66+Y66+Z66+AA66 -> 3089.7794 | AC66: =O66*$C66 -> 515 | AD66: =P66*$C66 -> 0 | AE66: =Q66*$C66 -> 0 | AF66: =R66*$C66 -> 10.3 | AG66: =S66*$C66 -> 25.75 | AH66: =T66*$C66 -> 551.05 | AI66: =U66*$C66 -> 1550 | AJ66: =V66*$C66 -> 0 | ... AO66: =AA66*$C66 -> 387.5 | AP66: =AM66+AK66 -> 463.46691 | AQ66: =AM66+AL66+AH66 -> 2564.5169 | AR66: =AO66+AN66 -> 525.2625 | AS66: =AH66+AL66+AM66+AO66+AN66 -> 3089.7794
B67: Echafaudage jusqu'à 6m de hauteur | C67: 1 | D67: Forfait | E67: =AB67 -> 2308.5 | F67: =C67*E67 -> 2308.5 | H67: =H12 -> 1300 | I67: =I12 -> 200 | J67: =H67*$J$4 -> 39 | K67: 0 | L67: =H67*(1-$K67) -> 1300 | M67: =I67*(1-$K67) -> 200 | N67: =J67*(1-$K67) -> 39 | O67: =(L67+M67+N67) -> 1539 | P67: =O67*$P$4 -> 0 | Q67: =(O67+P67)*$Q$4 -> 0 | R67: =(O67+P67)*$R$4 -> 30.78 | S67: 0 | T67: =SUM(O67:S67) -> 1569.78 | U67: 0 | V67: =V56 -> 0 | W67: =W56 -> 0 | X67: =SUM(U67:W67) -> 0 | Y67: =$Y$4/(1-$Y$4)*(T67+X67+Z67+AA67) -> 346.275 | Z67: =T67*$Z$4 -> 392.445 | AA67: =X67*$AA$4 -> 0 | AB67: =T67+X67+Y67+Z67+AA67 -> 2308.5 | AC67: =O67*$C67 -> 1539 | AD67: =P67*$C67 -> 0 | AE67: =Q67*$C67 -> 0 | AF67: =R67*$C67 -> 30.78 | AG67: =S67*$C67 -> 0 | AH67: =T67*$C67 -> 1569.78 | AI67: =U67*$C67 -> 0 | AJ67: =V67*$C67 -> 0 | ... AO67: =AA67*$C67 -> 0 | AP67: =AM67+AK67 -> 346.275 | AQ67: =AM67+AL67+AH67 -> 1916.055 | AR67: =AO67+AN67 -> 392.445 | AS67: =AH67+AL67+AM67+AO67+AN67 -> 2308.5
B68: Travaux administratifs | C68: 1 | D68: Forfait | E68: =AB68 -> 900 | F68: =C68*E68 -> 900 | H68: 0 | I68: 0 | J68: =H68*$J$4 -> 0 | K68: 0 | L68: =H68*(1-$K68) -> 0 | M68: =I68*(1-$K68) -> 0 | N68: =J68*(1-$K68) -> 0 | O68: =(L68+M68+N68) -> 0 | P68: =O68*$P$4 -> 0 | Q68: =(O68+P68)*$Q$4 -> 0 | R68: =(O68+P68)*$R$4 -> 0 | S68: 0 | T68: =SUM(O68:S68) -> 0 | U68: 0 | V68: =V57 -> 0 | W68: =W57 -> 900 | X68: =SUM(U68:W68) -> 900 | Y68: 0 | Z68: =T68*$Z$4 -> 0 | AA68: 0 | AB68: =T68+X68+Y68+Z68+AA68 -> 900 | AC68: =O68*$C68 -> 0 | AD68: =P68*$C68 -> 0 | AE68: =Q68*$C68 -> 0 | AF68: =R68*$C68 -> 0 | AG68: =S68*$C68 -> 0 | AH68: =T68*$C68 -> 0 | AI68: =U68*$C68 -> 0 | AJ68: =V68*$C68 -> 0 | ... AO68: =AA68*$C68 -> 0 | AP68: =AM68+AK68 -> 900 | AQ68: =AM68+AL68+AH68 -> 900 | AR68: =AO68+AN68 -> 0 | AS68: =AH68+AL68+AM68+AO68+AN68 -> 900
B69: Travaux électriques, contrôle et Pronovo | C69: 1 | D69: Forfait | E69: =AB69 -> 1200 | F69: =C69*E69 -> 1200 | H69: 0 | I69: 0 | J69: =H69*$J$4 -> 0 | K69: 0 | L69: =H69*(1-$K69) -> 0 | M69: =I69*(1-$K69) -> 0 | N69: =J69*(1-$K69) -> 0 | O69: =(L69+M69+N69) -> 0 | P69: =O69*$P$4 -> 0 | Q69: =(O69+P69)*$Q$4 -> 0 | R69: =(O69+P69)*$R$4 -> 0 | S69: 0 | T69: =SUM(O69:S69) -> 0 | U69: 0 | V69: =V58 -> 1200 | W69: =W58 -> 0 | X69: =SUM(U69:W69) -> 1200 | Y69: 0 | Z69: =T69*$Z$4 -> 0 | AA69: 0 | AB69: =T69+X69+Y69+Z69+AA69 -> 1200 | AC69: =O69*$C69 -> 0 | AD69: =P69*$C69 -> 0 | AE69: =Q69*$C69 -> 0 | AF69: =R69*$C69 -> 0 | AG69: =S69*$C69 -> 0 | AH69: =T69*$C69 -> 0 | AI69: =U69*$C69 -> 0 | AJ69: =V69*$C69 -> 1200 | ... AO69: =AA69*$C69 -> 0 | AP69: =AM69+AK69 -> 0 | AQ69: =AM69+AL69+AH69 -> 1200 | AR69: =AO69+AN69 -> 0 | AS69: =AH69+AL69+AM69+AO69+AN69 -> 1200
A71: =A60+1 -> 16 | B71: Panneaux | C71: Puissance: | D71: =ROUNDUP((A71*465)/1000,2) -> 7.44 | F71: =SUM(F72:F81) -> 18006.555 | AC71: =+SUM(AC72:AC81) -> 6485.4275 | AD71: =+SUM(AD72:AD81) -> 0 | AE71: =+SUM(AE72:AE81) -> 0 | AF71: =+SUM(AF72:AF81) -> 129.70855 | AG71: =+SUM(AG72:AG81) -> 247.32138 | AH71: =+SUM(AH72:AH81) -> 6862.4574 | AI71: =+SUM(AI72:AI81) -> 3954 | AJ71: =+SUM(AJ72:AJ81) -> 1200 | ... AS71: =+SUM(AS72:AS81) -> 18006.555 | AT71: =IF(F71=AS71,"Matching","Not Matching") -> Matching | AU71: =SUM(AC71:AG71) -> 6862.4574 | AV71: =AU71/AS71 -> 0.38110885 | AW71: =AI71 -> 3954 | AX71: =AW71/AS71 -> 0.2195867 | AY71: =AJ71 -> 1200 | AZ71: =AY71/AS71 -> 0.066642398 | BA71: =AK71+AM71 -> 3285.9833 | BB71: =BA71/AS71 -> 0.18248817 | BC71: =AN71+AO71 -> 2704.1144 | BD71: =BC71/AS71 -> 0.15017389 | BE71: =IF((AU71+AW71+AY71+BA71+BC71)=AS71,"Matching","Not Matching") -> Matching | BF71: =AQ71 -> 15302.441 | BG71: =BF71/AS71 -> 0.84982611 | BH71: =AR71 -> 2704.1144 | BI71: =BH71/AS71 -> 0.15017389 | BJ71: =IF((BH71+BF71)=AS71,"Matching","Not Matching") -> Matching | BK71: =AS71*1.081 -> 19465.086 | BL71: =ROUND(BK71,-1) -> 19470 | BM71: =D71*380 -> 2827.2 | BN71: =BK71-BM71 -> 16637.886 | BO71: =BK71/D71 -> 2616.275
B73: ="Panneau solaire "&G73 -> Panneau solaire JINKO JKM455N-54HL4R-V | C73: =A71 -> 16 | D73: U | E73: =AB73 -> 180.51476 | F73: =C73*E73 -> 2888.2362 | G73: =$G$7 -> JINKO JKM455N-54HL4R-V | H73: =H7 -> 52.4 | I73: =I7 -> 0 | J73: =H73*$J$4 -> 1.572 | K73: 0 | L73: =H73*(1-$K73) -> 52.4 | M73: =I73*(1-$K73) -> 0 | N73: =J73*(1-$K73) -> 1.572 | O73: =(L73+M73+N73) -> 53.972 | P73: =O73*$P$4 -> 0 | Q73: =(O73+P73)*$Q$4 -> 0 | R73: =(O73+P73)*$R$4 -> 1.07944 | S73: =(O73+P73)*$S$4 -> 2.6986 | T73: =SUM(O73:S73) -> 57.75004 | U73: =1*$U$4 -> 65 | V73: =V62 -> 0 | W73: =W62 -> 0 | X73: =SUM(U73:W73) -> 65 | Y73: =$Y$4/(1-$Y$4)*(T73+X73+Z73+AA73) -> 27.077215 | Z73: =T73*$Z$4 -> 14.43751 | AA73: =X73*$AA$4 -> 16.25 | AB73: =T73+X73+Y73+Z73+AA73 -> 180.51476 | AC73: =O73*$C73 -> 863.552 | AD73: =P73*$C73 -> 0 | AE73: =Q73*$C73 -> 0 | AF73: =R73*$C73 -> 17.27104 | AG73: =S73*$C73 -> 43.1776 | AH73: =T73*$C73 -> 924.00064 | AI73: =U73*$C73 -> 1040 | AJ73: =V73*$C73 -> 0 | ... AO73: =AA73*$C73 -> 260 | AP73: =AM73+AK73 -> 433.23544 | AQ73: =AM73+AL73+AH73 -> 2397.2361 | AR73: =AO73+AN73 -> 491.00016 | AS73: =AH73+AL73+AM73+AO73+AN73 -> 2888.2362
B74: ="Onduleur Huawei "&G74 -> Onduleur Huawei SUN2000-6K-MAP0 | C74: 1 | D74: U | E74: =AB74 -> 2119.7012 | F74: =C74*E74 -> 2119.7012 | G74: =$G$8 -> SUN2000-6K-MAP0 | H74: =H8 -> 900.85 | I74: ='Financial Data'!$C$40 -> 251 | J74: =H74*$J$4 -> 27.0255 | K74: 0 | L74: =H74*(1-$K74) -> 900.85 | M74: =I74*(1-$K74) -> 251 | N74: =J74*(1-$K74) -> 27.0255 | O74: =(L74+M74+N74) -> 1178.8755 | P74: =O74*$P$4 -> 0 | Q74: =(O74+P74)*$Q$4 -> 0 | R74: =(O74+P74)*$R$4 -> 23.57751 | S74: =(O74+P74)*$S$4 -> 58.943775 | T74: =SUM(O74:S74) -> 1261.3968 | U74: =2*$U$5 -> 180 | V74: =V63 -> 0 | W74: =W63 -> 0 | X74: =SUM(U74:W74) -> 180 | Y74: =$Y$4/(1-$Y$4)*(T74+X74+Z74+AA74) -> 317.95517 | Z74: =T74*$Z$4 -> 315.3492 | AA74: =X74*$AA$4 -> 45 | AB74: =T74+X74+Y74+Z74+AA74 -> 2119.7012 | AC74: =O74*$C74 -> 1178.8755 | AD74: =P74*$C74 -> 0 | AE74: =Q74*$C74 -> 0 | AF74: =R74*$C74 -> 23.57751 | AG74: =S74*$C74 -> 58.943775 | AH74: =T74*$C74 -> 1261.3968 | AI74: =U74*$C74 -> 180 | AJ74: =V74*$C74 -> 0 | ... AO74: =AA74*$C74 -> 45 | AP74: =AM74+AK74 -> 317.95517 | AQ74: =AM74+AL74+AH74 -> 1759.352 | AR74: =AO74+AN74 -> 360.3492 | AS74: =AH74+AL74+AM74+AO74+AN74 -> 2119.7012
B75: Optimiseurs et accessoires | C75: 1 | D75: Forfait | E75: =AB75 -> 1377.75 | F75: =C75*E75 -> 1377.75 | H75: =H9 -> 300 | I75: ='Financial Data'!$C$41*C73 -> 432 | J75: =H75*$J$4 -> 9 | K75: 0 | L75: =H75*(1-$K75) -> 300 | M75: =I75*(1-$K75) -> 432 | N75: =J75*(1-$K75) -> 9 | O75: =(L75+M75+N75) -> 741 | P75: =O75*$P$4 -> 0 | Q75: =(O75+P75)*$Q$4 -> 0 | R75: =(O75+P75)*$R$4 -> 14.82 | S75: =(O75+P75)*$S$4 -> 37.05 | T75: =SUM(O75:S75) -> 792.87 | U75: =(C73/10)*$U$5 -> 144 | V75: =V64 -> 0 | W75: =W64 -> 0 | X75: =SUM(U75:W75) -> 144 | Y75: =$Y$4/(1-$Y$4)*(T75+X75+Z75+AA75) -> 206.6625 | Z75: =T75*$Z$4 -> 198.2175 | AA75: =X75*$AA$4 -> 36 | AB75: =T75+X75+Y75+Z75+AA75 -> 1377.75 | AC75: =O75*$C75 -> 741 | AD75: =P75*$C75 -> 0 | AE75: =Q75*$C75 -> 0 | AF75: =R75*$C75 -> 14.82 | AG75: =S75*$C75 -> 37.05 | AH75: =T75*$C75 -> 792.87 | AI75: =U75*$C75 -> 144 | AJ75: =V75*$C75 -> 0 | ... AO75: =AA75*$C75 -> 36 | AP75: =AM75+AK75 -> 206.6625 | AQ75: =AM75+AL75+AH75 -> 1143.5325 | AR75: =AO75+AN75 -> 234.2175 | AS75: =AH75+AL75+AM75+AO75+AN75 -> 1377.75
B76: Système de montage sur tuile | C76: =A71 -> 16 | D76: U | E76: =AB76 -> 257.66176 | F76: =C76*E76 -> 4122.5882 | H76: =H10 -> 100 | I76: =I10 -> 0 | J76: =H76*$J$4 -> 3 | K76: 0 | L76: =H76*(1-$K76) -> 100 | M76: =I76*(1-$K76) -> 0 | N76: =J76*(1-$K76) -> 3 | O76: =(L76+M76+N76) -> 103 | P76: =O76*$P$4 -> 0 | Q76: =(O76+P76)*$Q$4 -> 0 | R76: =(O76+P76)*$R$4 -> 2.06 | S76: =(O76+P76)*$S$4 -> 5.15 | T76: =SUM(O76:S76) -> 110.21 | U76: =1*$U$4 -> 65 | V76: =V65 -> 0 | W76: =W65 -> 0 | X76: =SUM(U76:W76) -> 65 | Y76: =$Y$4/(1-$Y$4)*(T76+X76+Z76+AA76) -> 38.649265 | Z76: =T76*$Z$4 -> 27.5525 | AA76: =X76*$AA$4 -> 16.25 | AB76: =T76+X76+Y76+Z76+AA76 -> 257.66176 | AC76: =O76*$C76 -> 1648 | AD76: =P76*$C76 -> 0 | AE76: =Q76*$C76 -> 0 | AF76: =R76*$C76 -> 32.96 | AG76: =S76*$C76 -> 82.4 | AH76: =T76*$C76 -> 1763.36 | AI76: =U76*$C76 -> 1040 | AJ76: =V76*$C76 -> 0 | ... AO76: =AA76*$C76 -> 260 | AP76: =AM76+AK76 -> 618.38824 | AQ76: =AM76+AL76+AH76 -> 3421.7482 | AR76: =AO76+AN76 -> 700.84 | AS76: =AH76+AL76+AM76+AO76+AN76 -> 4122.5882
B77: Raccordement AC | C77: 1 | D77: Forfait | E77: =AB77 -> 3089.7794 | F77: =C77*E77 -> 3089.7794 | H77: =H11 -> 500 | I77: =I11 -> 0 | J77: =H77*$J$4 -> 15 | K77: 0 | L77: =H77*(1-$K77) -> 500 | M77: =I77*(1-$K77) -> 0 | N77: =J77*(1-$K77) -> 15 | O77: =(L77+M77+N77) -> 515 | P77: =O77*$P$4 -> 0 | Q77: =(O77+P77)*$Q$4 -> 0 | R77: =(O77+P77)*$R$4 -> 10.3 | S77: =(O77+P77)*$S$4 -> 25.75 | T77: =SUM(O77:S77) -> 551.05 | U77: =5*$U$5+600+500 -> 1550 | V77: =V66 -> 0 | W77: =W66 -> 0 | X77: =SUM(U77:W77) -> 1550 | Y77: =$Y$4/(1-$Y$4)*(T77+X77+Z77+AA77) -> 463.46691 | Z77: =T77*$Z$4 -> 137.7625 | AA77: =X77*$AA$4 -> 387.5 | AB77: =T77+X77+Y77+Z77+AA77 -> 3089.7794 | AC77: =O77*$C77 -> 515 | AD77: =P77*$C77 -> 0 | AE77: =Q77*$C77 -> 0 | AF77: =R77*$C77 -> 10.3 | AG77: =S77*$C77 -> 25.75 | AH77: =T77*$C77 -> 551.05 | AI77: =U77*$C77 -> 1550 | AJ77: =V77*$C77 -> 0 | ... AO77: =AA77*$C77 -> 387.5 | AP77: =AM77+AK77 -> 463.46691 | AQ77: =AM77+AL77+AH77 -> 2564.5169 | AR77: =AO77+AN77 -> 525.2625 | AS77: =AH77+AL77+AM77+AO77+AN77 -> 3089.7794
B78: Echafaudage jusqu'à 6m de hauteur | C78: 1 | D78: Forfait | E78: =AB78 -> 2308.5 | F78: =C78*E78 -> 2308.5 | H78: =H12 -> 1300 | I78: =I12 -> 200 | J78: =H78*$J$4 -> 39 | K78: 0 | L78: =H78*(1-$K78) -> 1300 | M78: =I78*(1-$K78) -> 200 | N78: =J78*(1-$K78) -> 39 | O78: =(L78+M78+N78) -> 1539 | P78: =O78*$P$4 -> 0 | Q78: =(O78+P78)*$Q$4 -> 0 | R78: =(O78+P78)*$R$4 -> 30.78 | S78: 0 | T78: =SUM(O78:S78) -> 1569.78 | U78: 0 | V78: =V67 -> 0 | W78: =W67 -> 0 | X78: =SUM(U78:W78) -> 0 | Y78: =$Y$4/(1-$Y$4)*(T78+X78+Z78+AA78) -> 346.275 | Z78: =T78*$Z$4 -> 392.445 | AA78: =X78*$AA$4 -> 0 | AB78: =T78+X78+Y78+Z78+AA78 -> 2308.5 | AC78: =O78*$C78 -> 1539 | AD78: =P78*$C78 -> 0 | AE78: =Q78*$C78 -> 0 | AF78: =R78*$C78 -> 30.78 | AG78: =S78*$C78 -> 0 | AH78: =T78*$C78 -> 1569.78 | AI78: =U78*$C78 -> 0 | AJ78: =V78*$C78 -> 0 | ... AO78: =AA78*$C78 -> 0 | AP78: =AM78+AK78 -> 346.275 | AQ78: =AM78+AL78+AH78 -> 1916.055 | AR78: =AO78+AN78 -> 392.445 | AS78: =AH78+AL78+AM78+AO78+AN78 -> 2308.5
B79: Travaux administratifs | C79: 1 | D79: Forfait | E79: =AB79 -> 900 | F79: =C79*E79 -> 900 | H79: 0 | I79: 0 | J79: =H79*$J$4 -> 0 | K79: 0 | L79: =H79*(1-$K79) -> 0 | M79: =I79*(1-$K79) -> 0 | N79: =J79*(1-$K79) -> 0 | O79: =(L79+M79+N79) -> 0 | P79: =O79*$P$4 -> 0 | Q79: =(O79+P79)*$Q$4 -> 0 | R79: =(O79+P79)*$R$4 -> 0 | S79: 0 | T79: =SUM(O79:S79) -> 0 | U79: 0 | V79: =V68 -> 0 | W79: =W68 -> 900 | X79: =SUM(U79:W79) -> 900 | Y79: 0 | Z79: =T79*$Z$4 -> 0 | AA79: 0 | AB79: =T79+X79+Y79+Z79+AA79 -> 900 | AC79: =O79*$C79 -> 0 | AD79: =P79*$C79 -> 0 | AE79: =Q79*$C79 -> 0 | AF79: =R79*$C79 -> 0 | AG79: =S79*$C79 -> 0 | AH79: =T79*$C79 -> 0 | AI79: =U79*$C79 -> 0 | AJ79: =V79*$C79 -> 0 | ... AO79: =AA79*$C79 -> 0 | AP79: =AM79+AK79 -> 900 | AQ79: =AM79+AL79+AH79 -> 900 | AR79: =AO79+AN79 -> 0 | AS79: =AH79+AL79+AM79+AO79+AN79 -> 900
B80: Travaux électriques, contrôle et Pronovo | C80: 1 | D80: Forfait | E80: =AB80 -> 1200 | F80: =C80*E80 -> 1200 | H80: 0 | I80: 0 | J80: =H80*$J$4 -> 0 | K80: 0 | L80: =H80*(1-$K80) -> 0 | M80: =I80*(1-$K80) -> 0 | N80: =J80*(1-$K80) -> 0 | O80: =(L80+M80+N80) -> 0 | P80: =O80*$P$4 -> 0 | Q80: =(O80+P80)*$Q$4 -> 0 | R80: =(O80+P80)*$R$4 -> 0 | S80: 0 | T80: =SUM(O80:S80) -> 0 | U80: 0 | V80: =V69 -> 1200 | W80: =W69 -> 0 | X80: =SUM(U80:W80) -> 1200 | Y80: 0 | Z80: =T80*$Z$4 -> 0 | AA80: 0 | AB80: =T80+X80+Y80+Z80+AA80 -> 1200 | AC80: =O80*$C80 -> 0 | AD80: =P80*$C80 -> 0 | AE80: =Q80*$C80 -> 0 | AF80: =R80*$C80 -> 0 | AG80: =S80*$C80 -> 0 | AH80: =T80*$C80 -> 0 | AI80: =U80*$C80 -> 0 | AJ80: =V80*$C80 -> 1200 | ... AO80: =AA80*$C80 -> 0 | AP80: =AM80+AK80 -> 0 | AQ80: =AM80+AL80+AH80 -> 1200 | AR80: =AO80+AN80 -> 0 | AS80: =AH80+AL80+AM80+AO80+AN80 -> 1200
A82: =A71+1 -> 17 | B82: Panneaux | C82: Puissance: | D82: =ROUNDUP((A82*465)/1000,2) -> 7.91 | F82: =SUM(F83:F92) -> 18771.439 | AC82: =+SUM(AC83:AC92) -> 6841.6155 | AD82: =+SUM(AD83:AD92) -> 0 | AE82: =+SUM(AE83:AE92) -> 0 | AF82: =+SUM(AF83:AF92) -> 136.83231 | AG82: =+SUM(AG83:AG92) -> 265.13078 | AH82: =+SUM(AH83:AH92) -> 7243.5786 | AI82: =+SUM(AI83:AI92) -> 4093 | AJ82: =+SUM(AJ83:AJ92) -> 1200 | ... AS82: =+SUM(AS83:AS92) -> 18771.439 | AT82: =IF(F82=AS82,"Matching","Not Matching") -> Matching | AU82: =SUM(AC82:AG82) -> 7243.5786 | AV82: =AU82/AS82 -> 0.38588297 | AW82: =AI82 -> 4093 | AX82: =AW82/AS82 -> 0.21804402 | AY82: =AJ82 -> 1200 | AZ82: =AY82/AS82 -> 0.063926905 | BA82: =AK82+AM82 -> 3400.7159 | BB82: =BA82/AS82 -> 0.18116437 | BC82: =AN82+AO82 -> 2834.1446 | BD82: =BC82/AS82 -> 0.15098175 | BE82: =IF((AU82+AW82+AY82+BA82+BC82)=AS82,"Matching","Not Matching") -> Matching | BF82: =AQ82 -> 15937.294 | BG82: =BF82/AS82 -> 0.84901825 | BH82: =AR82 -> 2834.1446 | BI82: =BH82/AS82 -> 0.15098175 | BJ82: =IF((BH82+BF82)=AS82,"Matching","Not Matching") -> Matching | BK82: =AS82*1.081 -> 20291.926 | BL82: =ROUND(BK82,-1) -> 20290 | BM82: =D82*380 -> 3005.8 | BN82: =BK82-BM82 -> 17286.126 | BO82: =BK82/D82 -> 2565.3509
B84: ="Panneau solaire "&G84 -> Panneau solaire JINKO JKM455N-54HL4R-V | C84: =A82 -> 17 | D84: U | E84: =AB84 -> 180.51476 | F84: =C84*E84 -> 3068.751 | G84: =$G$7 -> JINKO JKM455N-54HL4R-V | H84: =H73 -> 52.4 | I84: =I73 -> 0 | J84: =H84*$J$4 -> 1.572 | K84: 0 | L84: =H84*(1-$K84) -> 52.4 | M84: =I84*(1-$K84) -> 0 | N84: =J84*(1-$K84) -> 1.572 | O84: =(L84+M84+N84) -> 53.972 | P84: =O84*$P$4 -> 0 | Q84: =(O84+P84)*$Q$4 -> 0 | R84: =(O84+P84)*$R$4 -> 1.07944 | S84: =(O84+P84)*$S$4 -> 2.6986 | T84: =SUM(O84:S84) -> 57.75004 | U84: =1*$U$4 -> 65 | V84: =V73 -> 0 | W84: =W73 -> 0 | X84: =SUM(U84:W84) -> 65 | Y84: =$Y$4/(1-$Y$4)*(T84+X84+Z84+AA84) -> 27.077215 | Z84: =T84*$Z$4 -> 14.43751 | AA84: =X84*$AA$4 -> 16.25 | AB84: =T84+X84+Y84+Z84+AA84 -> 180.51476 | AC84: =O84*$C84 -> 917.524 | AD84: =P84*$C84 -> 0 | AE84: =Q84*$C84 -> 0 | AF84: =R84*$C84 -> 18.35048 | AG84: =S84*$C84 -> 45.8762 | AH84: =T84*$C84 -> 981.75068 | AI84: =U84*$C84 -> 1105 | AJ84: =V84*$C84 -> 0 | ... AO84: =AA84*$C84 -> 276.25 | AP84: =AM84+AK84 -> 460.31265 | AQ84: =AM84+AL84+AH84 -> 2547.0633 | AR84: =AO84+AN84 -> 521.68767 | AS84: =AH84+AL84+AM84+AO84+AN84 -> 3068.751
B85: ="Onduleur Huawei "&G85 -> Onduleur Huawei SUN2000-8K-MAP0 | C85: 1 | D85: U | E85: =AB85 -> 2390.6881 | F85: =C85*E85 -> 2390.6881 | G85: ='Technical Data'!B13 -> SUN2000-8K-MAP0 | H85: ='Financial Data'!C34 -> 1068.05 | I85: ='Financial Data'!$C$40 -> 251 | J85: =H85*$J$4 -> 32.0415 | K85: 0 | L85: =H85*(1-$K85) -> 1068.05 | M85: =I85*(1-$K85) -> 251 | N85: =J85*(1-$K85) -> 32.0415 | O85: =(L85+M85+N85) -> 1351.0915 | P85: =O85*$P$4 -> 0 | Q85: =(O85+P85)*$Q$4 -> 0 | R85: =(O85+P85)*$R$4 -> 27.02183 | S85: =(O85+P85)*$S$4 -> 67.554575 | T85: =SUM(O85:S85) -> 1445.6679 | U85: =2*$U$5 -> 180 | V85: =V74 -> 0 | W85: =W74 -> 0 | X85: =SUM(U85:W85) -> 180 | Y85: =$Y$4/(1-$Y$4)*(T85+X85+Z85+AA85) -> 358.60321 | Z85: =T85*$Z$4 -> 361.41698 | AA85: =X85*$AA$4 -> 45 | AB85: =T85+X85+Y85+Z85+AA85 -> 2390.6881 | AC85: =O85*$C85 -> 1351.0915 | AD85: =P85*$C85 -> 0 | AE85: =Q85*$C85 -> 0 | AF85: =R85*$C85 -> 27.02183 | AG85: =S85*$C85 -> 67.554575 | AH85: =T85*$C85 -> 1445.6679 | AI85: =U85*$C85 -> 180 | AJ85: =V85*$C85 -> 0 | ... AO85: =AA85*$C85 -> 45 | AP85: =AM85+AK85 -> 358.60321 | AQ85: =AM85+AL85+AH85 -> 1984.2711 | AR85: =AO85+AN85 -> 406.41698 | AS85: =AH85+AL85+AM85+AO85+AN85 -> 2390.6881
B86: Optimiseurs et accessoires | C86: 1 | D86: Forfait | E86: =AB86 -> 1433.4706 | F86: =C86*E86 -> 1433.4706 | H86: =H9 -> 300 | I86: ='Financial Data'!$C$41*C84 -> 459 | J86: =H86*$J$4 -> 9 | K86: 0 | L86: =H86*(1-$K86) -> 300 | M86: =I86*(1-$K86) -> 459 | N86: =J86*(1-$K86) -> 9 | O86: =(L86+M86+N86) -> 768 | P86: =O86*$P$4 -> 0 | Q86: =(O86+P86)*$Q$4 -> 0 | R86: =(O86+P86)*$R$4 -> 15.36 | S86: =(O86+P86)*$S$4 -> 38.4 | T86: =SUM(O86:S86) -> 821.76 | U86: =(C84/10)*$U$5 -> 153 | V86: =V75 -> 0 | W86: =W75 -> 0 | X86: =SUM(U86:W86) -> 153 | Y86: =$Y$4/(1-$Y$4)*(T86+X86+Z86+AA86) -> 215.02059 | Z86: =T86*$Z$4 -> 205.44 | AA86: =X86*$AA$4 -> 38.25 | AB86: =T86+X86+Y86+Z86+AA86 -> 1433.4706 | AC86: =O86*$C86 -> 768 | AD86: =P86*$C86 -> 0 | AE86: =Q86*$C86 -> 0 | AF86: =R86*$C86 -> 15.36 | AG86: =S86*$C86 -> 38.4 | AH86: =T86*$C86 -> 821.76 | AI86: =U86*$C86 -> 153 | AJ86: =V86*$C86 -> 0 | ... AO86: =AA86*$C86 -> 38.25 | AP86: =AM86+AK86 -> 215.02059 | AQ86: =AM86+AL86+AH86 -> 1189.7806 | AR86: =AO86+AN86 -> 243.69 | AS86: =AH86+AL86+AM86+AO86+AN86 -> 1433.4706
B87: Système de montage sur tuile | C87: =A82 -> 17 | D87: U | E87: =AB87 -> 257.66176 | F87: =C87*E87 -> 4380.25 | H87: =H10 -> 100 | I87: =I76 -> 0 | J87: =H87*$J$4 -> 3 | K87: 0 | L87: =H87*(1-$K87) -> 100 | M87: =I87*(1-$K87) -> 0 | N87: =J87*(1-$K87) -> 3 | O87: =(L87+M87+N87) -> 103 | P87: =O87*$P$4 -> 0 | Q87: =(O87+P87)*$Q$4 -> 0 | R87: =(O87+P87)*$R$4 -> 2.06 | S87: =(O87+P87)*$S$4 -> 5.15 | T87: =SUM(O87:S87) -> 110.21 | U87: =1*$U$4 -> 65 | V87: =V76 -> 0 | W87: =W76 -> 0 | X87: =SUM(U87:W87) -> 65 | Y87: =$Y$4/(1-$Y$4)*(T87+X87+Z87+AA87) -> 38.649265 | Z87: =T87*$Z$4 -> 27.5525 | AA87: =X87*$AA$4 -> 16.25 | AB87: =T87+X87+Y87+Z87+AA87 -> 257.66176 | AC87: =O87*$C87 -> 1751 | AD87: =P87*$C87 -> 0 | AE87: =Q87*$C87 -> 0 | AF87: =R87*$C87 -> 35.02 | AG87: =S87*$C87 -> 87.55 | AH87: =T87*$C87 -> 1873.57 | AI87: =U87*$C87 -> 1105 | AJ87: =V87*$C87 -> 0 | ... AO87: =AA87*$C87 -> 276.25 | AP87: =AM87+AK87 -> 657.0375 | AQ87: =AM87+AL87+AH87 -> 3635.6075 | AR87: =AO87+AN87 -> 744.6425 | AS87: =AH87+AL87+AM87+AO87+AN87 -> 4380.25
B88: Raccordement AC | C88: 1 | D88: Forfait | E88: =AB88 -> 3089.7794 | F88: =C88*E88 -> 3089.7794 | H88: =H11 -> 500 | I88: =I77 -> 0 | J88: =H88*$J$4 -> 15 | K88: 0 | L88: =H88*(1-$K88) -> 500 | M88: =I88*(1-$K88) -> 0 | N88: =J88*(1-$K88) -> 15 | O88: =(L88+M88+N88) -> 515 | P88: =O88*$P$4 -> 0 | Q88: =(O88+P88)*$Q$4 -> 0 | R88: =(O88+P88)*$R$4 -> 10.3 | S88: =(O88+P88)*$S$4 -> 25.75 | T88: =SUM(O88:S88) -> 551.05 | U88: =5*$U$5+600+500 -> 1550 | V88: =V77 -> 0 | W88: =W77 -> 0 | X88: =SUM(U88:W88) -> 1550 | Y88: =$Y$4/(1-$Y$4)*(T88+X88+Z88+AA88) -> 463.46691 | Z88: =T88*$Z$4 -> 137.7625 | AA88: =X88*$AA$4 -> 387.5 | AB88: =T88+X88+Y88+Z88+AA88 -> 3089.7794 | AC88: =O88*$C88 -> 515 | AD88: =P88*$C88 -> 0 | AE88: =Q88*$C88 -> 0 | AF88: =R88*$C88 -> 10.3 | AG88: =S88*$C88 -> 25.75 | AH88: =T88*$C88 -> 551.05 | AI88: =U88*$C88 -> 1550 | AJ88: =V88*$C88 -> 0 | ... AO88: =AA88*$C88 -> 387.5 | AP88: =AM88+AK88 -> 463.46691 | AQ88: =AM88+AL88+AH88 -> 2564.5169 | AR88: =AO88+AN88 -> 525.2625 | AS88: =AH88+AL88+AM88+AO88+AN88 -> 3089.7794
B89: Echafaudage jusqu'à 6m de hauteur | C89: 1 | D89: Forfait | E89: =AB89 -> 2308.5 | F89: =C89*E89 -> 2308.5 | H89: =H45 -> 1300 | I89: =I45 -> 200 | J89: =H89*$J$4 -> 39 | K89: 0 | L89: =H89*(1-$K89) -> 1300 | M89: =I89*(1-$K89) -> 200 | N89: =J89*(1-$K89) -> 39 | O89: =(L89+M89+N89) -> 1539 | P89: =O89*$P$4 -> 0 | Q89: =(O89+P89)*$Q$4 -> 0 | R89: =(O89+P89)*$R$4 -> 30.78 | S89: 0 | T89: =SUM(O89:S89) -> 1569.78 | U89: 0 | V89: =V78 -> 0 | W89: =W78 -> 0 | X89: =SUM(U89:W89) -> 0 | Y89: =$Y$4/(1-$Y$4)*(T89+X89+Z89+AA89) -> 346.275 | Z89: =T89*$Z$4 -> 392.445 | AA89: =X89*$AA$4 -> 0 | AB89: =T89+X89+Y89+Z89+AA89 -> 2308.5 | AC89: =O89*$C89 -> 1539 | AD89: =P89*$C89 -> 0 | AE89: =Q89*$C89 -> 0 | AF89: =R89*$C89 -> 30.78 | AG89: =S89*$C89 -> 0 | AH89: =T89*$C89 -> 1569.78 | AI89: =U89*$C89 -> 0 | AJ89: =V89*$C89 -> 0 | ... AO89: =AA89*$C89 -> 0 | AP89: =AM89+AK89 -> 346.275 | AQ89: =AM89+AL89+AH89 -> 1916.055 | AR89: =AO89+AN89 -> 392.445 | AS89: =AH89+AL89+AM89+AO89+AN89 -> 2308.5
B90: Travaux administratifs | C90: 1 | D90: Forfait | E90: =AB90 -> 900 | F90: =C90*E90 -> 900 | H90: 0 | I90: 0 | J90: =H90*$J$4 -> 0 | K90: 0 | L90: =H90*(1-$K90) -> 0 | M90: =I90*(1-$K90) -> 0 | N90: =J90*(1-$K90) -> 0 | O90: =(L90+M90+N90) -> 0 | P90: =O90*$P$4 -> 0 | Q90: =(O90+P90)*$Q$4 -> 0 | R90: =(O90+P90)*$R$4 -> 0 | S90: 0 | T90: =SUM(O90:S90) -> 0 | U90: 0 | V90: =V79 -> 0 | W90: =W79 -> 900 | X90: =SUM(U90:W90) -> 900 | Y90: 0 | Z90: =T90*$Z$4 -> 0 | AA90: 0 | AB90: =T90+X90+Y90+Z90+AA90 -> 900 | AC90: =O90*$C90 -> 0 | AD90: =P90*$C90 -> 0 | AE90: =Q90*$C90 -> 0 | AF90: =R90*$C90 -> 0 | AG90: =S90*$C90 -> 0 | AH90: =T90*$C90 -> 0 | AI90: =U90*$C90 -> 0 | AJ90: =V90*$C90 -> 0 | ... AO90: =AA90*$C90 -> 0 | AP90: =AM90+AK90 -> 900 | AQ90: =AM90+AL90+AH90 -> 900 | AR90: =AO90+AN90 -> 0 | AS90: =AH90+AL90+AM90+AO90+AN90 -> 900
B91: Travaux électriques, contrôle et Pronovo | C91: 1 | D91: Forfait | E91: =AB91 -> 1200 | F91: =C91*E91 -> 1200 | H91: 0 | I91: 0 | J91: =H91*$J$4 -> 0 | K91: 0 | L91: =H91*(1-$K91) -> 0 | M91: =I91*(1-$K91) -> 0 | N91: =J91*(1-$K91) -> 0 | O91: =(L91+M91+N91) -> 0 | P91: =O91*$P$4 -> 0 | Q91: =(O91+P91)*$Q$4 -> 0 | R91: =(O91+P91)*$R$4 -> 0 | S91: 0 | T91: =SUM(O91:S91) -> 0 | U91: 0 | V91: =V80 -> 1200 | W91: =W80 -> 0 | X91: =SUM(U91:W91) -> 1200 | Y91: 0 | Z91: =T91*$Z$4 -> 0 | AA91: 0 | AB91: =T91+X91+Y91+Z91+AA91 -> 1200 | AC91: =O91*$C91 -> 0 | AD91: =P91*$C91 -> 0 | AE91: =Q91*$C91 -> 0 | AF91: =R91*$C91 -> 0 | AG91: =S91*$C91 -> 0 | AH91: =T91*$C91 -> 0 | AI91: =U91*$C91 -> 0 | AJ91: =V91*$C91 -> 1200 | ... AO91: =AA91*$C91 -> 0 | AP91: =AM91+AK91 -> 0 | AQ91: =AM91+AL91+AH91 -> 1200 | AR91: =AO91+AN91 -> 0 | AS91: =AH91+AL91+AM91+AO91+AN91 -> 1200
A93: =A82+1 -> 18 | B93: Panneaux | C93: Puissance: | D93: =ROUNDUP((A93*465)/1000,2) -> 8.37 | F93: =SUM(F94:F103) -> 19265.336 | AC93: =+SUM(AC94:AC103) -> 7025.5875 | AD93: =+SUM(AD94:AD103) -> 0 | AE93: =+SUM(AE94:AE103) -> 0 | AF93: =+SUM(AF94:AF103) -> 140.51175 | AG93: =+SUM(AG94:AG103) -> 274.32938 | AH93: =+SUM(AH94:AH103) -> 7440.4286 | AI93: =+SUM(AI94:AI103) -> 4232 | AJ93: =+SUM(AJ94:AJ103) -> 1200 | ... AS93: =+SUM(AS94:AS103) -> 19265.336 | AT93: =IF(F93=AS93,"Matching","Not Matching") -> Matching | AU93: =SUM(AC93:AG93) -> 7440.4286 | AV93: =AU93/AS93 -> 0.38620809 | AW93: =AI93 -> 4232 | AX93: =AW93/AS93 -> 0.21966915 | AY93: =AJ93 -> 1200 | AZ93: =AY93/AS93 -> 0.062288038 | BA93: =AK93+AM93 -> 3474.8004 | BB93: =BA93/AS93 -> 0.18036542 | BC93: =AN93+AO93 -> 2918.1072 | BD93: =BC93/AS93 -> 0.15146931 | BE93: =IF((AU93+AW93+AY93+BA93+BC93)=AS93,"Matching","Not Matching") -> Matching | BF93: =AQ93 -> 16347.229 | BG93: =BF93/AS93 -> 0.84853069 | BH93: =AR93 -> 2918.1072 | BI93: =BH93/AS93 -> 0.15146931 | BJ93: =IF((BH93+BF93)=AS93,"Matching","Not Matching") -> Matching | BK93: =AS93*1.081 -> 20825.828 | BL93: =ROUND(BK93,-1) -> 20830 | BM93: =D93*380 -> 3180.6 | BN93: =BK93-BM93 -> 17645.228 | BO93: =BK93/D93 -> 2488.1515
B95: ="Panneau solaire "&G95 -> Panneau solaire JINKO JKM455N-54HL4R-V | C95: =A93 -> 18 | D95: U | E95: =AB95 -> 180.51476 | F95: =C95*E95 -> 3249.2658 | G95: =$G$7 -> JINKO JKM455N-54HL4R-V | H95: =H73 -> 52.4 | I95: =I73 -> 0 | J95: =H95*$J$4 -> 1.572 | K95: 0 | L95: =H95*(1-$K95) -> 52.4 | M95: =I95*(1-$K95) -> 0 | N95: =J95*(1-$K95) -> 1.572 | O95: =(L95+M95+N95) -> 53.972 | P95: =O95*$P$4 -> 0 | Q95: =(O95+P95)*$Q$4 -> 0 | R95: =(O95+P95)*$R$4 -> 1.07944 | S95: =(O95+P95)*$S$4 -> 2.6986 | T95: =SUM(O95:S95) -> 57.75004 | U95: =1*$U$4 -> 65 | V95: =V84 -> 0 | W95: =W84 -> 0 | X95: =SUM(U95:W95) -> 65 | Y95: =$Y$4/(1-$Y$4)*(T95+X95+Z95+AA95) -> 27.077215 | Z95: =T95*$Z$4 -> 14.43751 | AA95: =X95*$AA$4 -> 16.25 | AB95: =T95+X95+Y95+Z95+AA95 -> 180.51476 | AC95: =O95*$C95 -> 971.496 | AD95: =P95*$C95 -> 0 | AE95: =Q95*$C95 -> 0 | AF95: =R95*$C95 -> 19.42992 | AG95: =S95*$C95 -> 48.5748 | AH95: =T95*$C95 -> 1039.5007 | AI95: =U95*$C95 -> 1170 | AJ95: =V95*$C95 -> 0 | ... AO95: =AA95*$C95 -> 292.5 | AP95: =AM95+AK95 -> 487.38986 | AQ95: =AM95+AL95+AH95 -> 2696.8906 | AR95: =AO95+AN95 -> 552.37518 | AS95: =AH95+AL95+AM95+AO95+AN95 -> 3249.2658
B96: ="Onduleur Huawei "&G96 -> Onduleur Huawei SUN2000-8K-MAP0 | C96: 1 | D96: U | E96: =AB96 -> 2390.6881 | F96: =C96*E96 -> 2390.6881 | G96: =$G$85 -> SUN2000-8K-MAP0 | H96: =$H$85 -> 1068.05 | I96: ='Financial Data'!$C$40 -> 251 | J96: =H96*$J$4 -> 32.0415 | K96: 0 | L96: =H96*(1-$K96) -> 1068.05 | M96: =I96*(1-$K96) -> 251 | N96: =J96*(1-$K96) -> 32.0415 | O96: =(L96+M96+N96) -> 1351.0915 | P96: =O96*$P$4 -> 0 | Q96: =(O96+P96)*$Q$4 -> 0 | R96: =(O96+P96)*$R$4 -> 27.02183 | S96: =(O96+P96)*$S$4 -> 67.554575 | T96: =SUM(O96:S96) -> 1445.6679 | U96: =2*$U$5 -> 180 | V96: =V85 -> 0 | W96: =W85 -> 0 | X96: =SUM(U96:W96) -> 180 | Y96: =$Y$4/(1-$Y$4)*(T96+X96+Z96+AA96) -> 358.60321 | Z96: =T96*$Z$4 -> 361.41698 | AA96: =X96*$AA$4 -> 45 | AB96: =T96+X96+Y96+Z96+AA96 -> 2390.6881 | AC96: =O96*$C96 -> 1351.0915 | AD96: =P96*$C96 -> 0 | AE96: =Q96*$C96 -> 0 | AF96: =R96*$C96 -> 27.02183 | AG96: =S96*$C96 -> 67.554575 | AH96: =T96*$C96 -> 1445.6679 | AI96: =U96*$C96 -> 180 | AJ96: =V96*$C96 -> 0 | ... AO96: =AA96*$C96 -> 45 | AP96: =AM96+AK96 -> 358.60321 | AQ96: =AM96+AL96+AH96 -> 1984.2711 | AR96: =AO96+AN96 -> 406.41698 | AS96: =AH96+AL96+AM96+AO96+AN96 -> 2390.6881
B97: Optimiseurs et accessoires | C97: 1 | D97: Forfait | E97: =AB97 -> 1489.1912 | F97: =C97*E97 -> 1489.1912 | H97: =$H$86 -> 300 | I97: ='Financial Data'!$C$41*C95 -> 486 | J97: =H97*$J$4 -> 9 | K97: 0 | L97: =H97*(1-$K97) -> 300 | M97: =I97*(1-$K97) -> 486 | N97: =J97*(1-$K97) -> 9 | O97: =(L97+M97+N97) -> 795 | P97: =O97*$P$4 -> 0 | Q97: =(O97+P97)*$Q$4 -> 0 | R97: =(O97+P97)*$R$4 -> 15.9 | S97: =(O97+P97)*$S$4 -> 39.75 | T97: =SUM(O97:S97) -> 850.65 | U97: =(C95/10)*$U$5 -> 162 | V97: =V86 -> 0 | W97: =W86 -> 0 | X97: =SUM(U97:W97) -> 162 | Y97: =$Y$4/(1-$Y$4)*(T97+X97+Z97+AA97) -> 223.37868 | Z97: =T97*$Z$4 -> 212.6625 | AA97: =X97*$AA$4 -> 40.5 | AB97: =T97+X97+Y97+Z97+AA97 -> 1489.1912 | AC97: =O97*$C97 -> 795 | AD97: =P97*$C97 -> 0 | AE97: =Q97*$C97 -> 0 | AF97: =R97*$C97 -> 15.9 | AG97: =S97*$C97 -> 39.75 | AH97: =T97*$C97 -> 850.65 | AI97: =U97*$C97 -> 162 | AJ97: =V97*$C97 -> 0 | ... AO97: =AA97*$C97 -> 40.5 | AP97: =AM97+AK97 -> 223.37868 | AQ97: =AM97+AL97+AH97 -> 1236.0287 | AR97: =AO97+AN97 -> 253.1625 | AS97: =AH97+AL97+AM97+AO97+AN97 -> 1489.1912
B98: Système de montage sur tuile | C98: =A93 -> 18 | D98: U | E98: =AB98 -> 257.66176 | F98: =C98*E98 -> 4637.9118 | H98: =$H$87 -> 100 | I98: 0 | J98: =H98*$J$4 -> 3 | K98: 0 | L98: =H98*(1-$K98) -> 100 | M98: =I98*(1-$K98) -> 0 | N98: =J98*(1-$K98) -> 3 | O98: =(L98+M98+N98) -> 103 | P98: =O98*$P$4 -> 0 | Q98: =(O98+P98)*$Q$4 -> 0 | R98: =(O98+P98)*$R$4 -> 2.06 | S98: =(O98+P98)*$S$4 -> 5.15 | T98: =SUM(O98:S98) -> 110.21 | U98: =1*$U$4 -> 65 | V98: =V87 -> 0 | W98: =W87 -> 0 | X98: =SUM(U98:W98) -> 65 | Y98: =$Y$4/(1-$Y$4)*(T98+X98+Z98+AA98) -> 38.649265 | Z98: =T98*$Z$4 -> 27.5525 | AA98: =X98*$AA$4 -> 16.25 | AB98: =T98+X98+Y98+Z98+AA98 -> 257.66176 | AC98: =O98*$C98 -> 1854 | AD98: =P98*$C98 -> 0 | AE98: =Q98*$C98 -> 0 | AF98: =R98*$C98 -> 37.08 | AG98: =S98*$C98 -> 92.7 | AH98: =T98*$C98 -> 1983.78 | AI98: =U98*$C98 -> 1170 | AJ98: =V98*$C98 -> 0 | ... AO98: =AA98*$C98 -> 292.5 | AP98: =AM98+AK98 -> 695.68676 | AQ98: =AM98+AL98+AH98 -> 3849.4668 | AR98: =AO98+AN98 -> 788.445 | AS98: =AH98+AL98+AM98+AO98+AN98 -> 4637.9118
B99: Raccordement AC | C99: 1 | D99: Forfait | E99: =AB99 -> 3089.7794 | F99: =C99*E99 -> 3089.7794 | H99: =$H$88 -> 500 | I99: =I88 -> 0 | J99: =H99*$J$4 -> 15 | K99: 0 | L99: =H99*(1-$K99) -> 500 | M99: =I99*(1-$K99) -> 0 | N99: =J99*(1-$K99) -> 15 | O99: =(L99+M99+N99) -> 515 | P99: =O99*$P$4 -> 0 | Q99: =(O99+P99)*$Q$4 -> 0 | R99: =(O99+P99)*$R$4 -> 10.3 | S99: =(O99+P99)*$S$4 -> 25.75 | T99: =SUM(O99:S99) -> 551.05 | U99: =5*$U$5+600+500 -> 1550 | V99: =V88 -> 0 | W99: =W88 -> 0 | X99: =SUM(U99:W99) -> 1550 | Y99: =$Y$4/(1-$Y$4)*(T99+X99+Z99+AA99) -> 463.46691 | Z99: =T99*$Z$4 -> 137.7625 | AA99: =X99*$AA$4 -> 387.5 | AB99: =T99+X99+Y99+Z99+AA99 -> 3089.7794 | AC99: =O99*$C99 -> 515 | AD99: =P99*$C99 -> 0 | AE99: =Q99*$C99 -> 0 | AF99: =R99*$C99 -> 10.3 | AG99: =S99*$C99 -> 25.75 | AH99: =T99*$C99 -> 551.05 | AI99: =U99*$C99 -> 1550 | AJ99: =V99*$C99 -> 0 | ... AO99: =AA99*$C99 -> 387.5 | AP99: =AM99+AK99 -> 463.46691 | AQ99: =AM99+AL99+AH99 -> 2564.5169 | AR99: =AO99+AN99 -> 525.2625 | AS99: =AH99+AL99+AM99+AO99+AN99 -> 3089.7794
B100: Echafaudage jusqu'à 6m de hauteur | C100: 1 | D100: Forfait | E100: =AB100 -> 2308.5 | F100: =C100*E100 -> 2308.5 | H100: =$H$89 -> 1300 | I100: =$I$89 -> 200 | J100: =H100*$J$4 -> 39 | K100: 0 | L100: =H100*(1-$K100) -> 1300 | M100: =I100*(1-$K100) -> 200 | N100: =J100*(1-$K100) -> 39 | O100: =(L100+M100+N100) -> 1539 | P100: =O100*$P$4 -> 0 | Q100: =(O100+P100)*$Q$4 -> 0 | R100: =(O100+P100)*$R$4 -> 30.78 | S100: 0 | T100: =SUM(O100:S100) -> 1569.78 | U100: 0 | V100: =V89 -> 0 | W100: =W89 -> 0 | X100: =SUM(U100:W100) -> 0 | Y100: =$Y$4/(1-$Y$4)*(T100+X100+Z100+AA100) -> 346.275 | Z100: =T100*$Z$4 -> 392.445 | AA100: =X100*$AA$4 -> 0 | AB100: =T100+X100+Y100+Z100+AA100 -> 2308.5 | AC100: =O100*$C100 -> 1539 | AD100: =P100*$C100 -> 0 | AE100: =Q100*$C100 -> 0 | AF100: =R100*$C100 -> 30.78 | AG100: =S100*$C100 -> 0 | AH100: =T100*$C100 -> 1569.78 | AI100: =U100*$C100 -> 0 | AJ100: =V100*$C100 -> 0 | ... AO100: =AA100*$C100 -> 0 | AP100: =AM100+AK100 -> 346.275 | AQ100: =AM100+AL100+AH100 -> 1916.055 | AR100: =AO100+AN100 -> 392.445 | AS100: =AH100+AL100+AM100+AO100+AN100 -> 2308.5
B101: Travaux administratifs | C101: 1 | D101: Forfait | E101: =AB101 -> 900 | F101: =C101*E101 -> 900 | H101: 0 | I101: 0 | J101: =H101*$J$4 -> 0 | K101: 0 | L101: =H101*(1-$K101) -> 0 | M101: =I101*(1-$K101) -> 0 | N101: =J101*(1-$K101) -> 0 | O101: =(L101+M101+N101) -> 0 | P101: =O101*$P$4 -> 0 | Q101: =(O101+P101)*$Q$4 -> 0 | R101: =(O101+P101)*$R$4 -> 0 | S101: 0 | T101: =SUM(O101:S101) -> 0 | U101: 0 | V101: =V90 -> 0 | W101: =W90 -> 900 | X101: =SUM(U101:W101) -> 900 | Y101: 0 | Z101: =T101*$Z$4 -> 0 | AA101: 0 | AB101: =T101+X101+Y101+Z101+AA101 -> 900 | AC101: =O101*$C101 -> 0 | AD101: =P101*$C101 -> 0 | AE101: =Q101*$C101 -> 0 | AF101: =R101*$C101 -> 0 | AG101: =S101*$C101 -> 0 | AH101: =T101*$C101 -> 0 | AI101: =U101*$C101 -> 0 | AJ101: =V101*$C101 -> 0 | ... AO101: =AA101*$C101 -> 0 | AP101: =AM101+AK101 -> 900 | AQ101: =AM101+AL101+AH101 -> 900 | AR101: =AO101+AN101 -> 0 | AS101: =AH101+AL101+AM101+AO101+AN101 -> 900
B102: Travaux électriques, contrôle et Pronovo | C102: 1 | D102: Forfait | E102: =AB102 -> 1200 | F102: =C102*E102 -> 1200 | H102: 0 | I102: 0 | J102: =H102*$J$4 -> 0 | K102: 0 | L102: =H102*(1-$K102) -> 0 | M102: =I102*(1-$K102) -> 0 | N102: =J102*(1-$K102) -> 0 | O102: =(L102+M102+N102) -> 0 | P102: =O102*$P$4 -> 0 | Q102: =(O102+P102)*$Q$4 -> 0 | R102: =(O102+P102)*$R$4 -> 0 | S102: 0 | T102: =SUM(O102:S102) -> 0 | U102: 0 | V102: =V91 -> 1200 | W102: =W91 -> 0 | X102: =SUM(U102:W102) -> 1200 | Y102: 0 | Z102: =T102*$Z$4 -> 0 | AA102: 0 | AB102: =T102+X102+Y102+Z102+AA102 -> 1200 | AC102: =O102*$C102 -> 0 | AD102: =P102*$C102 -> 0 | AE102: =Q102*$C102 -> 0 | AF102: =R102*$C102 -> 0 | AG102: =S102*$C102 -> 0 | AH102: =T102*$C102 -> 0 | AI102: =U102*$C102 -> 0 | AJ102: =V102*$C102 -> 1200 | ... AO102: =AA102*$C102 -> 0 | AP102: =AM102+AK102 -> 0 | AQ102: =AM102+AL102+AH102 -> 1200 | AR102: =AO102+AN102 -> 0 | AS102: =AH102+AL102+AM102+AO102+AN102 -> 1200
A104: =A93+1 -> 19 | B104: Panneaux | C104: Puissance: | D104: =ROUNDUP((A104*465)/1000,2) -> 8.84 | F104: =SUM(F105:F114) -> 19759.233 | AC104: =+SUM(AC105:AC114) -> 7209.5595 | AD104: =+SUM(AD105:AD114) -> 0 | AE104: =+SUM(AE105:AE114) -> 0 | AF104: =+SUM(AF105:AF114) -> 144.19119 | AG104: =+SUM(AG105:AG114) -> 283.52798 | AH104: =+SUM(AH105:AH114) -> 7637.2787 | AI104: =+SUM(AI105:AI114) -> 4371 | AJ104: =+SUM(AJ105:AJ114) -> 1200 | ... AS104: =+SUM(AS105:AS114) -> 19759.233 | AT104: =IF(F104=AS104,"Matching","Not Matching") -> Matching | AU104: =SUM(AC104:AG104) -> 7637.2787 | AV104: =AU104/AS104 -> 0.38651695 | AW104: =AI104 -> 4371 | AX104: =AW104/AS104 -> 0.22121304 | AY104: =AJ104 -> 1200 | AZ104: =AY104/AS104 -> 0.060731101 | BA104: =AK104+AM104 -> 3548.885 | BB104: =BA104/AS104 -> 0.17960641 | BC104: =AN104+AO104 -> 3002.0697 | BD104: =BC104/AS104 -> 0.1519325 | BE104: =IF((AU104+AW104+AY104+BA104+BC104)=AS104,"Matching","Not Matching") -> Matching | BF104: =AQ104 -> 16757.164 | BG104: =BF104/AS104 -> 0.8480675 | BH104: =AR104 -> 3002.0697 | BI104: =BH104/AS104 -> 0.1519325 | BJ104: =IF((BH104+BF104)=AS104,"Matching","Not Matching") -> Matching | BK104: =AS104*1.081 -> 21359.731 | BL104: =ROUND(BK104,-1) -> 21360 | BM104: =D104*380 -> 3359.2 | BN104: =BK104-BM104 -> 18000.531 | BO104: =BK104/D104 -> 2416.2592
B106: ="Panneau solaire "&G106 -> Panneau solaire JINKO JKM455N-54HL4R-V | C106: =A104 -> 19 | D106: U | E106: =AB106 -> 180.51476 | F106: =C106*E106 -> 3429.7805 | G106: =$G$7 -> JINKO JKM455N-54HL4R-V | H106: =H73 -> 52.4 | I106: =I73 -> 0 | J106: =H106*$J$4 -> 1.572 | K106: 0 | L106: =H106*(1-$K106) -> 52.4 | M106: =I106*(1-$K106) -> 0 | N106: =J106*(1-$K106) -> 1.572 | O106: =(L106+M106+N106) -> 53.972 | P106: =O106*$P$4 -> 0 | Q106: =(O106+P106)*$Q$4 -> 0 | R106: =(O106+P106)*$R$4 -> 1.07944 | S106: =(O106+P106)*$S$4 -> 2.6986 | T106: =SUM(O106:S106) -> 57.75004 | U106: =1*$U$4 -> 65 | V106: =V95 -> 0 | W106: =W95 -> 0 | X106: =SUM(U106:W106) -> 65 | Y106: =$Y$4/(1-$Y$4)*(T106+X106+Z106+AA106) -> 27.077215 | Z106: =T106*$Z$4 -> 14.43751 | AA106: =X106*$AA$4 -> 16.25 | AB106: =T106+X106+Y106+Z106+AA106 -> 180.51476 | AC106: =O106*$C106 -> 1025.468 | AD106: =P106*$C106 -> 0 | AE106: =Q106*$C106 -> 0 | AF106: =R106*$C106 -> 20.50936 | AG106: =S106*$C106 -> 51.2734 | AH106: =T106*$C106 -> 1097.2508 | AI106: =U106*$C106 -> 1235 | AJ106: =V106*$C106 -> 0 | ... AO106: =AA106*$C106 -> 308.75 | AP106: =AM106+AK106 -> 514.46708 | AQ106: =AM106+AL106+AH106 -> 2846.7178 | AR106: =AO106+AN106 -> 583.06269 | AS106: =AH106+AL106+AM106+AO106+AN106 -> 3429.7805
B107: ="Onduleur Huawei "&G107 -> Onduleur Huawei SUN2000-8K-MAP0 | C107: 1 | D107: U | E107: =AB107 -> 2390.6881 | F107: =C107*E107 -> 2390.6881 | G107: =$G$85 -> SUN2000-8K-MAP0 | H107: =$H$85 -> 1068.05 | I107: ='Financial Data'!$C$40 -> 251 | J107: =H107*$J$4 -> 32.0415 | K107: 0 | L107: =H107*(1-$K107) -> 1068.05 | M107: =I107*(1-$K107) -> 251 | N107: =J107*(1-$K107) -> 32.0415 | O107: =(L107+M107+N107) -> 1351.0915 | P107: =O107*$P$4 -> 0 | Q107: =(O107+P107)*$Q$4 -> 0 | R107: =(O107+P107)*$R$4 -> 27.02183 | S107: =(O107+P107)*$S$4 -> 67.554575 | T107: =SUM(O107:S107) -> 1445.6679 | U107: =2*$U$5 -> 180 | V107: =V96 -> 0 | W107: =W96 -> 0 | X107: =SUM(U107:W107) -> 180 | Y107: =$Y$4/(1-$Y$4)*(T107+X107+Z107+AA107) -> 358.60321 | Z107: =T107*$Z$4 -> 361.41698 | AA107: =X107*$AA$4 -> 45 | AB107: =T107+X107+Y107+Z107+AA107 -> 2390.6881 | AC107: =O107*$C107 -> 1351.0915 | AD107: =P107*$C107 -> 0 | AE107: =Q107*$C107 -> 0 | AF107: =R107*$C107 -> 27.02183 | AG107: =S107*$C107 -> 67.554575 | AH107: =T107*$C107 -> 1445.6679 | AI107: =U107*$C107 -> 180 | AJ107: =V107*$C107 -> 0 | ... AO107: =AA107*$C107 -> 45 | AP107: =AM107+AK107 -> 358.60321 | AQ107: =AM107+AL107+AH107 -> 1984.2711 | AR107: =AO107+AN107 -> 406.41698 | AS107: =AH107+AL107+AM107+AO107+AN107 -> 2390.6881
B108: Optimiseurs et accessoires | C108: 1 | D108: Forfait | E108: =AB108 -> 1544.9118 | F108: =C108*E108 -> 1544.9118 | H108: =$H$86 -> 300 | I108: ='Financial Data'!$C$41*C106 -> 513 | J108: =H108*$J$4 -> 9 | K108: 0 | L108: =H108*(1-$K108) -> 300 | M108: =I108*(1-$K108) -> 513 | N108: =J108*(1-$K108) -> 9 | O108: =(L108+M108+N108) -> 822 | P108: =O108*$P$4 -> 0 | Q108: =(O108+P108)*$Q$4 -> 0 | R108: =(O108+P108)*$R$4 -> 16.44 | S108: =(O108+P108)*$S$4 -> 41.1 | T108: =SUM(O108:S108) -> 879.54 | U108: =(C106/10)*$U$5 -> 171 | V108: =V97 -> 0 | W108: =W97 -> 0 | X108: =SUM(U108:W108) -> 171 | Y108: =$Y$4/(1-$Y$4)*(T108+X108+Z108+AA108) -> 231.73676 | Z108: =T108*$Z$4 -> 219.885 | AA108: =X108*$AA$4 -> 42.75 | AB108: =T108+X108+Y108+Z108+AA108 -> 1544.9118 | AC108: =O108*$C108 -> 822 | AD108: =P108*$C108 -> 0 | AE108: =Q108*$C108 -> 0 | AF108: =R108*$C108 -> 16.44 | AG108: =S108*$C108 -> 41.1 | AH108: =T108*$C108 -> 879.54 | AI108: =U108*$C108 -> 171 | AJ108: =V108*$C108 -> 0 | ... AO108: =AA108*$C108 -> 42.75 | AP108: =AM108+AK108 -> 231.73676 | AQ108: =AM108+AL108+AH108 -> 1282.2768 | AR108: =AO108+AN108 -> 262.635 | AS108: =AH108+AL108+AM108+AO108+AN108 -> 1544.9118
B109: Système de montage sur tuile | C109: =A104 -> 19 | D109: U | E109: =AB109 -> 257.66176 | F109: =C109*E109 -> 4895.5735 | H109: =$H$87 -> 100 | I109: 0 | J109: =H109*$J$4 -> 3 | K109: 0 | L109: =H109*(1-$K109) -> 100 | M109: =I109*(1-$K109) -> 0 | N109: =J109*(1-$K109) -> 3 | O109: =(L109+M109+N109) -> 103 | P109: =O109*$P$4 -> 0 | Q109: =(O109+P109)*$Q$4 -> 0 | R109: =(O109+P109)*$R$4 -> 2.06 | S109: =(O109+P109)*$S$4 -> 5.15 | T109: =SUM(O109:S109) -> 110.21 | U109: =1*$U$4 -> 65 | V109: =V98 -> 0 | W109: =W98 -> 0 | X109: =SUM(U109:W109) -> 65 | Y109: =$Y$4/(1-$Y$4)*(T109+X109+Z109+AA109) -> 38.649265 | Z109: =T109*$Z$4 -> 27.5525 | AA109: =X109*$AA$4 -> 16.25 | AB109: =T109+X109+Y109+Z109+AA109 -> 257.66176 | AC109: =O109*$C109 -> 1957 | AD109: =P109*$C109 -> 0 | AE109: =Q109*$C109 -> 0 | AF109: =R109*$C109 -> 39.14 | AG109: =S109*$C109 -> 97.85 | AH109: =T109*$C109 -> 2093.99 | AI109: =U109*$C109 -> 1235 | AJ109: =V109*$C109 -> 0 | ... AO109: =AA109*$C109 -> 308.75 | AP109: =AM109+AK109 -> 734.33603 | AQ109: =AM109+AL109+AH109 -> 4063.326 | AR109: =AO109+AN109 -> 832.2475 | AS109: =AH109+AL109+AM109+AO109+AN109 -> 4895.5735
B110: Raccordement AC | C110: 1 | D110: Forfait | E110: =AB110 -> 3089.7794 | F110: =C110*E110 -> 3089.7794 | H110: =$H$88 -> 500 | I110: =I99 -> 0 | J110: =H110*$J$4 -> 15 | K110: 0 | L110: =H110*(1-$K110) -> 500 | M110: =I110*(1-$K110) -> 0 | N110: =J110*(1-$K110) -> 15 | O110: =(L110+M110+N110) -> 515 | P110: =O110*$P$4 -> 0 | Q110: =(O110+P110)*$Q$4 -> 0 | R110: =(O110+P110)*$R$4 -> 10.3 | S110: =(O110+P110)*$S$4 -> 25.75 | T110: =SUM(O110:S110) -> 551.05 | U110: =5*$U$5+600+500 -> 1550 | V110: =V99 -> 0 | W110: =W99 -> 0 | X110: =SUM(U110:W110) -> 1550 | Y110: =$Y$4/(1-$Y$4)*(T110+X110+Z110+AA110) -> 463.46691 | Z110: =T110*$Z$4 -> 137.7625 | AA110: =X110*$AA$4 -> 387.5 | AB110: =T110+X110+Y110+Z110+AA110 -> 3089.7794 | AC110: =O110*$C110 -> 515 | AD110: =P110*$C110 -> 0 | AE110: =Q110*$C110 -> 0 | AF110: =R110*$C110 -> 10.3 | AG110: =S110*$C110 -> 25.75 | AH110: =T110*$C110 -> 551.05 | AI110: =U110*$C110 -> 1550 | AJ110: =V110*$C110 -> 0 | ... AO110: =AA110*$C110 -> 387.5 | AP110: =AM110+AK110 -> 463.46691 | AQ110: =AM110+AL110+AH110 -> 2564.5169 | AR110: =AO110+AN110 -> 525.2625 | AS110: =AH110+AL110+AM110+AO110+AN110 -> 3089.7794
B111: Echafaudage jusqu'à 6m de hauteur | C111: 1 | D111: Forfait | E111: =AB111 -> 2308.5 | F111: =C111*E111 -> 2308.5 | H111: =$H$89 -> 1300 | I111: =$I$89 -> 200 | J111: =H111*$J$4 -> 39 | K111: 0 | L111: =H111*(1-$K111) -> 1300 | M111: =I111*(1-$K111) -> 200 | N111: =J111*(1-$K111) -> 39 | O111: =(L111+M111+N111) -> 1539 | P111: =O111*$P$4 -> 0 | Q111: =(O111+P111)*$Q$4 -> 0 | R111: =(O111+P111)*$R$4 -> 30.78 | S111: 0 | T111: =SUM(O111:S111) -> 1569.78 | U111: 0 | V111: =V100 -> 0 | W111: =W100 -> 0 | X111: =SUM(U111:W111) -> 0 | Y111: =$Y$4/(1-$Y$4)*(T111+X111+Z111+AA111) -> 346.275 | Z111: =T111*$Z$4 -> 392.445 | AA111: =X111*$AA$4 -> 0 | AB111: =T111+X111+Y111+Z111+AA111 -> 2308.5 | AC111: =O111*$C111 -> 1539 | AD111: =P111*$C111 -> 0 | AE111: =Q111*$C111 -> 0 | AF111: =R111*$C111 -> 30.78 | AG111: =S111*$C111 -> 0 | AH111: =T111*$C111 -> 1569.78 | AI111: =U111*$C111 -> 0 | AJ111: =V111*$C111 -> 0 | ... AO111: =AA111*$C111 -> 0 | AP111: =AM111+AK111 -> 346.275 | AQ111: =AM111+AL111+AH111 -> 1916.055 | AR111: =AO111+AN111 -> 392.445 | AS111: =AH111+AL111+AM111+AO111+AN111 -> 2308.5
B112: Travaux administratifs | C112: 1 | D112: Forfait | E112: =AB112 -> 900 | F112: =C112*E112 -> 900 | H112: 0 | I112: 0 | J112: =H112*$J$4 -> 0 | K112: 0 | L112: =H112*(1-$K112) -> 0 | M112: =I112*(1-$K112) -> 0 | N112: =J112*(1-$K112) -> 0 | O112: =(L112+M112+N112) -> 0 | P112: =O112*$P$4 -> 0 | Q112: =(O112+P112)*$Q$4 -> 0 | R112: =(O112+P112)*$R$4 -> 0 | S112: 0 | T112: =SUM(O112:S112) -> 0 | U112: 0 | V112: =V101 -> 0 | W112: =W101 -> 900 | X112: =SUM(U112:W112) -> 900 | Y112: 0 | Z112: =T112*$Z$4 -> 0 | AA112: 0 | AB112: =T112+X112+Y112+Z112+AA112 -> 900 | AC112: =O112*$C112 -> 0 | AD112: =P112*$C112 -> 0 | AE112: =Q112*$C112 -> 0 | AF112: =R112*$C112 -> 0 | AG112: =S112*$C112 -> 0 | AH112: =T112*$C112 -> 0 | AI112: =U112*$C112 -> 0 | AJ112: =V112*$C112 -> 0 | ... AO112: =AA112*$C112 -> 0 | AP112: =AM112+AK112 -> 900 | AQ112: =AM112+AL112+AH112 -> 900 | AR112: =AO112+AN112 -> 0 | AS112: =AH112+AL112+AM112+AO112+AN112 -> 900
B113: Travaux électriques, contrôle et Pronovo | C113: 1 | D113: Forfait | E113: =AB113 -> 1200 | F113: =C113*E113 -> 1200 | H113: 0 | I113: 0 | J113: =H113*$J$4 -> 0 | K113: 0 | L113: =H113*(1-$K113) -> 0 | M113: =I113*(1-$K113) -> 0 | N113: =J113*(1-$K113) -> 0 | O113: =(L113+M113+N113) -> 0 | P113: =O113*$P$4 -> 0 | Q113: =(O113+P113)*$Q$4 -> 0 | R113: =(O113+P113)*$R$4 -> 0 | S113: 0 | T113: =SUM(O113:S113) -> 0 | U113: 0 | V113: =V102 -> 1200 | W113: =W102 -> 0 | X113: =SUM(U113:W113) -> 1200 | Y113: 0 | Z113: =T113*$Z$4 -> 0 | AA113: 0 | AB113: =T113+X113+Y113+Z113+AA113 -> 1200 | AC113: =O113*$C113 -> 0 | AD113: =P113*$C113 -> 0 | AE113: =Q113*$C113 -> 0 | AF113: =R113*$C113 -> 0 | AG113: =S113*$C113 -> 0 | AH113: =T113*$C113 -> 0 | AI113: =U113*$C113 -> 0 | AJ113: =V113*$C113 -> 1200 | ... AO113: =AA113*$C113 -> 0 | AP113: =AM113+AK113 -> 0 | AQ113: =AM113+AL113+AH113 -> 1200 | AR113: =AO113+AN113 -> 0 | AS113: =AH113+AL113+AM113+AO113+AN113 -> 1200
A115: =A104+1 -> 20 | B115: Panneaux | C115: Puissance: | D115: =ROUNDUP((A115*465)/1000,2) -> 9.3 | F115: =SUM(F116:F125) -> 20253.13 | AC115: =+SUM(AC116:AC125) -> 7393.5315 | AD115: =+SUM(AD116:AD125) -> 0 | AE115: =+SUM(AE116:AE125) -> 0 | AF115: =+SUM(AF116:AF125) -> 147.87063 | AG115: =+SUM(AG116:AG125) -> 292.72658 | AH115: =+SUM(AH116:AH125) -> 7834.1287 | AI115: =+SUM(AI116:AI125) -> 4510 | AJ115: =+SUM(AJ116:AJ125) -> 1200 | ... AS115: =+SUM(AS116:AS125) -> 20253.13 | AT115: =IF(F115=AS115,"Matching","Not Matching") -> Matching | AU115: =SUM(AC115:AG115) -> 7834.1287 | AV115: =AU115/AS115 -> 0.38681076 | AW115: =AI115 -> 4510 | AX115: =AW115/AS115 -> 0.22268163 | AY115: =AJ115 -> 1200 | AZ115: =AY115/AS115 -> 0.0592501 | BA115: =AK115+AM115 -> 3622.9696 | BB115: =BA115/AS115 -> 0.17888442 | BC115: =AN115+AO115 -> 3086.0322 | BD115: =BC115/AS115 -> 0.1523731 | BE115: =IF((AU115+AW115+AY115+BA115+BC115)=AS115,"Matching","Not Matching") -> Matching | BF115: =AQ115 -> 17167.098 | BG115: =BF115/AS115 -> 0.8476269 | BH115: =AR115 -> 3086.0322 | BI115: =BH115/AS115 -> 0.1523731 | BJ115: =IF((BH115+BF115)=AS115,"Matching","Not Matching") -> Matching | BK115: =AS115*1.081 -> 21893.634 | BL115: =ROUND(BK115,-1) -> 21890 | BM115: =D115*380 -> 3534 | BN115: =BK115-BM115 -> 18359.634 | BO115: =BK115/D115 -> 2354.1542
B117: ="Panneau solaire "&G117 -> Panneau solaire JINKO JKM455N-54HL4R-V | C117: =A115 -> 20 | D117: U | E117: =AB117 -> 180.51476 | F117: =C117*E117 -> 3610.2953 | G117: =$G$7 -> JINKO JKM455N-54HL4R-V | H117: =H73 -> 52.4 | I117: =I73 -> 0 | J117: =H117*$J$4 -> 1.572 | K117: 0 | L117: =H117*(1-$K117) -> 52.4 | M117: =I117*(1-$K117) -> 0 | N117: =J117*(1-$K117) -> 1.572 | O117: =(L117+M117+N117) -> 53.972 | P117: =O117*$P$4 -> 0 | Q117: =(O117+P117)*$Q$4 -> 0 | R117: =(O117+P117)*$R$4 -> 1.07944 | S117: =(O117+P117)*$S$4 -> 2.6986 | T117: =SUM(O117:S117) -> 57.75004 | U117: =1*$U$4 -> 65 | V117: =V106 -> 0 | W117: =W106 -> 0 | X117: =SUM(U117:W117) -> 65 | Y117: =$Y$4/(1-$Y$4)*(T117+X117+Z117+AA117) -> 27.077215 | Z117: =T117*$Z$4 -> 14.43751 | AA117: =X117*$AA$4 -> 16.25 | AB117: =T117+X117+Y117+Z117+AA117 -> 180.51476 | AC117: =O117*$C117 -> 1079.44 | AD117: =P117*$C117 -> 0 | AE117: =Q117*$C117 -> 0 | AF117: =R117*$C117 -> 21.5888 | AG117: =S117*$C117 -> 53.972 | AH117: =T117*$C117 -> 1155.0008 | AI117: =U117*$C117 -> 1300 | AJ117: =V117*$C117 -> 0 | ... AO117: =AA117*$C117 -> 325 | AP117: =AM117+AK117 -> 541.54429 | AQ117: =AM117+AL117+AH117 -> 2996.5451 | AR117: =AO117+AN117 -> 613.7502 | AS117: =AH117+AL117+AM117+AO117+AN117 -> 3610.2953
B118: ="Onduleur Huawei "&G118 -> Onduleur Huawei SUN2000-8K-MAP0 | C118: 1 | D118: U | E118: =AB118 -> 2390.6881 | F118: =C118*E118 -> 2390.6881 | G118: =$G$85 -> SUN2000-8K-MAP0 | H118: =$H$85 -> 1068.05 | I118: ='Financial Data'!$C$40 -> 251 | J118: =H118*$J$4 -> 32.0415 | K118: 0 | L118: =H118*(1-$K118) -> 1068.05 | M118: =I118*(1-$K118) -> 251 | N118: =J118*(1-$K118) -> 32.0415 | O118: =(L118+M118+N118) -> 1351.0915 | P118: =O118*$P$4 -> 0 | Q118: =(O118+P118)*$Q$4 -> 0 | R118: =(O118+P118)*$R$4 -> 27.02183 | S118: =(O118+P118)*$S$4 -> 67.554575 | T118: =SUM(O118:S118) -> 1445.6679 | U118: =2*$U$5 -> 180 | V118: =V107 -> 0 | W118: =W107 -> 0 | X118: =SUM(U118:W118) -> 180 | Y118: =$Y$4/(1-$Y$4)*(T118+X118+Z118+AA118) -> 358.60321 | Z118: =T118*$Z$4 -> 361.41698 | AA118: =X118*$AA$4 -> 45 | AB118: =T118+X118+Y118+Z118+AA118 -> 2390.6881 | AC118: =O118*$C118 -> 1351.0915 | AD118: =P118*$C118 -> 0 | AE118: =Q118*$C118 -> 0 | AF118: =R118*$C118 -> 27.02183 | AG118: =S118*$C118 -> 67.554575 | AH118: =T118*$C118 -> 1445.6679 | AI118: =U118*$C118 -> 180 | AJ118: =V118*$C118 -> 0 | ... AO118: =AA118*$C118 -> 45 | AP118: =AM118+AK118 -> 358.60321 | AQ118: =AM118+AL118+AH118 -> 1984.2711 | AR118: =AO118+AN118 -> 406.41698 | AS118: =AH118+AL118+AM118+AO118+AN118 -> 2390.6881
B119: Optimiseurs et accessoires | C119: 1 | D119: Forfait | E119: =AB119 -> 1600.6324 | F119: =C119*E119 -> 1600.6324 | H119: =$H$86 -> 300 | I119: ='Financial Data'!$C$41*C117 -> 540 | J119: =H119*$J$4 -> 9 | K119: 0 | L119: =H119*(1-$K119) -> 300 | M119: =I119*(1-$K119) -> 540 | N119: =J119*(1-$K119) -> 9 | O119: =(L119+M119+N119) -> 849 | P119: =O119*$P$4 -> 0 | Q119: =(O119+P119)*$Q$4 -> 0 | R119: =(O119+P119)*$R$4 -> 16.98 | S119: =(O119+P119)*$S$4 -> 42.45 | T119: =SUM(O119:S119) -> 908.43 | U119: =(C117/10)*$U$5 -> 180 | V119: =V108 -> 0 | W119: =W108 -> 0 | X119: =SUM(U119:W119) -> 180 | Y119: =$Y$4/(1-$Y$4)*(T119+X119+Z119+AA119) -> 240.09485 | Z119: =T119*$Z$4 -> 227.1075 | AA119: =X119*$AA$4 -> 45 | AB119: =T119+X119+Y119+Z119+AA119 -> 1600.6324 | AC119: =O119*$C119 -> 849 | AD119: =P119*$C119 -> 0 | AE119: =Q119*$C119 -> 0 | AF119: =R119*$C119 -> 16.98 | AG119: =S119*$C119 -> 42.45 | AH119: =T119*$C119 -> 908.43 | AI119: =U119*$C119 -> 180 | AJ119: =V119*$C119 -> 0 | ... AO119: =AA119*$C119 -> 45 | AP119: =AM119+AK119 -> 240.09485 | AQ119: =AM119+AL119+AH119 -> 1328.5249 | AR119: =AO119+AN119 -> 272.1075 | AS119: =AH119+AL119+AM119+AO119+AN119 -> 1600.6324
B120: Système de montage sur tuile | C120: =A115 -> 20 | D120: U | E120: =AB120 -> 257.66176 | F120: =C120*E120 -> 5153.2353 | H120: =$H$87 -> 100 | I120: 0 | J120: =H120*$J$4 -> 3 | K120: 0 | L120: =H120*(1-$K120) -> 100 | M120: =I120*(1-$K120) -> 0 | N120: =J120*(1-$K120) -> 3 | O120: =(L120+M120+N120) -> 103 | P120: =O120*$P$4 -> 0 | Q120: =(O120+P120)*$Q$4 -> 0 | R120: =(O120+P120)*$R$4 -> 2.06 | S120: =(O120+P120)*$S$4 -> 5.15 | T120: =SUM(O120:S120) -> 110.21 | U120: =1*$U$4 -> 65 | V120: =V109 -> 0 | W120: =W109 -> 0 | X120: =SUM(U120:W120) -> 65 | Y120: =$Y$4/(1-$Y$4)*(T120+X120+Z120+AA120) -> 38.649265 | Z120: =T120*$Z$4 -> 27.5525 | AA120: =X120*$AA$4 -> 16.25 | AB120: =T120+X120+Y120+Z120+AA120 -> 257.66176 | AC120: =O120*$C120 -> 2060 | AD120: =P120*$C120 -> 0 | AE120: =Q120*$C120 -> 0 | AF120: =R120*$C120 -> 41.2 | AG120: =S120*$C120 -> 103 | AH120: =T120*$C120 -> 2204.2 | AI120: =U120*$C120 -> 1300 | AJ120: =V120*$C120 -> 0 | ... AO120: =AA120*$C120 -> 325 | AP120: =AM120+AK120 -> 772.98529 | AQ120: =AM120+AL120+AH120 -> 4277.1853 | AR120: =AO120+AN120 -> 876.05 | AS120: =AH120+AL120+AM120+AO120+AN120 -> 5153.2353
B121: Raccordement AC | C121: 1 | D121: Forfait | E121: =AB121 -> 3089.7794 | F121: =C121*E121 -> 3089.7794 | H121: =$H$88 -> 500 | I121: =I110 -> 0 | J121: =H121*$J$4 -> 15 | K121: 0 | L121: =H121*(1-$K121) -> 500 | M121: =I121*(1-$K121) -> 0 | N121: =J121*(1-$K121) -> 15 | O121: =(L121+M121+N121) -> 515 | P121: =O121*$P$4 -> 0 | Q121: =(O121+P121)*$Q$4 -> 0 | R121: =(O121+P121)*$R$4 -> 10.3 | S121: =(O121+P121)*$S$4 -> 25.75 | T121: =SUM(O121:S121) -> 551.05 | U121: =5*$U$5+600+500 -> 1550 | V121: =V110 -> 0 | W121: =W110 -> 0 | X121: =SUM(U121:W121) -> 1550 | Y121: =$Y$4/(1-$Y$4)*(T121+X121+Z121+AA121) -> 463.46691 | Z121: =T121*$Z$4 -> 137.7625 | AA121: =X121*$AA$4 -> 387.5 | AB121: =T121+X121+Y121+Z121+AA121 -> 3089.7794 | AC121: =O121*$C121 -> 515 | AD121: =P121*$C121 -> 0 | AE121: =Q121*$C121 -> 0 | AF121: =R121*$C121 -> 10.3 | AG121: =S121*$C121 -> 25.75 | AH121: =T121*$C121 -> 551.05 | AI121: =U121*$C121 -> 1550 | AJ121: =V121*$C121 -> 0 | ... AO121: =AA121*$C121 -> 387.5 | AP121: =AM121+AK121 -> 463.46691 | AQ121: =AM121+AL121+AH121 -> 2564.5169 | AR121: =AO121+AN121 -> 525.2625 | AS121: =AH121+AL121+AM121+AO121+AN121 -> 3089.7794
...

Sheet Fronius-Hybrid-10 to 30P
A1: N° | B1: DESCRIPTION | C1: QUANTITE | D1: UNITE DE MESURE | E1: PRIX UNITAIRE | F1: PRIX TOTAL | H1: Calcul Matériel | O1: Approvisionnement | U1: Construction | Y1: Sales | Z1: Profit | AB1: P.U. CHF | AC1: TOTAL Approvisionnement | AI1: TOTAL Construction | AM1: Sales | AN1: TOTAL Profit | AP1: TOTAL Frais | AQ1: COUT TOTAL | AR1: PROFIT TOTAL | AS1: PRIX TOTAL | AU1: Appro. Matériel Net | AW1: Main-d'œuvre Construction | AY1: Project Management | BA1: Frais Administratifs et Sales | BC1: Profit | BF1: Cout Total | BH1: Profit | BK1: Prix TTC | BM1: Pronovo | BN1: Prix Pronovo TTC | BO1: Prix TTC/kWc
E2: CHF (HT) | F2: CHF (HT) | H2: Matériel Avant Rabais | L2: Matériel Après Rabais | O2: Matériel Net | P2: Expédition | Q2: Douanes | R2: Frais Supp. | S2: Transport | T2: P.U. Matériel | U2: Main-d'œuvre | V2: Project Management | W2: Frais Administratifs | X2: P.U. Construction | Y2: Frais Généraux Sales | Z2: Profit Appro | AA2: Profit Construction | AC2: TOTAL Matériel Net | AD2: TOTAL Expédition | AE2: TOTAL Douanes | AF2: TOTAL Frais Supp. | AG2: TOTAL Transport | AH2: TOTAL Approvision-nement | AI2: TOTAL Main-d'œuvre | AJ2: TOTAL Project Management | AK2: TOTAL Frais Administratifs | AL2: TOTAL Construction | AM2: TOTAL Frais Généraux Sales | AN2: TOTAL Profit Appro. | AO2: TOTAL Profit Construction | AP2: TOTAL Frais Administratifs et Ingénierie
B3: Choisir le panneau : | H3: MAT (1) | I3: MAT (2) | J3: ACC | K3: Rabais | L3: MAT (1) | M3: MAT (2) | N3: ACC
B4: Longi 485W Full Black | J4: ='Financial Data'!$C$3 -> 0.03 | P4: ='Financial Data'!C4 -> 0 | Q4: ='Financial Data'!C5 -> 0 | R4: ='Financial Data'!C6 -> 0.02 | S4: ='Financial Data'!C7 -> 0.05 | U4: ='Financial Data'!C8 -> 65 | V4: ='Financial Data'!C10 -> 1200 | W4: ='Financial Data'!C11 -> 900 | Y4: ='Financial Data'!C12 -> 0.15 | Z4: ='Financial Data'!C13 -> 0.25 | AA4: ='Financial Data'!C14 -> 0.25
A5: 10 | B5: Panneaux | C5: Puissance: | D5: =ROUNDUP((A5*465)/1000,2) -> 4.65 | F5: =SUM(F6:F15) -> 16493.471 | U5: ='Financial Data'!C9 -> 90 | AC5: =+SUM(AC6:AC15) -> 6303.2805 | AD5: =+SUM(AD6:AD15) -> 0 | AE5: =+SUM(AE6:AE15) -> 0 | AF5: =+SUM(AF6:AF15) -> 126.06561 | AG5: =+SUM(AG6:AG15) -> 238.21402 | AH5: =+SUM(AH6:AH15) -> 6667.5601 | AI5: =+SUM(AI6:AI15) -> 3120 | AJ5: =+SUM(AJ6:AJ15) -> 1200 | ... AS5: =+SUM(AS6:AS15) -> 16493.471 | AT5: =IF(F5=AS5,"Matching","Not Matching") -> Matching | AU5: =SUM(AC5:AG5) -> 6667.5601 | AV5: =AU5/AS5 -> 0.40425452 | AW5: =AI5 -> 3120 | AX5: =AW5/AS5 -> 0.18916576 | AY5: =AJ5 -> 1200 | AZ5: =AY5/AS5 -> 0.072756063 | BA5: =AK5+AM5 -> 3059.0206 | BB5: =BA5/AS5 -> 0.18546858 | BC5: =AN5+AO5 -> 2446.89 | BD5: =BC5/AS5 -> 0.14835507 | BE5: =IF((AU5+AW5+AY5+BA5+BC5)=AS5,"Matching","Not Matching") -> Matching | BF5: =AQ5 -> 14046.581 | BG5: =BF5/AS5 -> 0.85164493 | BH5: =AR5 -> 2446.89 | BI5: =BH5/AS5 -> 0.14835507 | BJ5: =IF((BH5+BF5)=AS5,"Matching","Not Matching") -> Matching | BK5: =AS5*1.081 -> 17829.442 | BL5: =ROUND(BK5,-1) -> 17830 | BM5: =D5*380 -> 1767 | BN5: =BK5-BM5 -> 16062.442 | BO5: =BK5/D5 -> 3834.2886
I6: Parafoudres
B7: ="Panneau solaire "&G7 -> Panneau solaire LONGi Hi-MO X10 Artist LR7-54HVB-485M | C7: =A5 -> 10 | D7: U | E7: =AB7 -> 266.65685 | F7: =C7*E7 -> 2666.5685 | G7: =IF($B4="Jinko 455W Non Full Black",'Technical Data'!B3,IF($B4="Jinko 465W Full Black",'Technical Data'!B4,IF($B4="Longi 485W Non Full Black",'Technical Data'!B5,IF($B4="Longi 485W Full Black",'Technical Data'!B6,IF($B4="Aiko 480W Non Full Black",'Technical Data'!B7,IF($B4="Aiko 485W Full Black",'Technical Data'!B8,IF(ISBLANK($B4)," "))))))) -> LONGi Hi-MO X10 Artist LR7-54HVB-485M | H7: =IF($B4="Jinko 455W Non Full Black",'Financial Data'!$C$25,IF($B4="Jinko 465W Full Black",'Financial Data'!$C$26,IF($B4="Longi 485W Non Full Black",'Financial Data'!$C$27,IF($B4="Longi 485W Full Black",'Financial Data'!$C$28,IF($B4="Aiko 480W Non Full Black",'Financial Data'!$C$29,IF($B4="Aiko 485W Full Black",'Financial Data'!$C$30,IF(ISBLANK($B4),'Technical Data'!#REF!))))))) -> 105.55 | I7: ='Financial Data'!C56 -> 0 | J7: =H7*$J$4 -> 3.1665 | K7: 0 | L7: =H7*(1-$K7) -> 105.55 | M7: =I7*(1-$K7) -> 0 | N7: =J7*(1-$K7) -> 3.1665 | O7: =(L7+M7+N7) -> 108.7165 | P7: =O7*$P$4 -> 0 | Q7: =(O7+P7)*$Q$4 -> 0 | R7: =(O7+P7)*$R$4 -> 2.17433 | S7: =(O7+P7)*$S$4 -> 5.435825 | T7: =SUM(O7:S7) -> 116.32665 | U7: =1*$U$4 -> 65 | V7: 0 | W7: 0 | X7: =SUM(U7:W7) -> 65 | Y7: =$Y$4/(1-$Y$4)*(T7+X7+Z7+AA7) -> 39.998527 | Z7: =T7*$Z$4 -> 29.081664 | AA7: =X7*$AA$4 -> 16.25 | AB7: =T7+X7+Y7+Z7+AA7 -> 266.65685 | AC7: =O7*$C7 -> 1087.165 | AD7: =P7*$C7 -> 0 | AE7: =Q7*$C7 -> 0 | AF7: =R7*$C7 -> 21.7433 | AG7: =S7*$C7 -> 54.35825 | AH7: =T7*$C7 -> 1163.2665 | AI7: =U7*$C7 -> 650 | AJ7: =V7*$C7 -> 0 | ... AO7: =AA7*$C7 -> 162.5 | AP7: =AM7+AK7 -> 399.98527 | AQ7: =AM7+AL7+AH7 -> 2213.2518 | AR7: =AO7+AN7 -> 453.31664 | AS7: =AH7+AL7+AM7+AO7+AN7 -> 2666.5685
B8: ="Onduleur Fronius "&G8 -> Onduleur Fronius Symo GEN24 6.0 SC | C8: 1 | D8: U | E8: =AB8 -> 3133.4317 | F8: =C8*E8 -> 3133.4317 | G8: ='Financial Data'!B42 -> Symo GEN24 6.0 SC | H8: ='Financial Data'!C42 -> 1333.85 | I8: ='Financial Data'!C53+'Financial Data'!C54+'Financial Data'!C55 -> 449.25 | J8: =H8*$J$4 -> 40.0155 | K8: 0 | L8: =H8*(1-$K8) -> 1333.85 | M8: =I8*(1-$K8) -> 449.25 | N8: =J8*(1-$K8) -> 40.0155 | O8: =(L8+M8+N8) -> 1823.1155 | P8: =O8*$P$4 -> 0 | Q8: =(O8+P8)*$Q$4 -> 0 | R8: =(O8+P8)*$R$4 -> 36.46231 | S8: =(O8+P8)*$S$4 -> 91.155775 | T8: =SUM(O8:S8) -> 1950.7336 | U8: =2*$U$5 -> 180 | V8: 0 | W8: 0 | X8: =SUM(U8:W8) -> 180 | Y8: =$Y$4/(1-$Y$4)*(T8+X8+Z8+AA8) -> 470.01476 | Z8: =T8*$Z$4 -> 487.6834 | AA8: =X8*$AA$4 -> 45 | AB8: =T8+X8+Y8+Z8+AA8 -> 3133.4317 | AC8: =O8*$C8 -> 1823.1155 | AD8: =P8*$C8 -> 0 | AE8: =Q8*$C8 -> 0 | AF8: =R8*$C8 -> 36.46231 | AG8: =S8*$C8 -> 91.155775 | AH8: =T8*$C8 -> 1950.7336 | AI8: =U8*$C8 -> 180 | AJ8: =V8*$C8 -> 0 | ... AO8: =AA8*$C8 -> 45 | AP8: =AM8+AK8 -> 470.01476 | AQ8: =AM8+AL8+AH8 -> 2600.7483 | AR8: =AO8+AN8 -> 532.6834 | AS8: =AH8+AL8+AM8+AO8+AN8 -> 3133.4317
B9: Accessoires | C9: 1 | D9: Forfait | E9: =AB9 -> 618.57353 | F9: =C9*E9 -> 618.57353 | H9: 300 | I9: 0 | J9: =H9*$J$4 -> 9 | K9: 0 | L9: =H9*(1-$K9) -> 300 | M9: =I9*(1-$K9) -> 0 | N9: =J9*(1-$K9) -> 9 | O9: =(L9+M9+N9) -> 309 | P9: =O9*$P$4 -> 0 | Q9: =(O9+P9)*$Q$4 -> 0 | R9: =(O9+P9)*$R$4 -> 6.18 | S9: =(O9+P9)*$S$4 -> 15.45 | T9: =SUM(O9:S9) -> 330.63 | U9: =(C7/10)*$U$5 -> 90 | V9: 0 | W9: 0 | X9: =SUM(U9:W9) -> 90 | Y9: =$Y$4/(1-$Y$4)*(T9+X9+Z9+AA9) -> 92.786029 | Z9: =T9*$Z$4 -> 82.6575 | AA9: =X9*$AA$4 -> 22.5 | AB9: =T9+X9+Y9+Z9+AA9 -> 618.57353 | AC9: =O9*$C9 -> 309 | AD9: =P9*$C9 -> 0 | AE9: =Q9*$C9 -> 0 | AF9: =R9*$C9 -> 6.18 | AG9: =S9*$C9 -> 15.45 | AH9: =T9*$C9 -> 330.63 | AI9: =U9*$C9 -> 90 | AJ9: =V9*$C9 -> 0 | ... AO9: =AA9*$C9 -> 22.5 | AP9: =AM9+AK9 -> 92.786029 | AQ9: =AM9+AL9+AH9 -> 513.41603 | AR9: =AO9+AN9 -> 105.1575 | AS9: =AH9+AL9+AM9+AO9+AN9 -> 618.57353
B10: Système de montage sur tuile | C10: =A5 -> 10 | D10: U | E10: =AB10 -> 257.66176 | F10: =C10*E10 -> 2576.6176 | H10: 100 | I10: 0 | J10: =H10*$J$4 -> 3 | K10: 0 | L10: =H10*(1-$K10) -> 100 | M10: =I10*(1-$K10) -> 0 | N10: =J10*(1-$K10) -> 3 | O10: =(L10+M10+N10) -> 103 | P10: =O10*$P$4 -> 0 | Q10: =(O10+P10)*$Q$4 -> 0 | R10: =(O10+P10)*$R$4 -> 2.06 | S10: =(O10+P10)*$S$4 -> 5.15 | T10: =SUM(O10:S10) -> 110.21 | U10: =1*$U$4 -> 65 | V10: 0 | W10: 0 | X10: =SUM(U10:W10) -> 65 | Y10: =$Y$4/(1-$Y$4)*(T10+X10+Z10+AA10) -> 38.649265 | Z10: =T10*$Z$4 -> 27.5525 | AA10: =X10*$AA$4 -> 16.25 | AB10: =T10+X10+Y10+Z10+AA10 -> 257.66176 | AC10: =O10*$C10 -> 1030 | AD10: =P10*$C10 -> 0 | AE10: =Q10*$C10 -> 0 | AF10: =R10*$C10 -> 20.6 | AG10: =S10*$C10 -> 51.5 | AH10: =T10*$C10 -> 1102.1 | AI10: =U10*$C10 -> 650 | AJ10: =V10*$C10 -> 0 | ... AO10: =AA10*$C10 -> 162.5 | AP10: =AM10+AK10 -> 386.49265 | AQ10: =AM10+AL10+AH10 -> 2138.5926 | AR10: =AO10+AN10 -> 438.025 | AS10: =AH10+AL10+AM10+AO10+AN10 -> 2576.6176
B11: Raccordement AC | C11: 1 | D11: Forfait | E11: =AB11 -> 3089.7794 | F11: =C11*E11 -> 3089.7794 | H11: 500 | I11: 0 | J11: =H11*$J$4 -> 15 | K11: 0 | L11: =H11*(1-$K11) -> 500 | M11: =I11*(1-$K11) -> 0 | N11: =J11*(1-$K11) -> 15 | O11: =(L11+M11+N11) -> 515 | P11: =O11*$P$4 -> 0 | Q11: =(O11+P11)*$Q$4 -> 0 | R11: =(O11+P11)*$R$4 -> 10.3 | S11: =(O11+P11)*$S$4 -> 25.75 | T11: =SUM(O11:S11) -> 551.05 | U11: =5*$U$5+600+500 -> 1550 | V11: 0 | W11: 0 | X11: =SUM(U11:W11) -> 1550 | Y11: =$Y$4/(1-$Y$4)*(T11+X11+Z11+AA11) -> 463.46691 | Z11: =T11*$Z$4 -> 137.7625 | AA11: =X11*$AA$4 -> 387.5 | AB11: =T11+X11+Y11+Z11+AA11 -> 3089.7794 | AC11: =O11*$C11 -> 515 | AD11: =P11*$C11 -> 0 | AE11: =Q11*$C11 -> 0 | AF11: =R11*$C11 -> 10.3 | AG11: =S11*$C11 -> 25.75 | AH11: =T11*$C11 -> 551.05 | AI11: =U11*$C11 -> 1550 | AJ11: =V11*$C11 -> 0 | ... AO11: =AA11*$C11 -> 387.5 | AP11: =AM11+AK11 -> 463.46691 | AQ11: =AM11+AL11+AH11 -> 2564.5169 | AR11: =AO11+AN11 -> 525.2625 | AS11: =AH11+AL11+AM11+AO11+AN11 -> 3089.7794
B12: Echafaudage jusqu'à 6m de hauteur | C12: 1 | D12: Forfait | E12: =AB12 -> 2308.5 | F12: =C12*E12 -> 2308.5 | H12: 1300 | I12: 200 | J12: =H12*$J$4 -> 39 | K12: 0 | L12: =H12*(1-$K12) -> 1300 | M12: =I12*(1-$K12) -> 200 | N12: =J12*(1-$K12) -> 39 | O12: =(L12+M12+N12) -> 1539 | P12: =O12*$P$4 -> 0 | Q12: =(O12+P12)*$Q$4 -> 0 | R12: =(O12+P12)*$R$4 -> 30.78 | S12: 0 | T12: =SUM(O12:S12) -> 1569.78 | U12: 0 | V12: 0 | W12: 0 | X12: =SUM(U12:W12) -> 0 | Y12: =$Y$4/(1-$Y$4)*(T12+X12+Z12+AA12) -> 346.275 | Z12: =T12*$Z$4 -> 392.445 | AA12: =X12*$AA$4 -> 0 | AB12: =T12+X12+Y12+Z12+AA12 -> 2308.5 | AC12: =O12*$C12 -> 1539 | AD12: =P12*$C12 -> 0 | AE12: =Q12*$C12 -> 0 | AF12: =R12*$C12 -> 30.78 | AG12: =S12*$C12 -> 0 | AH12: =T12*$C12 -> 1569.78 | AI12: =U12*$C12 -> 0 | AJ12: =V12*$C12 -> 0 | ... AO12: =AA12*$C12 -> 0 | AP12: =AM12+AK12 -> 346.275 | AQ12: =AM12+AL12+AH12 -> 1916.055 | AR12: =AO12+AN12 -> 392.445 | AS12: =AH12+AL12+AM12+AO12+AN12 -> 2308.5
B13: Travaux administratifs | C13: 1 | D13: Forfait | E13: =AB13 -> 900 | F13: =C13*E13 -> 900 | H13: 0 | I13: 0 | J13: =H13*$J$4 -> 0 | K13: 0 | L13: =H13*(1-$K13) -> 0 | M13: =I13*(1-$K13) -> 0 | N13: =J13*(1-$K13) -> 0 | O13: =(L13+M13+N13) -> 0 | P13: =O13*$P$4 -> 0 | Q13: =(O13+P13)*$Q$4 -> 0 | R13: =(O13+P13)*$R$4 -> 0 | S13: 0 | T13: =SUM(O13:S13) -> 0 | U13: 0 | V13: 0 | W13: =$W$4 -> 900 | X13: =SUM(U13:W13) -> 900 | Y13: 0 | Z13: =T13*$Z$4 -> 0 | AA13: 0 | AB13: =T13+X13+Y13+Z13+AA13 -> 900 | AC13: =O13*$C13 -> 0 | AD13: =P13*$C13 -> 0 | AE13: =Q13*$C13 -> 0 | AF13: =R13*$C13 -> 0 | AG13: =S13*$C13 -> 0 | AH13: =T13*$C13 -> 0 | AI13: =U13*$C13 -> 0 | AJ13: =V13*$C13 -> 0 | ... AO13: =AA13*$C13 -> 0 | AP13: =AM13+AK13 -> 900 | AQ13: =AM13+AL13+AH13 -> 900 | AR13: =AO13+AN13 -> 0 | AS13: =AH13+AL13+AM13+AO13+AN13 -> 900
B14: Travaux électriques, contrôle et Pronovo | C14: 1 | D14: Forfait | E14: =AB14 -> 1200 | F14: =C14*E14 -> 1200 | H14: 0 | I14: 0 | J14: =H14*$J$4 -> 0 | K14: 0 | L14: =H14*(1-$K14) -> 0 | M14: =I14*(1-$K14) -> 0 | N14: =J14*(1-$K14) -> 0 | O14: =(L14+M14+N14) -> 0 | P14: =O14*$P$4 -> 0 | Q14: =(O14+P14)*$Q$4 -> 0 | R14: =(O14+P14)*$R$4 -> 0 | S14: 0 | T14: =SUM(O14:S14) -> 0 | U14: 0 | V14: =$V$4 -> 1200 | W14: 0 | X14: =SUM(U14:W14) -> 1200 | Y14: 0 | Z14: =T14*$Z$4 -> 0 | AA14: 0 | AB14: =T14+X14+Y14+Z14+AA14 -> 1200 | AC14: =O14*$C14 -> 0 | AD14: =P14*$C14 -> 0 | AE14: =Q14*$C14 -> 0 | AF14: =R14*$C14 -> 0 | AG14: =S14*$C14 -> 0 | AH14: =T14*$C14 -> 0 | AI14: =U14*$C14 -> 0 | AJ14: =V14*$C14 -> 1200 | ... AO14: =AA14*$C14 -> 0 | AP14: =AM14+AK14 -> 0 | AQ14: =AM14+AL14+AH14 -> 1200 | AR14: =AO14+AN14 -> 0 | AS14: =AH14+AL14+AM14+AO14+AN14 -> 1200
A16: 11 | B16: Panneaux | C16: Puissance: | D16: =ROUNDUP((A16*465)/1000,2) -> 5.12 | F16: =SUM(F17:F26) -> 17031.025 | AC16: =+SUM(AC17:AC26) -> 6514.997 | AD16: =+SUM(AD17:AD26) -> 0 | AE16: =+SUM(AE17:AE26) -> 0 | AF16: =+SUM(AF17:AF26) -> 130.29994 | AG16: =+SUM(AG17:AG26) -> 248.79985 | AH16: =+SUM(AH17:AH26) -> 6894.0968 | AI16: =+SUM(AI17:AI26) -> 3259 | AJ16: =+SUM(AJ17:AJ26) -> 1200 | ... AS16: =+SUM(AS17:AS26) -> 17031.025 | AT16: =IF(F16=AS16,"Matching","Not Matching") -> Matching | AU16: =SUM(AC16:AG16) -> 6894.0968 | AV16: =AU16/AS16 -> 0.40479636 | AW16: =AI16 -> 3259 | AX16: =AW16/AS16 -> 0.19135666 | AY16: =AJ16 -> 1200 | AZ16: =AY16/AS16 -> 0.070459648 | BA16: =AK16+AM16 -> 3139.6537 | BB16: =BA16/AS16 -> 0.18434908 | BC16: =AN16+AO16 -> 2538.2742 | BD16: =BC16/AS16 -> 0.14903825 | BE16: =IF((AU16+AW16+AY16+BA16+BC16)=AS16,"Matching","Not Matching") -> Matching | BF16: =AQ16 -> 14492.75 | BG16: =BF16/AS16 -> 0.85096175 | BH16: =AR16 -> 2538.2742 | BI16: =BH16/AS16 -> 0.14903825 | BJ16: =IF((BH16+BF16)=AS16,"Matching","Not Matching") -> Matching | BK16: =AS16*1.081 -> 18410.538 | BL16: =ROUND(BK16,-1) -> 18410 | BM16: =D16*380 -> 1945.6 | BN16: =BK16-BM16 -> 16464.938 | BO16: =BK16/D16 -> 3595.8081
I17: Parafoudres
B18: ="Panneau solaire "&G18 -> Panneau solaire LONGi Hi-MO X10 Artist LR7-54HVB-485M | C18: =A16 -> 11 | D18: U | E18: =AB18 -> 266.65685 | F18: =C18*E18 -> 2933.2253 | G18: =$G$7 -> LONGi Hi-MO X10 Artist LR7-54HVB-485M | H18: =$H$7 -> 105.55 | I18: =$I$7 -> 0 | J18: =H18*$J$4 -> 3.1665 | K18: 0 | L18: =H18*(1-$K18) -> 105.55 | M18: =I18*(1-$K18) -> 0 | N18: =J18*(1-$K18) -> 3.1665 | O18: =(L18+M18+N18) -> 108.7165 | P18: =O18*$P$4 -> 0 | Q18: =(O18+P18)*$Q$4 -> 0 | R18: =(O18+P18)*$R$4 -> 2.17433 | S18: =(O18+P18)*$S$4 -> 5.435825 | T18: =SUM(O18:S18) -> 116.32665 | U18: =1*$U$4 -> 65 | V18: =V7 -> 0 | W18: =W7 -> 0 | X18: =SUM(U18:W18) -> 65 | Y18: =$Y$4/(1-$Y$4)*(T18+X18+Z18+AA18) -> 39.998527 | Z18: =T18*$Z$4 -> 29.081664 | AA18: =X18*$AA$4 -> 16.25 | AB18: =T18+X18+Y18+Z18+AA18 -> 266.65685 | AC18: =O18*$C18 -> 1195.8815 | AD18: =P18*$C18 -> 0 | AE18: =Q18*$C18 -> 0 | AF18: =R18*$C18 -> 23.91763 | AG18: =S18*$C18 -> 59.794075 | AH18: =T18*$C18 -> 1279.5932 | AI18: =U18*$C18 -> 715 | AJ18: =V18*$C18 -> 0 | ... AO18: =AA18*$C18 -> 178.75 | AP18: =AM18+AK18 -> 439.9838 | AQ18: =AM18+AL18+AH18 -> 2434.577 | AR18: =AO18+AN18 -> 498.6483 | AS18: =AH18+AL18+AM18+AO18+AN18 -> 2933.2253
B19: ="Onduleur Fronius "&G19 -> Onduleur Fronius Symo GEN24 6.0 SC | C19: 1 | D19: U | E19: =AB19 -> 3133.4317 | F19: =C19*E19 -> 3133.4317 | G19: =$G$8 -> Symo GEN24 6.0 SC | H19: =$H$8 -> 1333.85 | I19: =$I$8 -> 449.25 | J19: =H19*$J$4 -> 40.0155 | K19: 0 | L19: =H19*(1-$K19) -> 1333.85 | M19: =I19*(1-$K19) -> 449.25 | N19: =J19*(1-$K19) -> 40.0155 | O19: =(L19+M19+N19) -> 1823.1155 | P19: =O19*$P$4 -> 0 | Q19: =(O19+P19)*$Q$4 -> 0 | R19: =(O19+P19)*$R$4 -> 36.46231 | S19: =(O19+P19)*$S$4 -> 91.155775 | T19: =SUM(O19:S19) -> 1950.7336 | U19: =2*$U$5 -> 180 | V19: =V8 -> 0 | W19: =W8 -> 0 | X19: =SUM(U19:W19) -> 180 | Y19: =$Y$4/(1-$Y$4)*(T19+X19+Z19+AA19) -> 470.01476 | Z19: =T19*$Z$4 -> 487.6834 | AA19: =X19*$AA$4 -> 45 | AB19: =T19+X19+Y19+Z19+AA19 -> 3133.4317 | AC19: =O19*$C19 -> 1823.1155 | AD19: =P19*$C19 -> 0 | AE19: =Q19*$C19 -> 0 | AF19: =R19*$C19 -> 36.46231 | AG19: =S19*$C19 -> 91.155775 | AH19: =T19*$C19 -> 1950.7336 | AI19: =U19*$C19 -> 180 | AJ19: =V19*$C19 -> 0 | ... AO19: =AA19*$C19 -> 45 | AP19: =AM19+AK19 -> 470.01476 | AQ19: =AM19+AL19+AH19 -> 2600.7483 | AR19: =AO19+AN19 -> 532.6834 | AS19: =AH19+AL19+AM19+AO19+AN19 -> 3133.4317
B20: Accessoires | C20: 1 | D20: Forfait | E20: =AB20 -> 631.80882 | F20: =C20*E20 -> 631.80882 | H20: =$H$9 -> 300 | I20: =I9 -> 0 | J20: =H20*$J$4 -> 9 | K20: 0 | L20: =H20*(1-$K20) -> 300 | M20: =I20*(1-$K20) -> 0 | N20: =J20*(1-$K20) -> 9 | O20: =(L20+M20+N20) -> 309 | P20: =O20*$P$4 -> 0 | Q20: =(O20+P20)*$Q$4 -> 0 | R20: =(O20+P20)*$R$4 -> 6.18 | S20: =(O20+P20)*$S$4 -> 15.45 | T20: =SUM(O20:S20) -> 330.63 | U20: =(C18/10)*$U$5 -> 99 | V20: =V9 -> 0 | W20: =W9 -> 0 | X20: =SUM(U20:W20) -> 99 | Y20: =$Y$4/(1-$Y$4)*(T20+X20+Z20+AA20) -> 94.771324 | Z20: =T20*$Z$4 -> 82.6575 | AA20: =X20*$AA$4 -> 24.75 | AB20: =T20+X20+Y20+Z20+AA20 -> 631.80882 | AC20: =O20*$C20 -> 309 | AD20: =P20*$C20 -> 0 | AE20: =Q20*$C20 -> 0 | AF20: =R20*$C20 -> 6.18 | AG20: =S20*$C20 -> 15.45 | AH20: =T20*$C20 -> 330.63 | AI20: =U20*$C20 -> 99 | AJ20: =V20*$C20 -> 0 | ... AO20: =AA20*$C20 -> 24.75 | AP20: =AM20+AK20 -> 94.771324 | AQ20: =AM20+AL20+AH20 -> 524.40132 | AR20: =AO20+AN20 -> 107.4075 | AS20: =AH20+AL20+AM20+AO20+AN20 -> 631.80882
B21: Système de montage sur tuile | C21: =A16 -> 11 | D21: U | E21: =AB21 -> 257.66176 | F21: =C21*E21 -> 2834.2794 | H21: =$H$10 -> 100 | I21: =I10 -> 0 | J21: =H21*$J$4 -> 3 | K21: 0 | L21: =H21*(1-$K21) -> 100 | M21: =I21*(1-$K21) -> 0 | N21: =J21*(1-$K21) -> 3 | O21: =(L21+M21+N21) -> 103 | P21: =O21*$P$4 -> 0 | Q21: =(O21+P21)*$Q$4 -> 0 | R21: =(O21+P21)*$R$4 -> 2.06 | S21: =(O21+P21)*$S$4 -> 5.15 | T21: =SUM(O21:S21) -> 110.21 | U21: =1*$U$4 -> 65 | V21: =V10 -> 0 | W21: =W10 -> 0 | X21: =SUM(U21:W21) -> 65 | Y21: =$Y$4/(1-$Y$4)*(T21+X21+Z21+AA21) -> 38.649265 | Z21: =T21*$Z$4 -> 27.5525 | AA21: =X21*$AA$4 -> 16.25 | AB21: =T21+X21+Y21+Z21+AA21 -> 257.66176 | AC21: =O21*$C21 -> 1133 | AD21: =P21*$C21 -> 0 | AE21: =Q21*$C21 -> 0 | AF21: =R21*$C21 -> 22.66 | AG21: =S21*$C21 -> 56.65 | AH21: =T21*$C21 -> 1212.31 | AI21: =U21*$C21 -> 715 | AJ21: =V21*$C21 -> 0 | ... AO21: =AA21*$C21 -> 178.75 | AP21: =AM21+AK21 -> 425.14191 | AQ21: =AM21+AL21+AH21 -> 2352.4519 | AR21: =AO21+AN21 -> 481.8275 | AS21: =AH21+AL21+AM21+AO21+AN21 -> 2834.2794
B22: Raccordement AC | C22: 1 | D22: Forfait | E22: =AB22 -> 3089.7794 | F22: =C22*E22 -> 3089.7794 | H22: =$H$11 -> 500 | I22: =I11 -> 0 | J22: =H22*$J$4 -> 15 | K22: 0 | L22: =H22*(1-$K22) -> 500 | M22: =I22*(1-$K22) -> 0 | N22: =J22*(1-$K22) -> 15 | O22: =(L22+M22+N22) -> 515 | P22: =O22*$P$4 -> 0 | Q22: =(O22+P22)*$Q$4 -> 0 | R22: =(O22+P22)*$R$4 -> 10.3 | S22: =(O22+P22)*$S$4 -> 25.75 | T22: =SUM(O22:S22) -> 551.05 | U22: =5*$U$5+600+500 -> 1550 | V22: =V11 -> 0 | W22: =W11 -> 0 | X22: =SUM(U22:W22) -> 1550 | Y22: =$Y$4/(1-$Y$4)*(T22+X22+Z22+AA22) -> 463.46691 | Z22: =T22*$Z$4 -> 137.7625 | AA22: =X22*$AA$4 -> 387.5 | AB22: =T22+X22+Y22+Z22+AA22 -> 3089.7794 | AC22: =O22*$C22 -> 515 | AD22: =P22*$C22 -> 0 | AE22: =Q22*$C22 -> 0 | AF22: =R22*$C22 -> 10.3 | AG22: =S22*$C22 -> 25.75 | AH22: =T22*$C22 -> 551.05 | AI22: =U22*$C22 -> 1550 | AJ22: =V22*$C22 -> 0 | ... AO22: =AA22*$C22 -> 387.5 | AP22: =AM22+AK22 -> 463.46691 | AQ22: =AM22+AL22+AH22 -> 2564.5169 | AR22: =AO22+AN22 -> 525.2625 | AS22: =AH22+AL22+AM22+AO22+AN22 -> 3089.7794
B23: Echafaudage jusqu'à 6m de hauteur | C23: 1 | D23: Forfait | E23: =AB23 -> 2308.5 | F23: =C23*E23 -> 2308.5 | H23: =$H$12 -> 1300 | I23: =I12 -> 200 | J23: =H23*$J$4 -> 39 | K23: 0 | L23: =H23*(1-$K23) -> 1300 | M23: =I23*(1-$K23) -> 200 | N23: =J23*(1-$K23) -> 39 | O23: =(L23+M23+N23) -> 1539 | P23: =O23*$P$4 -> 0 | Q23: =(O23+P23)*$Q$4 -> 0 | R23: =(O23+P23)*$R$4 -> 30.78 | S23: 0 | T23: =SUM(O23:S23) -> 1569.78 | U23: 0 | V23: =V12 -> 0 | W23: =W12 -> 0 | X23: =SUM(U23:W23) -> 0 | Y23: =$Y$4/(1-$Y$4)*(T23+X23+Z23+AA23) -> 346.275 | Z23: =T23*$Z$4 -> 392.445 | AA23: =X23*$AA$4 -> 0 | AB23: =T23+X23+Y23+Z23+AA23 -> 2308.5 | AC23: =O23*$C23 -> 1539 | AD23: =P23*$C23 -> 0 | AE23: =Q23*$C23 -> 0 | AF23: =R23*$C23 -> 30.78 | AG23: =S23*$C23 -> 0 | AH23: =T23*$C23 -> 1569.78 | AI23: =U23*$C23 -> 0 | AJ23: =V23*$C23 -> 0 | ... AO23: =AA23*$C23 -> 0 | AP23: =AM23+AK23 -> 346.275 | AQ23: =AM23+AL23+AH23 -> 1916.055 | AR23: =AO23+AN23 -> 392.445 | AS23: =AH23+AL23+AM23+AO23+AN23 -> 2308.5
B24: Travaux administratifs | C24: 1 | D24: Forfait | E24: =AB24 -> 900 | F24: =C24*E24 -> 900 | H24: 0 | I24: 0 | J24: =H24*$J$4 -> 0 | K24: 0 | L24: =H24*(1-$K24) -> 0 | M24: =I24*(1-$K24) -> 0 | N24: =J24*(1-$K24) -> 0 | O24: =(L24+M24+N24) -> 0 | P24: =O24*$P$4 -> 0 | Q24: =(O24+P24)*$Q$4 -> 0 | R24: =(O24+P24)*$R$4 -> 0 | S24: 0 | T24: =SUM(O24:S24) -> 0 | U24: 0 | V24: =V13 -> 0 | W24: =W13 -> 900 | X24: =SUM(U24:W24) -> 900 | Y24: 0 | Z24: =T24*$Z$4 -> 0 | AA24: 0 | AB24: =T24+X24+Y24+Z24+AA24 -> 900 | AC24: =O24*$C24 -> 0 | AD24: =P24*$C24 -> 0 | AE24: =Q24*$C24 -> 0 | AF24: =R24*$C24 -> 0 | AG24: =S24*$C24 -> 0 | AH24: =T24*$C24 -> 0 | AI24: =U24*$C24 -> 0 | AJ24: =V24*$C24 -> 0 | ... AO24: =AA24*$C24 -> 0 | AP24: =AM24+AK24 -> 900 | AQ24: =AM24+AL24+AH24 -> 900 | AR24: =AO24+AN24 -> 0 | AS24: =AH24+AL24+AM24+AO24+AN24 -> 900
B25: Travaux électriques, contrôle et Pronovo | C25: 1 | D25: Forfait | E25: =AB25 -> 1200 | F25: =C25*E25 -> 1200 | H25: 0 | I25: 0 | J25: =H25*$J$4 -> 0 | K25: 0 | L25: =H25*(1-$K25) -> 0 | M25: =I25*(1-$K25) -> 0 | N25: =J25*(1-$K25) -> 0 | O25: =(L25+M25+N25) -> 0 | P25: =O25*$P$4 -> 0 | Q25: =(O25+P25)*$Q$4 -> 0 | R25: =(O25+P25)*$R$4 -> 0 | S25: 0 | T25: =SUM(O25:S25) -> 0 | U25: 0 | V25: =V14 -> 1200 | W25: =W14 -> 0 | X25: =SUM(U25:W25) -> 1200 | Y25: 0 | Z25: =T25*$Z$4 -> 0 | AA25: 0 | AB25: =T25+X25+Y25+Z25+AA25 -> 1200 | AC25: =O25*$C25 -> 0 | AD25: =P25*$C25 -> 0 | AE25: =Q25*$C25 -> 0 | AF25: =R25*$C25 -> 0 | AG25: =S25*$C25 -> 0 | AH25: =T25*$C25 -> 0 | AI25: =U25*$C25 -> 0 | AJ25: =V25*$C25 -> 1200 | ... AO25: =AA25*$C25 -> 0 | AP25: =AM25+AK25 -> 0 | AQ25: =AM25+AL25+AH25 -> 1200 | AR25: =AO25+AN25 -> 0 | AS25: =AH25+AL25+AM25+AO25+AN25 -> 1200
A27: 12 | B27: Panneaux | C27: Puissance: | D27: =ROUNDUP((A27*465)/1000,2) -> 5.58 | F27: =SUM(F28:F37) -> 17568.579 | AC27: =+SUM(AC28:AC37) -> 6726.7135 | AD27: =+SUM(AD28:AD37) -> 0 | AE27: =+SUM(AE28:AE37) -> 0 | AF27: =+SUM(AF28:AF37) -> 134.53427 | AG27: =+SUM(AG28:AG37) -> 259.38567 | AH27: =+SUM(AH28:AH37) -> 7120.6334 | AI27: =+SUM(AI28:AI37) -> 3398 | AJ27: =+SUM(AJ28:AJ37) -> 1200 | ... AS27: =+SUM(AS28:AS37) -> 17568.579 | AT27: =IF(F27=AS27,"Matching","Not Matching") -> Matching | AU27: =SUM(AC27:AG27) -> 7120.6334 | AV27: =AU27/AS27 -> 0.40530504 | AW27: =AI27 -> 3398 | AX27: =AW27/AS27 -> 0.19341348 | AY27: =AJ27 -> 1200 | AZ27: =AY27/AS27 -> 0.068303761 | BA27: =AK27+AM27 -> 3220.2868 | BB27: =BA27/AS27 -> 0.18329808 | BC27: =AN27+AO27 -> 2629.6584 | BD27: =BC27/AS27 -> 0.14967963 | BE27: =IF((AU27+AW27+AY27+BA27+BC27)=AS27,"Matching","Not Matching") -> Matching | BF27: =AQ27 -> 14938.92 | BG27: =BF27/AS27 -> 0.85032037 | BH27: =AR27 -> 2629.6584 | BI27: =BH27/AS27 -> 0.14967963 | BJ27: =IF((BH27+BF27)=AS27,"Matching","Not Matching") -> Matching | BK27: =AS27*1.081 -> 18991.633 | BL27: =ROUND(BK27,-1) -> 18990 | BM27: =D27*380 -> 2120.4 | BN27: =BK27-BM27 -> 16871.233 | BO27: =BK27/D27 -> 3403.5185
I28: Parafoudres
B29: ="Panneau solaire "&G29 -> Panneau solaire LONGi Hi-MO X10 Artist LR7-54HVB-485M | C29: =A27 -> 12 | D29: U | E29: =AB29 -> 266.65685 | F29: =C29*E29 -> 3199.8821 | G29: =$G$7 -> LONGi Hi-MO X10 Artist LR7-54HVB-485M | H29: =$H$7 -> 105.55 | I29: =$I$7 -> 0 | J29: =H29*$J$4 -> 3.1665 | K29: 0 | L29: =H29*(1-$K29) -> 105.55 | M29: =I29*(1-$K29) -> 0 | N29: =J29*(1-$K29) -> 3.1665 | O29: =(L29+M29+N29) -> 108.7165 | P29: =O29*$P$4 -> 0 | Q29: =(O29+P29)*$Q$4 -> 0 | R29: =(O29+P29)*$R$4 -> 2.17433 | S29: =(O29+P29)*$S$4 -> 5.435825 | T29: =SUM(O29:S29) -> 116.32665 | U29: =1*$U$4 -> 65 | V29: =V18 -> 0 | W29: =W18 -> 0 | X29: =SUM(U29:W29) -> 65 | Y29: =$Y$4/(1-$Y$4)*(T29+X29+Z29+AA29) -> 39.998527 | Z29: =T29*$Z$4 -> 29.081664 | AA29: =X29*$AA$4 -> 16.25 | AB29: =T29+X29+Y29+Z29+AA29 -> 266.65685 | AC29: =O29*$C29 -> 1304.598 | AD29: =P29*$C29 -> 0 | AE29: =Q29*$C29 -> 0 | AF29: =R29*$C29 -> 26.09196 | AG29: =S29*$C29 -> 65.2299 | AH29: =T29*$C29 -> 1395.9199 | AI29: =U29*$C29 -> 780 | AJ29: =V29*$C29 -> 0 | ... AO29: =AA29*$C29 -> 195 | AP29: =AM29+AK29 -> 479.98232 | AQ29: =AM29+AL29+AH29 -> 2655.9022 | AR29: =AO29+AN29 -> 543.97996 | AS29: =AH29+AL29+AM29+AO29+AN29 -> 3199.8821
B30: ="Onduleur Fronius "&G30 -> Onduleur Fronius Symo GEN24 6.0 SC | C30: 1 | D30: U | E30: =AB30 -> 3133.4317 | F30: =C30*E30 -> 3133.4317 | G30: =$G$8 -> Symo GEN24 6.0 SC | H30: =$H$8 -> 1333.85 | I30: =$I$8 -> 449.25 | J30: =H30*$J$4 -> 40.0155 | K30: 0 | L30: =H30*(1-$K30) -> 1333.85 | M30: =I30*(1-$K30) -> 449.25 | N30: =J30*(1-$K30) -> 40.0155 | O30: =(L30+M30+N30) -> 1823.1155 | P30: =O30*$P$4 -> 0 | Q30: =(O30+P30)*$Q$4 -> 0 | R30: =(O30+P30)*$R$4 -> 36.46231 | S30: =(O30+P30)*$S$4 -> 91.155775 | T30: =SUM(O30:S30) -> 1950.7336 | U30: =2*$U$5 -> 180 | V30: =V19 -> 0 | W30: =W19 -> 0 | X30: =SUM(U30:W30) -> 180 | Y30: =$Y$4/(1-$Y$4)*(T30+X30+Z30+AA30) -> 470.01476 | Z30: =T30*$Z$4 -> 487.6834 | AA30: =X30*$AA$4 -> 45 | AB30: =T30+X30+Y30+Z30+AA30 -> 3133.4317 | AC30: =O30*$C30 -> 1823.1155 | AD30: =P30*$C30 -> 0 | AE30: =Q30*$C30 -> 0 | AF30: =R30*$C30 -> 36.46231 | AG30: =S30*$C30 -> 91.155775 | AH30: =T30*$C30 -> 1950.7336 | AI30: =U30*$C30 -> 180 | AJ30: =V30*$C30 -> 0 | ... AO30: =AA30*$C30 -> 45 | AP30: =AM30+AK30 -> 470.01476 | AQ30: =AM30+AL30+AH30 -> 2600.7483 | AR30: =AO30+AN30 -> 532.6834 | AS30: =AH30+AL30+AM30+AO30+AN30 -> 3133.4317
B31: Accessoires | C31: 1 | D31: Forfait | E31: =AB31 -> 645.04412 | F31: =C31*E31 -> 645.04412 | H31: =$H$9 -> 300 | I31: =I9 -> 0 | J31: =H31*$J$4 -> 9 | K31: 0 | L31: =H31*(1-$K31) -> 300 | M31: =I31*(1-$K31) -> 0 | N31: =J31*(1-$K31) -> 9 | O31: =(L31+M31+N31) -> 309 | P31: =O31*$P$4 -> 0 | Q31: =(O31+P31)*$Q$4 -> 0 | R31: =(O31+P31)*$R$4 -> 6.18 | S31: =(O31+P31)*$S$4 -> 15.45 | T31: =SUM(O31:S31) -> 330.63 | U31: =(C29/10)*$U$5 -> 108 | V31: =V20 -> 0 | W31: =W20 -> 0 | X31: =SUM(U31:W31) -> 108 | Y31: =$Y$4/(1-$Y$4)*(T31+X31+Z31+AA31) -> 96.756618 | Z31: =T31*$Z$4 -> 82.6575 | AA31: =X31*$AA$4 -> 27 | AB31: =T31+X31+Y31+Z31+AA31 -> 645.04412 | AC31: =O31*$C31 -> 309 | AD31: =P31*$C31 -> 0 | AE31: =Q31*$C31 -> 0 | AF31: =R31*$C31 -> 6.18 | AG31: =S31*$C31 -> 15.45 | AH31: =T31*$C31 -> 330.63 | AI31: =U31*$C31 -> 108 | AJ31: =V31*$C31 -> 0 | ... AO31: =AA31*$C31 -> 27 | AP31: =AM31+AK31 -> 96.756618 | AQ31: =AM31+AL31+AH31 -> 535.38662 | AR31: =AO31+AN31 -> 109.6575 | AS31: =AH31+AL31+AM31+AO31+AN31 -> 645.04412
B32: Système de montage sur tuile | C32: =A27 -> 12 | D32: U | E32: =AB32 -> 257.66176 | F32: =C32*E32 -> 3091.9412 | H32: =$H$10 -> 100 | I32: =I10 -> 0 | J32: =H32*$J$4 -> 3 | K32: 0 | L32: =H32*(1-$K32) -> 100 | M32: =I32*(1-$K32) -> 0 | N32: =J32*(1-$K32) -> 3 | O32: =(L32+M32+N32) -> 103 | P32: =O32*$P$4 -> 0 | Q32: =(O32+P32)*$Q$4 -> 0 | R32: =(O32+P32)*$R$4 -> 2.06 | S32: =(O32+P32)*$S$4 -> 5.15 | T32: =SUM(O32:S32) -> 110.21 | U32: =1*$U$4 -> 65 | V32: =V21 -> 0 | W32: =W21 -> 0 | X32: =SUM(U32:W32) -> 65 | Y32: =$Y$4/(1-$Y$4)*(T32+X32+Z32+AA32) -> 38.649265 | Z32: =T32*$Z$4 -> 27.5525 | AA32: =X32*$AA$4 -> 16.25 | AB32: =T32+X32+Y32+Z32+AA32 -> 257.66176 | AC32: =O32*$C32 -> 1236 | AD32: =P32*$C32 -> 0 | AE32: =Q32*$C32 -> 0 | AF32: =R32*$C32 -> 24.72 | AG32: =S32*$C32 -> 61.8 | AH32: =T32*$C32 -> 1322.52 | AI32: =U32*$C32 -> 780 | AJ32: =V32*$C32 -> 0 | ... AO32: =AA32*$C32 -> 195 | AP32: =AM32+AK32 -> 463.79118 | AQ32: =AM32+AL32+AH32 -> 2566.3112 | AR32: =AO32+AN32 -> 525.63 | AS32: =AH32+AL32+AM32+AO32+AN32 -> 3091.9412
B33: Raccordement AC | C33: 1 | D33: Forfait | E33: =AB33 -> 3089.7794 | F33: =C33*E33 -> 3089.7794 | H33: =$H$11 -> 500 | I33: =I11 -> 0 | J33: =H33*$J$4 -> 15 | K33: 0 | L33: =H33*(1-$K33) -> 500 | M33: =I33*(1-$K33) -> 0 | N33: =J33*(1-$K33) -> 15 | O33: =(L33+M33+N33) -> 515 | P33: =O33*$P$4 -> 0 | Q33: =(O33+P33)*$Q$4 -> 0 | R33: =(O33+P33)*$R$4 -> 10.3 | S33: =(O33+P33)*$S$4 -> 25.75 | T33: =SUM(O33:S33) -> 551.05 | U33: =5*$U$5+600+500 -> 1550 | V33: =V22 -> 0 | W33: =W22 -> 0 | X33: =SUM(U33:W33) -> 1550 | Y33: =$Y$4/(1-$Y$4)*(T33+X33+Z33+AA33) -> 463.46691 | Z33: =T33*$Z$4 -> 137.7625 | AA33: =X33*$AA$4 -> 387.5 | AB33: =T33+X33+Y33+Z33+AA33 -> 3089.7794 | AC33: =O33*$C33 -> 515 | AD33: =P33*$C33 -> 0 | AE33: =Q33*$C33 -> 0 | AF33: =R33*$C33 -> 10.3 | AG33: =S33*$C33 -> 25.75 | AH33: =T33*$C33 -> 551.05 | AI33: =U33*$C33 -> 1550 | AJ33: =V33*$C33 -> 0 | ... AO33: =AA33*$C33 -> 387.5 | AP33: =AM33+AK33 -> 463.46691 | AQ33: =AM33+AL33+AH33 -> 2564.5169 | AR33: =AO33+AN33 -> 525.2625 | AS33: =AH33+AL33+AM33+AO33+AN33 -> 3089.7794
B34: Echafaudage jusqu'à 6m de hauteur | C34: 1 | D34: Forfait | E34: =AB34 -> 2308.5 | F34: =C34*E34 -> 2308.5 | H34: =$H$12 -> 1300 | I34: =I12 -> 200 | J34: =H34*$J$4 -> 39 | K34: 0 | L34: =H34*(1-$K34) -> 1300 | M34: =I34*(1-$K34) -> 200 | N34: =J34*(1-$K34) -> 39 | O34: =(L34+M34+N34) -> 1539 | P34: =O34*$P$4 -> 0 | Q34: =(O34+P34)*$Q$4 -> 0 | R34: =(O34+P34)*$R$4 -> 30.78 | S34: 0 | T34: =SUM(O34:S34) -> 1569.78 | U34: 0 | V34: =V23 -> 0 | W34: =W23 -> 0 | X34: =SUM(U34:W34) -> 0 | Y34: =$Y$4/(1-$Y$4)*(T34+X34+Z34+AA34) -> 346.275 | Z34: =T34*$Z$4 -> 392.445 | AA34: =X34*$AA$4 -> 0 | AB34: =T34+X34+Y34+Z34+AA34 -> 2308.5 | AC34: =O34*$C34 -> 1539 | AD34: =P34*$C34 -> 0 | AE34: =Q34*$C34 -> 0 | AF34: =R34*$C34 -> 30.78 | AG34: =S34*$C34 -> 0 | AH34: =T34*$C34 -> 1569.78 | AI34: =U34*$C34 -> 0 | AJ34: =V34*$C34 -> 0 | ... AO34: =AA34*$C34 -> 0 | AP34: =AM34+AK34 -> 346.275 | AQ34: =AM34+AL34+AH34 -> 1916.055 | AR34: =AO34+AN34 -> 392.445 | AS34: =AH34+AL34+AM34+AO34+AN34 -> 2308.5
B35: Travaux administratifs | C35: 1 | D35: Forfait | E35: =AB35 -> 900 | F35: =C35*E35 -> 900 | H35: 0 | I35: 0 | J35: =H35*$J$4 -> 0 | K35: 0 | L35: =H35*(1-$K35) -> 0 | M35: =I35*(1-$K35) -> 0 | N35: =J35*(1-$K35) -> 0 | O35: =(L35+M35+N35) -> 0 | P35: =O35*$P$4 -> 0 | Q35: =(O35+P35)*$Q$4 -> 0 | R35: =(O35+P35)*$R$4 -> 0 | S35: 0 | T35: =SUM(O35:S35) -> 0 | U35: 0 | V35: =V24 -> 0 | W35: =W24 -> 900 | X35: =SUM(U35:W35) -> 900 | Y35: 0 | Z35: =T35*$Z$4 -> 0 | AA35: 0 | AB35: =T35+X35+Y35+Z35+AA35 -> 900 | AC35: =O35*$C35 -> 0 | AD35: =P35*$C35 -> 0 | AE35: =Q35*$C35 -> 0 | AF35: =R35*$C35 -> 0 | AG35: =S35*$C35 -> 0 | AH35: =T35*$C35 -> 0 | AI35: =U35*$C35 -> 0 | AJ35: =V35*$C35 -> 0 | ... AO35: =AA35*$C35 -> 0 | AP35: =AM35+AK35 -> 900 | AQ35: =AM35+AL35+AH35 -> 900 | AR35: =AO35+AN35 -> 0 | AS35: =AH35+AL35+AM35+AO35+AN35 -> 900
B36: Travaux électriques, contrôle et Pronovo | C36: 1 | D36: Forfait | E36: =AB36 -> 1200 | F36: =C36*E36 -> 1200 | H36: 0 | I36: 0 | J36: =H36*$J$4 -> 0 | K36: 0 | L36: =H36*(1-$K36) -> 0 | M36: =I36*(1-$K36) -> 0 | N36: =J36*(1-$K36) -> 0 | O36: =(L36+M36+N36) -> 0 | P36: =O36*$P$4 -> 0 | Q36: =(O36+P36)*$Q$4 -> 0 | R36: =(O36+P36)*$R$4 -> 0 | S36: 0 | T36: =SUM(O36:S36) -> 0 | U36: 0 | V36: =V25 -> 1200 | W36: =W25 -> 0 | X36: =SUM(U36:W36) -> 1200 | Y36: 0 | Z36: =T36*$Z$4 -> 0 | AA36: 0 | AB36: =T36+X36+Y36+Z36+AA36 -> 1200 | AC36: =O36*$C36 -> 0 | AD36: =P36*$C36 -> 0 | AE36: =Q36*$C36 -> 0 | AF36: =R36*$C36 -> 0 | AG36: =S36*$C36 -> 0 | AH36: =T36*$C36 -> 0 | AI36: =U36*$C36 -> 0 | AJ36: =V36*$C36 -> 1200 | ... AO36: =AA36*$C36 -> 0 | AP36: =AM36+AK36 -> 0 | AQ36: =AM36+AL36+AH36 -> 1200 | AR36: =AO36+AN36 -> 0 | AS36: =AH36+AL36+AM36+AO36+AN36 -> 1200
A38: 13 | B38: Panneaux | C38: Puissance: | D38: =ROUNDUP((A38*465)/1000,2) -> 6.05 | F38: =SUM(F39:F48) -> 18106.132 | AC38: =+SUM(AC39:AC48) -> 6938.43 | AD38: =+SUM(AD39:AD48) -> 0 | AE38: =+SUM(AE39:AE48) -> 0 | AF38: =+SUM(AF39:AF48) -> 138.7686 | AG38: =+SUM(AG39:AG48) -> 269.9715 | AH38: =+SUM(AH39:AH48) -> 7347.1701 | AI38: =+SUM(AI39:AI48) -> 3537 | AJ38: =+SUM(AJ39:AJ48) -> 1200 | ... AS38: =+SUM(AS39:AS48) -> 18106.132 | AT38: =IF(F38=AS38,"Matching","Not Matching") -> Matching | AU38: =SUM(AC38:AG38) -> 7347.1701 | AV38: =AU38/AS38 -> 0.40578352 | AW38: =AI38 -> 3537 | AX38: =AW38/AS38 -> 0.19534818 | AY38: =AJ38 -> 1200 | AZ38: =AY38/AS38 -> 0.066275887 | BA38: =AK38+AM38 -> 3300.9199 | BB38: =BA38/AS38 -> 0.1823095 | BC38: =AN38+AO38 -> 2721.0425 | BD38: =BC38/AS38 -> 0.15028292 | BE38: =IF((AU38+AW38+AY38+BA38+BC38)=AS38,"Matching","Not Matching") -> Matching | BF38: =AQ38 -> 15385.09 | BG38: =BF38/AS38 -> 0.84971708 | BH38: =AR38 -> 2721.0425 | BI38: =BH38/AS38 -> 0.15028292 | BJ38: =IF((BH38+BF38)=AS38,"Matching","Not Matching") -> Matching | BK38: =AS38*1.081 -> 19572.729 | BL38: =ROUND(BK38,-1) -> 19570 | BM38: =D38*380 -> 2299 | BN38: =BK38-BM38 -> 17273.729 | BO38: =BK38/D38 -> 3235.1619
I39: Parafoudres
B40: ="Panneau solaire "&G40 -> Panneau solaire LONGi Hi-MO X10 Artist LR7-54HVB-485M | C40: =A38 -> 13 | D40: U | E40: =AB40 -> 266.65685 | F40: =C40*E40 -> 3466.539 | G40: =$G$7 -> LONGi Hi-MO X10 Artist LR7-54HVB-485M | H40: =$H$7 -> 105.55 | I40: =$I$7 -> 0 | J40: =H40*$J$4 -> 3.1665 | K40: 0 | L40: =H40*(1-$K40) -> 105.55 | M40: =I40*(1-$K40) -> 0 | N40: =J40*(1-$K40) -> 3.1665 | O40: =(L40+M40+N40) -> 108.7165 | P40: =O40*$P$4 -> 0 | Q40: =(O40+P40)*$Q$4 -> 0 | R40: =(O40+P40)*$R$4 -> 2.17433 | S40: =(O40+P40)*$S$4 -> 5.435825 | T40: =SUM(O40:S40) -> 116.32665 | U40: =1*$U$4 -> 65 | V40: =V29 -> 0 | W40: =W29 -> 0 | X40: =SUM(U40:W40) -> 65 | Y40: =$Y$4/(1-$Y$4)*(T40+X40+Z40+AA40) -> 39.998527 | Z40: =T40*$Z$4 -> 29.081664 | AA40: =X40*$AA$4 -> 16.25 | AB40: =T40+X40+Y40+Z40+AA40 -> 266.65685 | AC40: =O40*$C40 -> 1413.3145 | AD40: =P40*$C40 -> 0 | AE40: =Q40*$C40 -> 0 | AF40: =R40*$C40 -> 28.26629 | AG40: =S40*$C40 -> 70.665725 | AH40: =T40*$C40 -> 1512.2465 | AI40: =U40*$C40 -> 845 | AJ40: =V40*$C40 -> 0 | ... AO40: =AA40*$C40 -> 211.25 | AP40: =AM40+AK40 -> 519.98085 | AQ40: =AM40+AL40+AH40 -> 2877.2274 | AR40: =AO40+AN40 -> 589.31163 | AS40: =AH40+AL40+AM40+AO40+AN40 -> 3466.539
B41: ="Onduleur Fronius "&G41 -> Onduleur Fronius Symo GEN24 6.0 SC | C41: 1 | D41: U | E41: =AB41 -> 3133.4317 | F41: =C41*E41 -> 3133.4317 | G41: =$G$8 -> Symo GEN24 6.0 SC | H41: =$H$8 -> 1333.85 | I41: =$I$8 -> 449.25 | J41: =H41*$J$4 -> 40.0155 | K41: 0 | L41: =H41*(1-$K41) -> 1333.85 | M41: =I41*(1-$K41) -> 449.25 | N41: =J41*(1-$K41) -> 40.0155 | O41: =(L41+M41+N41) -> 1823.1155 | P41: =O41*$P$4 -> 0 | Q41: =(O41+P41)*$Q$4 -> 0 | R41: =(O41+P41)*$R$4 -> 36.46231 | S41: =(O41+P41)*$S$4 -> 91.155775 | T41: =SUM(O41:S41) -> 1950.7336 | U41: =2*$U$5 -> 180 | V41: =V30 -> 0 | W41: =W30 -> 0 | X41: =SUM(U41:W41) -> 180 | Y41: =$Y$4/(1-$Y$4)*(T41+X41+Z41+AA41) -> 470.01476 | Z41: =T41*$Z$4 -> 487.6834 | AA41: =X41*$AA$4 -> 45 | AB41: =T41+X41+Y41+Z41+AA41 -> 3133.4317 | AC41: =O41*$C41 -> 1823.1155 | AD41: =P41*$C41 -> 0 | AE41: =Q41*$C41 -> 0 | AF41: =R41*$C41 -> 36.46231 | AG41: =S41*$C41 -> 91.155775 | AH41: =T41*$C41 -> 1950.7336 | AI41: =U41*$C41 -> 180 | AJ41: =V41*$C41 -> 0 | ... AO41: =AA41*$C41 -> 45 | AP41: =AM41+AK41 -> 470.01476 | AQ41: =AM41+AL41+AH41 -> 2600.7483 | AR41: =AO41+AN41 -> 532.6834 | AS41: =AH41+AL41+AM41+AO41+AN41 -> 3133.4317
B42: Accessoires | C42: 1 | D42: Forfait | E42: =AB42 -> 658.27941 | F42: =C42*E42 -> 658.27941 | H42: =$H$9 -> 300 | I42: =I9 -> 0 | J42: =H42*$J$4 -> 9 | K42: 0 | L42: =H42*(1-$K42) -> 300 | M42: =I42*(1-$K42) -> 0 | N42: =J42*(1-$K42) -> 9 | O42: =(L42+M42+N42) -> 309 | P42: =O42*$P$4 -> 0 | Q42: =(O42+P42)*$Q$4 -> 0 | R42: =(O42+P42)*$R$4 -> 6.18 | S42: =(O42+P42)*$S$4 -> 15.45 | T42: =SUM(O42:S42) -> 330.63 | U42: =(C40/10)*$U$5 -> 117 | V42: =V31 -> 0 | W42: =W31 -> 0 | X42: =SUM(U42:W42) -> 117 | Y42: =$Y$4/(1-$Y$4)*(T42+X42+Z42+AA42) -> 98.741912 | Z42: =T42*$Z$4 -> 82.6575 | AA42: =X42*$AA$4 -> 29.25 | AB42: =T42+X42+Y42+Z42+AA42 -> 658.27941 | AC42: =O42*$C42 -> 309 | AD42: =P42*$C42 -> 0 | AE42: =Q42*$C42 -> 0 | AF42: =R42*$C42 -> 6.18 | AG42: =S42*$C42 -> 15.45 | AH42: =T42*$C42 -> 330.63 | AI42: =U42*$C42 -> 117 | AJ42: =V42*$C42 -> 0 | ... AO42: =AA42*$C42 -> 29.25 | AP42: =AM42+AK42 -> 98.741912 | AQ42: =AM42+AL42+AH42 -> 546.37191 | AR42: =AO42+AN42 -> 111.9075 | AS42: =AH42+AL42+AM42+AO42+AN42 -> 658.27941
B43: Système de montage sur tuile | C43: =A38 -> 13 | D43: U | E43: =AB43 -> 257.66176 | F43: =C43*E43 -> 3349.6029 | H43: =$H$10 -> 100 | I43: =I10 -> 0 | J43: =H43*$J$4 -> 3 | K43: 0 | L43: =H43*(1-$K43) -> 100 | M43: =I43*(1-$K43) -> 0 | N43: =J43*(1-$K43) -> 3 | O43: =(L43+M43+N43) -> 103 | P43: =O43*$P$4 -> 0 | Q43: =(O43+P43)*$Q$4 -> 0 | R43: =(O43+P43)*$R$4 -> 2.06 | S43: =(O43+P43)*$S$4 -> 5.15 | T43: =SUM(O43:S43) -> 110.21 | U43: =1*$U$4 -> 65 | V43: =V32 -> 0 | W43: =W32 -> 0 | X43: =SUM(U43:W43) -> 65 | Y43: =$Y$4/(1-$Y$4)*(T43+X43+Z43+AA43) -> 38.649265 | Z43: =T43*$Z$4 -> 27.5525 | AA43: =X43*$AA$4 -> 16.25 | AB43: =T43+X43+Y43+Z43+AA43 -> 257.66176 | AC43: =O43*$C43 -> 1339 | AD43: =P43*$C43 -> 0 | AE43: =Q43*$C43 -> 0 | AF43: =R43*$C43 -> 26.78 | AG43: =S43*$C43 -> 66.95 | AH43: =T43*$C43 -> 1432.73 | AI43: =U43*$C43 -> 845 | AJ43: =V43*$C43 -> 0 | ... AO43: =AA43*$C43 -> 211.25 | AP43: =AM43+AK43 -> 502.44044 | AQ43: =AM43+AL43+AH43 -> 2780.1704 | AR43: =AO43+AN43 -> 569.4325 | AS43: =AH43+AL43+AM43+AO43+AN43 -> 3349.6029
B44: Raccordement AC | C44: 1 | D44: Forfait | E44: =AB44 -> 3089.7794 | F44: =C44*E44 -> 3089.7794 | H44: =$H$11 -> 500 | I44: =I11 -> 0 | J44: =H44*$J$4 -> 15 | K44: 0 | L44: =H44*(1-$K44) -> 500 | M44: =I44*(1-$K44) -> 0 | N44: =J44*(1-$K44) -> 15 | O44: =(L44+M44+N44) -> 515 | P44: =O44*$P$4 -> 0 | Q44: =(O44+P44)*$Q$4 -> 0 | R44: =(O44+P44)*$R$4 -> 10.3 | S44: =(O44+P44)*$S$4 -> 25.75 | T44: =SUM(O44:S44) -> 551.05 | U44: =5*$U$5+600+500 -> 1550 | V44: =V33 -> 0 | W44: =W33 -> 0 | X44: =SUM(U44:W44) -> 1550 | Y44: =$Y$4/(1-$Y$4)*(T44+X44+Z44+AA44) -> 463.46691 | Z44: =T44*$Z$4 -> 137.7625 | AA44: =X44*$AA$4 -> 387.5 | AB44: =T44+X44+Y44+Z44+AA44 -> 3089.7794 | AC44: =O44*$C44 -> 515 | AD44: =P44*$C44 -> 0 | AE44: =Q44*$C44 -> 0 | AF44: =R44*$C44 -> 10.3 | AG44: =S44*$C44 -> 25.75 | AH44: =T44*$C44 -> 551.05 | AI44: =U44*$C44 -> 1550 | AJ44: =V44*$C44 -> 0 | ... AO44: =AA44*$C44 -> 387.5 | AP44: =AM44+AK44 -> 463.46691 | AQ44: =AM44+AL44+AH44 -> 2564.5169 | AR44: =AO44+AN44 -> 525.2625 | AS44: =AH44+AL44+AM44+AO44+AN44 -> 3089.7794
B45: Echafaudage jusqu'à 6m de hauteur | C45: 1 | D45: Forfait | E45: =AB45 -> 2308.5 | F45: =C45*E45 -> 2308.5 | H45: =$H$12 -> 1300 | I45: =I12 -> 200 | J45: =H45*$J$4 -> 39 | K45: 0 | L45: =H45*(1-$K45) -> 1300 | M45: =I45*(1-$K45) -> 200 | N45: =J45*(1-$K45) -> 39 | O45: =(L45+M45+N45) -> 1539 | P45: =O45*$P$4 -> 0 | Q45: =(O45+P45)*$Q$4 -> 0 | R45: =(O45+P45)*$R$4 -> 30.78 | S45: 0 | T45: =SUM(O45:S45) -> 1569.78 | U45: 0 | V45: =V34 -> 0 | W45: =W34 -> 0 | X45: =SUM(U45:W45) -> 0 | Y45: =$Y$4/(1-$Y$4)*(T45+X45+Z45+AA45) -> 346.275 | Z45: =T45*$Z$4 -> 392.445 | AA45: =X45*$AA$4 -> 0 | AB45: =T45+X45+Y45+Z45+AA45 -> 2308.5 | AC45: =O45*$C45 -> 1539 | AD45: =P45*$C45 -> 0 | AE45: =Q45*$C45 -> 0 | AF45: =R45*$C45 -> 30.78 | AG45: =S45*$C45 -> 0 | AH45: =T45*$C45 -> 1569.78 | AI45: =U45*$C45 -> 0 | AJ45: =V45*$C45 -> 0 | ... AO45: =AA45*$C45 -> 0 | AP45: =AM45+AK45 -> 346.275 | AQ45: =AM45+AL45+AH45 -> 1916.055 | AR45: =AO45+AN45 -> 392.445 | AS45: =AH45+AL45+AM45+AO45+AN45 -> 2308.5
B46: Travaux administratifs | C46: 1 | D46: Forfait | E46: =AB46 -> 900 | F46: =C46*E46 -> 900 | H46: 0 | I46: 0 | J46: =H46*$J$4 -> 0 | K46: 0 | L46: =H46*(1-$K46) -> 0 | M46: =I46*(1-$K46) -> 0 | N46: =J46*(1-$K46) -> 0 | O46: =(L46+M46+N46) -> 0 | P46: =O46*$P$4 -> 0 | Q46: =(O46+P46)*$Q$4 -> 0 | R46: =(O46+P46)*$R$4 -> 0 | S46: 0 | T46: =SUM(O46:S46) -> 0 | U46: 0 | V46: =V35 -> 0 | W46: =W35 -> 900 | X46: =SUM(U46:W46) -> 900 | Y46: 0 | Z46: =T46*$Z$4 -> 0 | AA46: 0 | AB46: =T46+X46+Y46+Z46+AA46 -> 900 | AC46: =O46*$C46 -> 0 | AD46: =P46*$C46 -> 0 | AE46: =Q46*$C46 -> 0 | AF46: =R46*$C46 -> 0 | AG46: =S46*$C46 -> 0 | AH46: =T46*$C46 -> 0 | AI46: =U46*$C46 -> 0 | AJ46: =V46*$C46 -> 0 | ... AO46: =AA46*$C46 -> 0 | AP46: =AM46+AK46 -> 900 | AQ46: =AM46+AL46+AH46 -> 900 | AR46: =AO46+AN46 -> 0 | AS46: =AH46+AL46+AM46+AO46+AN46 -> 900
B47: Travaux électriques, contrôle et Pronovo | C47: 1 | D47: Forfait | E47: =AB47 -> 1200 | F47: =C47*E47 -> 1200 | H47: 0 | I47: 0 | J47: =H47*$J$4 -> 0 | K47: 0 | L47: =H47*(1-$K47) -> 0 | M47: =I47*(1-$K47) -> 0 | N47: =J47*(1-$K47) -> 0 | O47: =(L47+M47+N47) -> 0 | P47: =O47*$P$4 -> 0 | Q47: =(O47+P47)*$Q$4 -> 0 | R47: =(O47+P47)*$R$4 -> 0 | S47: 0 | T47: =SUM(O47:S47) -> 0 | U47: 0 | V47: =V36 -> 1200 | W47: =W36 -> 0 | X47: =SUM(U47:W47) -> 1200 | Y47: 0 | Z47: =T47*$Z$4 -> 0 | AA47: 0 | AB47: =T47+X47+Y47+Z47+AA47 -> 1200 | AC47: =O47*$C47 -> 0 | AD47: =P47*$C47 -> 0 | AE47: =Q47*$C47 -> 0 | AF47: =R47*$C47 -> 0 | AG47: =S47*$C47 -> 0 | AH47: =T47*$C47 -> 0 | AI47: =U47*$C47 -> 0 | AJ47: =V47*$C47 -> 1200 | ... AO47: =AA47*$C47 -> 0 | AP47: =AM47+AK47 -> 0 | AQ47: =AM47+AL47+AH47 -> 1200 | AR47: =AO47+AN47 -> 0 | AS47: =AH47+AL47+AM47+AO47+AN47 -> 1200
A49: 14 | B49: Panneaux | C49: Puissance: | D49: =ROUNDUP((A49*465)/1000,2) -> 6.51 | F49: =SUM(F50:F59) -> 18643.686 | AC49: =+SUM(AC50:AC59) -> 7150.1465 | AD49: =+SUM(AD50:AD59) -> 0 | AE49: =+SUM(AE50:AE59) -> 0 | AF49: =+SUM(AF50:AF59) -> 143.00293 | AG49: =+SUM(AG50:AG59) -> 280.55732 | AH49: =+SUM(AH50:AH59) -> 7573.7068 | AI49: =+SUM(AI50:AI59) -> 3676 | AJ49: =+SUM(AJ50:AJ59) -> 1200 | ... AS49: =+SUM(AS50:AS59) -> 18643.686 | AT49: =IF(F49=AS49,"Matching","Not Matching") -> Matching | AU49: =SUM(AC49:AG49) -> 7573.7068 | AV49: =AU49/AS49 -> 0.4062344 | AW49: =AI49 -> 3676 | AX49: =AW49/AS49 -> 0.19717131 | AY49: =AJ49 -> 1200 | AZ49: =AY49/AS49 -> 0.064364953 | BA49: =AK49+AM49 -> 3381.553 | BB49: =BA49/AS49 -> 0.18137791 | BC49: =AN49+AO49 -> 2812.4267 | BD49: =BC49/AS49 -> 0.15085143 | BE49: =IF((AU49+AW49+AY49+BA49+BC49)=AS49,"Matching","Not Matching") -> Matching | BF49: =AQ49 -> 15831.26 | BG49: =BF49/AS49 -> 0.84914857 | BH49: =AR49 -> 2812.4267 | BI49: =BH49/AS49 -> 0.15085143 | BJ49: =IF((BH49+BF49)=AS49,"Matching","Not Matching") -> Matching | BK49: =AS49*1.081 -> 20153.825 | BL49: =ROUND(BK49,-1) -> 20150 | BM49: =D49*380 -> 2473.8 | BN49: =BK49-BM49 -> 17680.025 | BO49: =BK49/D49 -> 3095.8257
I50: Parafoudres
B51: ="Panneau solaire "&G51 -> Panneau solaire LONGi Hi-MO X10 Artist LR7-54HVB-485M | C51: =A49 -> 14 | D51: U | E51: =AB51 -> 266.65685 | F51: =C51*E51 -> 3733.1958 | G51: =$G$7 -> LONGi Hi-MO X10 Artist LR7-54HVB-485M | H51: =$H$7 -> 105.55 | I51: =$I$7 -> 0 | J51: =H51*$J$4 -> 3.1665 | K51: 0 | L51: =H51*(1-$K51) -> 105.55 | M51: =I51*(1-$K51) -> 0 | N51: =J51*(1-$K51) -> 3.1665 | O51: =(L51+M51+N51) -> 108.7165 | P51: =O51*$P$4 -> 0 | Q51: =(O51+P51)*$Q$4 -> 0 | R51: =(O51+P51)*$R$4 -> 2.17433 | S51: =(O51+P51)*$S$4 -> 5.435825 | T51: =SUM(O51:S51) -> 116.32665 | U51: =1*$U$4 -> 65 | V51: =V40 -> 0 | W51: =W40 -> 0 | X51: =SUM(U51:W51) -> 65 | Y51: =$Y$4/(1-$Y$4)*(T51+X51+Z51+AA51) -> 39.998527 | Z51: =T51*$Z$4 -> 29.081664 | AA51: =X51*$AA$4 -> 16.25 | AB51: =T51+X51+Y51+Z51+AA51 -> 266.65685 | AC51: =O51*$C51 -> 1522.031 | AD51: =P51*$C51 -> 0 | AE51: =Q51*$C51 -> 0 | AF51: =R51*$C51 -> 30.44062 | AG51: =S51*$C51 -> 76.10155 | AH51: =T51*$C51 -> 1628.5732 | AI51: =U51*$C51 -> 910 | AJ51: =V51*$C51 -> 0 | ... AO51: =AA51*$C51 -> 227.5 | AP51: =AM51+AK51 -> 559.97938 | AQ51: =AM51+AL51+AH51 -> 3098.5525 | AR51: =AO51+AN51 -> 634.64329 | AS51: =AH51+AL51+AM51+AO51+AN51 -> 3733.1958
B52: ="Onduleur Fronius "&G52 -> Onduleur Fronius Symo GEN24 6.0 SC | C52: 1 | D52: U | E52: =AB52 -> 3133.4317 | F52: =C52*E52 -> 3133.4317 | G52: =$G$8 -> Symo GEN24 6.0 SC | H52: =$H$8 -> 1333.85 | I52: =$I$8 -> 449.25 | J52: =H52*$J$4 -> 40.0155 | K52: 0 | L52: =H52*(1-$K52) -> 1333.85 | M52: =I52*(1-$K52) -> 449.25 | N52: =J52*(1-$K52) -> 40.0155 | O52: =(L52+M52+N52) -> 1823.1155 | P52: =O52*$P$4 -> 0 | Q52: =(O52+P52)*$Q$4 -> 0 | R52: =(O52+P52)*$R$4 -> 36.46231 | S52: =(O52+P52)*$S$4 -> 91.155775 | T52: =SUM(O52:S52) -> 1950.7336 | U52: =2*$U$5 -> 180 | V52: =V41 -> 0 | W52: =W41 -> 0 | X52: =SUM(U52:W52) -> 180 | Y52: =$Y$4/(1-$Y$4)*(T52+X52+Z52+AA52) -> 470.01476 | Z52: =T52*$Z$4 -> 487.6834 | AA52: =X52*$AA$4 -> 45 | AB52: =T52+X52+Y52+Z52+AA52 -> 3133.4317 | AC52: =O52*$C52 -> 1823.1155 | AD52: =P52*$C52 -> 0 | AE52: =Q52*$C52 -> 0 | AF52: =R52*$C52 -> 36.46231 | AG52: =S52*$C52 -> 91.155775 | AH52: =T52*$C52 -> 1950.7336 | AI52: =U52*$C52 -> 180 | AJ52: =V52*$C52 -> 0 | ... AO52: =AA52*$C52 -> 45 | AP52: =AM52+AK52 -> 470.01476 | AQ52: =AM52+AL52+AH52 -> 2600.7483 | AR52: =AO52+AN52 -> 532.6834 | AS52: =AH52+AL52+AM52+AO52+AN52 -> 3133.4317
B53: Accessoires | C53: 1 | D53: Forfait | E53: =AB53 -> 671.51471 | F53: =C53*E53 -> 671.51471 | H53: =$H$9 -> 300 | I53: =I9 -> 0 | J53: =H53*$J$4 -> 9 | K53: 0 | L53: =H53*(1-$K53) -> 300 | M53: =I53*(1-$K53) -> 0 | N53: =J53*(1-$K53) -> 9 | O53: =(L53+M53+N53) -> 309 | P53: =O53*$P$4 -> 0 | Q53: =(O53+P53)*$Q$4 -> 0 | R53: =(O53+P53)*$R$4 -> 6.18 | S53: =(O53+P53)*$S$4 -> 15.45 | T53: =SUM(O53:S53) -> 330.63 | U53: =(C51/10)*$U$5 -> 126 | V53: =V42 -> 0 | W53: =W42 -> 0 | X53: =SUM(U53:W53) -> 126 | Y53: =$Y$4/(1-$Y$4)*(T53+X53+Z53+AA53) -> 100.72721 | Z53: =T53*$Z$4 -> 82.6575 | AA53: =X53*$AA$4 -> 31.5 | AB53: =T53+X53+Y53+Z53+AA53 -> 671.51471 | AC53: =O53*$C53 -> 309 | AD53: =P53*$C53 -> 0 | AE53: =Q53*$C53 -> 0 | AF53: =R53*$C53 -> 6.18 | AG53: =S53*$C53 -> 15.45 | AH53: =T53*$C53 -> 330.63 | AI53: =U53*$C53 -> 126 | AJ53: =V53*$C53 -> 0 | ... AO53: =AA53*$C53 -> 31.5 | AP53: =AM53+AK53 -> 100.72721 | AQ53: =AM53+AL53+AH53 -> 557.35721 | AR53: =AO53+AN53 -> 114.1575 | AS53: =AH53+AL53+AM53+AO53+AN53 -> 671.51471
B54: Système de montage sur tuile | C54: =A49 -> 14 | D54: U | E54: =AB54 -> 257.66176 | F54: =C54*E54 -> 3607.2647 | H54: =$H$10 -> 100 | I54: =I10 -> 0 | J54: =H54*$J$4 -> 3 | K54: 0 | L54: =H54*(1-$K54) -> 100 | M54: =I54*(1-$K54) -> 0 | N54: =J54*(1-$K54) -> 3 | O54: =(L54+M54+N54) -> 103 | P54: =O54*$P$4 -> 0 | Q54: =(O54+P54)*$Q$4 -> 0 | R54: =(O54+P54)*$R$4 -> 2.06 | S54: =(O54+P54)*$S$4 -> 5.15 | T54: =SUM(O54:S54) -> 110.21 | U54: =1*$U$4 -> 65 | V54: =V43 -> 0 | W54: =W43 -> 0 | X54: =SUM(U54:W54) -> 65 | Y54: =$Y$4/(1-$Y$4)*(T54+X54+Z54+AA54) -> 38.649265 | Z54: =T54*$Z$4 -> 27.5525 | AA54: =X54*$AA$4 -> 16.25 | AB54: =T54+X54+Y54+Z54+AA54 -> 257.66176 | AC54: =O54*$C54 -> 1442 | AD54: =P54*$C54 -> 0 | AE54: =Q54*$C54 -> 0 | AF54: =R54*$C54 -> 28.84 | AG54: =S54*$C54 -> 72.1 | AH54: =T54*$C54 -> 1542.94 | AI54: =U54*$C54 -> 910 | AJ54: =V54*$C54 -> 0 | ... AO54: =AA54*$C54 -> 227.5 | AP54: =AM54+AK54 -> 541.08971 | AQ54: =AM54+AL54+AH54 -> 2994.0297 | AR54: =AO54+AN54 -> 613.235 | AS54: =AH54+AL54+AM54+AO54+AN54 -> 3607.2647
B55: Raccordement AC | C55: 1 | D55: Forfait | E55: =AB55 -> 3089.7794 | F55: =C55*E55 -> 3089.7794 | H55: =$H$11 -> 500 | I55: =I11 -> 0 | J55: =H55*$J$4 -> 15 | K55: 0 | L55: =H55*(1-$K55) -> 500 | M55: =I55*(1-$K55) -> 0 | N55: =J55*(1-$K55) -> 15 | O55: =(L55+M55+N55) -> 515 | P55: =O55*$P$4 -> 0 | Q55: =(O55+P55)*$Q$4 -> 0 | R55: =(O55+P55)*$R$4 -> 10.3 | S55: =(O55+P55)*$S$4 -> 25.75 | T55: =SUM(O55:S55) -> 551.05 | U55: =5*$U$5+600+500 -> 1550 | V55: =V44 -> 0 | W55: =W44 -> 0 | X55: =SUM(U55:W55) -> 1550 | Y55: =$Y$4/(1-$Y$4)*(T55+X55+Z55+AA55) -> 463.46691 | Z55: =T55*$Z$4 -> 137.7625 | AA55: =X55*$AA$4 -> 387.5 | AB55: =T55+X55+Y55+Z55+AA55 -> 3089.7794 | AC55: =O55*$C55 -> 515 | AD55: =P55*$C55 -> 0 | AE55: =Q55*$C55 -> 0 | AF55: =R55*$C55 -> 10.3 | AG55: =S55*$C55 -> 25.75 | AH55: =T55*$C55 -> 551.05 | AI55: =U55*$C55 -> 1550 | AJ55: =V55*$C55 -> 0 | ... AO55: =AA55*$C55 -> 387.5 | AP55: =AM55+AK55 -> 463.46691 | AQ55: =AM55+AL55+AH55 -> 2564.5169 | AR55: =AO55+AN55 -> 525.2625 | AS55: =AH55+AL55+AM55+AO55+AN55 -> 3089.7794
B56: Echafaudage jusqu'à 6m de hauteur | C56: 1 | D56: Forfait | E56: =AB56 -> 2308.5 | F56: =C56*E56 -> 2308.5 | H56: =$H$12 -> 1300 | I56: =I12 -> 200 | J56: =H56*$J$4 -> 39 | K56: 0 | L56: =H56*(1-$K56) -> 1300 | M56: =I56*(1-$K56) -> 200 | N56: =J56*(1-$K56) -> 39 | O56: =(L56+M56+N56) -> 1539 | P56: =O56*$P$4 -> 0 | Q56: =(O56+P56)*$Q$4 -> 0 | R56: =(O56+P56)*$R$4 -> 30.78 | S56: 0 | T56: =SUM(O56:S56) -> 1569.78 | U56: 0 | V56: =V45 -> 0 | W56: =W45 -> 0 | X56: =SUM(U56:W56) -> 0 | Y56: =$Y$4/(1-$Y$4)*(T56+X56+Z56+AA56) -> 346.275 | Z56: =T56*$Z$4 -> 392.445 | AA56: =X56*$AA$4 -> 0 | AB56: =T56+X56+Y56+Z56+AA56 -> 2308.5 | AC56: =O56*$C56 -> 1539 | AD56: =P56*$C56 -> 0 | AE56: =Q56*$C56 -> 0 | AF56: =R56*$C56 -> 30.78 | AG56: =S56*$C56 -> 0 | AH56: =T56*$C56 -> 1569.78 | AI56: =U56*$C56 -> 0 | AJ56: =V56*$C56 -> 0 | ... AO56: =AA56*$C56 -> 0 | AP56: =AM56+AK56 -> 346.275 | AQ56: =AM56+AL56+AH56 -> 1916.055 | AR56: =AO56+AN56 -> 392.445 | AS56: =AH56+AL56+AM56+AO56+AN56 -> 2308.5
B57: Travaux administratifs | C57: 1 | D57: Forfait | E57: =AB57 -> 900 | F57: =C57*E57 -> 900 | H57: 0 | I57: 0 | J57: =H57*$J$4 -> 0 | K57: 0 | L57: =H57*(1-$K57) -> 0 | M57: =I57*(1-$K57) -> 0 | N57: =J57*(1-$K57) -> 0 | O57: =(L57+M57+N57) -> 0 | P57: =O57*$P$4 -> 0 | Q57: =(O57+P57)*$Q$4 -> 0 | R57: =(O57+P57)*$R$4 -> 0 | S57: 0 | T57: =SUM(O57:S57) -> 0 | U57: 0 | V57: =V46 -> 0 | W57: =W46 -> 900 | X57: =SUM(U57:W57) -> 900 | Y57: 0 | Z57: =T57*$Z$4 -> 0 | AA57: 0 | AB57: =T57+X57+Y57+Z57+AA57 -> 900 | AC57: =O57*$C57 -> 0 | AD57: =P57*$C57 -> 0 | AE57: =Q57*$C57 -> 0 | AF57: =R57*$C57 -> 0 | AG57: =S57*$C57 -> 0 | AH57: =T57*$C57 -> 0 | AI57: =U57*$C57 -> 0 | AJ57: =V57*$C57 -> 0 | ... AO57: =AA57*$C57 -> 0 | AP57: =AM57+AK57 -> 900 | AQ57: =AM57+AL57+AH57 -> 900 | AR57: =AO57+AN57 -> 0 | AS57: =AH57+AL57+AM57+AO57+AN57 -> 900
B58: Travaux électriques, contrôle et Pronovo | C58: 1 | D58: Forfait | E58: =AB58 -> 1200 | F58: =C58*E58 -> 1200 | H58: 0 | I58: 0 | J58: =H58*$J$4 -> 0 | K58: 0 | L58: =H58*(1-$K58) -> 0 | M58: =I58*(1-$K58) -> 0 | N58: =J58*(1-$K58) -> 0 | O58: =(L58+M58+N58) -> 0 | P58: =O58*$P$4 -> 0 | Q58: =(O58+P58)*$Q$4 -> 0 | R58: =(O58+P58)*$R$4 -> 0 | S58: 0 | T58: =SUM(O58:S58) -> 0 | U58: 0 | V58: =V47 -> 1200 | W58: =W47 -> 0 | X58: =SUM(U58:W58) -> 1200 | Y58: 0 | Z58: =T58*$Z$4 -> 0 | AA58: 0 | AB58: =T58+X58+Y58+Z58+AA58 -> 1200 | AC58: =O58*$C58 -> 0 | AD58: =P58*$C58 -> 0 | AE58: =Q58*$C58 -> 0 | AF58: =R58*$C58 -> 0 | AG58: =S58*$C58 -> 0 | AH58: =T58*$C58 -> 0 | AI58: =U58*$C58 -> 0 | AJ58: =V58*$C58 -> 1200 | ... AO58: =AA58*$C58 -> 0 | AP58: =AM58+AK58 -> 0 | AQ58: =AM58+AL58+AH58 -> 1200 | AR58: =AO58+AN58 -> 0 | AS58: =AH58+AL58+AM58+AO58+AN58 -> 1200
A60: 15 | B60: Panneaux | C60: Puissance: | D60: =ROUNDUP((A60*465)/1000,2) -> 6.98 | F60: =SUM(F61:F70) -> 19181.24 | AC60: =+SUM(AC61:AC70) -> 7361.863 | AD60: =+SUM(AD61:AD70) -> 0 | AE60: =+SUM(AE61:AE70) -> 0 | AF60: =+SUM(AF61:AF70) -> 147.23726 | AG60: =+SUM(AG61:AG70) -> 291.14315 | AH60: =+SUM(AH61:AH70) -> 7800.2434 | AI60: =+SUM(AI61:AI70) -> 3815 | AJ60: =+SUM(AJ61:AJ70) -> 1200 | ... AS60: =+SUM(AS61:AS70) -> 19181.24 | AT60: =IF(F60=AS60,"Matching","Not Matching") -> Matching | AU60: =SUM(AC60:AG60) -> 7800.2434 | AV60: =AU60/AS60 -> 0.40666001 | AW60: =AI60 -> 3815 | AX60: =AW60/AS60 -> 0.19889225 | AY60: =AJ60 -> 1200 | AZ60: =AY60/AS60 -> 0.062561126 | BA60: =AK60+AM60 -> 3462.186 | BB60: =BA60/AS60 -> 0.18049855 | BC60: =AN60+AO60 -> 2903.8109 | BD60: =BC60/AS60 -> 0.15138806 | BE60: =IF((AU60+AW60+AY60+BA60+BC60)=AS60,"Matching","Not Matching") -> Matching | BF60: =AQ60 -> 16277.429 | BG60: =BF60/AS60 -> 0.84861194 | BH60: =AR60 -> 2903.8109 | BI60: =BH60/AS60 -> 0.15138806 | BJ60: =IF((BH60+BF60)=AS60,"Matching","Not Matching") -> Matching | BK60: =AS60*1.081 -> 20734.921 | BL60: =ROUND(BK60,-1) -> 20730 | BM60: =D60*380 -> 2652.4 | BN60: =BK60-BM60 -> 18082.521 | BO60: =BK60/D60 -> 2970.619
I61: Parafoudres
B62: ="Panneau solaire "&G62 -> Panneau solaire LONGi Hi-MO X10 Artist LR7-54HVB-485M | C62: =A60 -> 15 | D62: U | E62: =AB62 -> 266.65685 | F62: =C62*E62 -> 3999.8527 | G62: =$G$7 -> LONGi Hi-MO X10 Artist LR7-54HVB-485M | H62: =$H$7 -> 105.55 | I62: =$I$7 -> 0 | J62: =H62*$J$4 -> 3.1665 | K62: 0 | L62: =H62*(1-$K62) -> 105.55 | M62: =I62*(1-$K62) -> 0 | N62: =J62*(1-$K62) -> 3.1665 | O62: =(L62+M62+N62) -> 108.7165 | P62: =O62*$P$4 -> 0 | Q62: =(O62+P62)*$Q$4 -> 0 | R62: =(O62+P62)*$R$4 -> 2.17433 | S62: =(O62+P62)*$S$4 -> 5.435825 | T62: =SUM(O62:S62) -> 116.32665 | U62: =1*$U$4 -> 65 | V62: =V51 -> 0 | W62: =W51 -> 0 | X62: =SUM(U62:W62) -> 65 | Y62: =$Y$4/(1-$Y$4)*(T62+X62+Z62+AA62) -> 39.998527 | Z62: =T62*$Z$4 -> 29.081664 | AA62: =X62*$AA$4 -> 16.25 | AB62: =T62+X62+Y62+Z62+AA62 -> 266.65685 | AC62: =O62*$C62 -> 1630.7475 | AD62: =P62*$C62 -> 0 | AE62: =Q62*$C62 -> 0 | AF62: =R62*$C62 -> 32.61495 | AG62: =S62*$C62 -> 81.537375 | AH62: =T62*$C62 -> 1744.8998 | AI62: =U62*$C62 -> 975 | AJ62: =V62*$C62 -> 0 | ... AO62: =AA62*$C62 -> 243.75 | AP62: =AM62+AK62 -> 599.9779 | AQ62: =AM62+AL62+AH62 -> 3319.8777 | AR62: =AO62+AN62 -> 679.97496 | AS62: =AH62+AL62+AM62+AO62+AN62 -> 3999.8527
B63: ="Onduleur Fronius "&G63 -> Onduleur Fronius Symo GEN24 6.0 SC | C63: 1 | D63: U | E63: =AB63 -> 3133.4317 | F63: =C63*E63 -> 3133.4317 | G63: =$G$8 -> Symo GEN24 6.0 SC | H63: =$H$8 -> 1333.85 | I63: =$I$8 -> 449.25 | J63: =H63*$J$4 -> 40.0155 | K63: 0 | L63: =H63*(1-$K63) -> 1333.85 | M63: =I63*(1-$K63) -> 449.25 | N63: =J63*(1-$K63) -> 40.0155 | O63: =(L63+M63+N63) -> 1823.1155 | P63: =O63*$P$4 -> 0 | Q63: =(O63+P63)*$Q$4 -> 0 | R63: =(O63+P63)*$R$4 -> 36.46231 | S63: =(O63+P63)*$S$4 -> 91.155775 | T63: =SUM(O63:S63) -> 1950.7336 | U63: =2*$U$5 -> 180 | V63: =V52 -> 0 | W63: =W52 -> 0 | X63: =SUM(U63:W63) -> 180 | Y63: =$Y$4/(1-$Y$4)*(T63+X63+Z63+AA63) -> 470.01476 | Z63: =T63*$Z$4 -> 487.6834 | AA63: =X63*$AA$4 -> 45 | AB63: =T63+X63+Y63+Z63+AA63 -> 3133.4317 | AC63: =O63*$C63 -> 1823.1155 | AD63: =P63*$C63 -> 0 | AE63: =Q63*$C63 -> 0 | AF63: =R63*$C63 -> 36.46231 | AG63: =S63*$C63 -> 91.155775 | AH63: =T63*$C63 -> 1950.7336 | AI63: =U63*$C63 -> 180 | AJ63: =V63*$C63 -> 0 | ... AO63: =AA63*$C63 -> 45 | AP63: =AM63+AK63 -> 470.01476 | AQ63: =AM63+AL63+AH63 -> 2600.7483 | AR63: =AO63+AN63 -> 532.6834 | AS63: =AH63+AL63+AM63+AO63+AN63 -> 3133.4317
B64: Accessoires | C64: 1 | D64: Forfait | E64: =AB64 -> 684.75 | F64: =C64*E64 -> 684.75 | H64: =$H$9 -> 300 | I64: =I9 -> 0 | J64: =H64*$J$4 -> 9 | K64: 0 | L64: =H64*(1-$K64) -> 300 | M64: =I64*(1-$K64) -> 0 | N64: =J64*(1-$K64) -> 9 | O64: =(L64+M64+N64) -> 309 | P64: =O64*$P$4 -> 0 | Q64: =(O64+P64)*$Q$4 -> 0 | R64: =(O64+P64)*$R$4 -> 6.18 | S64: =(O64+P64)*$S$4 -> 15.45 | T64: =SUM(O64:S64) -> 330.63 | U64: =(C62/10)*$U$5 -> 135 | V64: =V53 -> 0 | W64: =W53 -> 0 | X64: =SUM(U64:W64) -> 135 | Y64: =$Y$4/(1-$Y$4)*(T64+X64+Z64+AA64) -> 102.7125 | Z64: =T64*$Z$4 -> 82.6575 | AA64: =X64*$AA$4 -> 33.75 | AB64: =T64+X64+Y64+Z64+AA64 -> 684.75 | AC64: =O64*$C64 -> 309 | AD64: =P64*$C64 -> 0 | AE64: =Q64*$C64 -> 0 | AF64: =R64*$C64 -> 6.18 | AG64: =S64*$C64 -> 15.45 | AH64: =T64*$C64 -> 330.63 | AI64: =U64*$C64 -> 135 | AJ64: =V64*$C64 -> 0 | ... AO64: =AA64*$C64 -> 33.75 | AP64: =AM64+AK64 -> 102.7125 | AQ64: =AM64+AL64+AH64 -> 568.3425 | AR64: =AO64+AN64 -> 116.4075 | AS64: =AH64+AL64+AM64+AO64+AN64 -> 684.75
B65: Système de montage sur tuile | C65: =A60 -> 15 | D65: U | E65: =AB65 -> 257.66176 | F65: =C65*E65 -> 3864.9265 | H65: =$H$10 -> 100 | I65: =I10 -> 0 | J65: =H65*$J$4 -> 3 | K65: 0 | L65: =H65*(1-$K65) -> 100 | M65: =I65*(1-$K65) -> 0 | N65: =J65*(1-$K65) -> 3 | O65: =(L65+M65+N65) -> 103 | P65: =O65*$P$4 -> 0 | Q65: =(O65+P65)*$Q$4 -> 0 | R65: =(O65+P65)*$R$4 -> 2.06 | S65: =(O65+P65)*$S$4 -> 5.15 | T65: =SUM(O65:S65) -> 110.21 | U65: =1*$U$4 -> 65 | V65: =V54 -> 0 | W65: =W54 -> 0 | X65: =SUM(U65:W65) -> 65 | Y65: =$Y$4/(1-$Y$4)*(T65+X65+Z65+AA65) -> 38.649265 | Z65: =T65*$Z$4 -> 27.5525 | AA65: =X65*$AA$4 -> 16.25 | AB65: =T65+X65+Y65+Z65+AA65 -> 257.66176 | AC65: =O65*$C65 -> 1545 | AD65: =P65*$C65 -> 0 | AE65: =Q65*$C65 -> 0 | AF65: =R65*$C65 -> 30.9 | AG65: =S65*$C65 -> 77.25 | AH65: =T65*$C65 -> 1653.15 | AI65: =U65*$C65 -> 975 | AJ65: =V65*$C65 -> 0 | ... AO65: =AA65*$C65 -> 243.75 | AP65: =AM65+AK65 -> 579.73897 | AQ65: =AM65+AL65+AH65 -> 3207.889 | AR65: =AO65+AN65 -> 657.0375 | AS65: =AH65+AL65+AM65+AO65+AN65 -> 3864.9265
B66: Raccordement AC | C66: 1 | D66: Forfait | E66: =AB66 -> 3089.7794 | F66: =C66*E66 -> 3089.7794 | H66: =$H$11 -> 500 | I66: =I11 -> 0 | J66: =H66*$J$4 -> 15 | K66: 0 | L66: =H66*(1-$K66) -> 500 | M66: =I66*(1-$K66) -> 0 | N66: =J66*(1-$K66) -> 15 | O66: =(L66+M66+N66) -> 515 | P66: =O66*$P$4 -> 0 | Q66: =(O66+P66)*$Q$4 -> 0 | R66: =(O66+P66)*$R$4 -> 10.3 | S66: =(O66+P66)*$S$4 -> 25.75 | T66: =SUM(O66:S66) -> 551.05 | U66: =5*$U$5+600+500 -> 1550 | V66: =V55 -> 0 | W66: =W55 -> 0 | X66: =SUM(U66:W66) -> 1550 | Y66: =$Y$4/(1-$Y$4)*(T66+X66+Z66+AA66) -> 463.46691 | Z66: =T66*$Z$4 -> 137.7625 | AA66: =X66*$AA$4 -> 387.5 | AB66: =T66+X66+Y66+Z66+AA66 -> 3089.7794 | AC66: =O66*$C66 -> 515 | AD66: =P66*$C66 -> 0 | AE66: =Q66*$C66 -> 0 | AF66: =R66*$C66 -> 10.3 | AG66: =S66*$C66 -> 25.75 | AH66: =T66*$C66 -> 551.05 | AI66: =U66*$C66 -> 1550 | AJ66: =V66*$C66 -> 0 | ... AO66: =AA66*$C66 -> 387.5 | AP66: =AM66+AK66 -> 463.46691 | AQ66: =AM66+AL66+AH66 -> 2564.5169 | AR66: =AO66+AN66 -> 525.2625 | AS66: =AH66+AL66+AM66+AO66+AN66 -> 3089.7794
B67: Echafaudage jusqu'à 6m de hauteur | C67: 1 | D67: Forfait | E67: =AB67 -> 2308.5 | F67: =C67*E67 -> 2308.5 | H67: =$H$12 -> 1300 | I67: =I12 -> 200 | J67: =H67*$J$4 -> 39 | K67: 0 | L67: =H67*(1-$K67) -> 1300 | M67: =I67*(1-$K67) -> 200 | N67: =J67*(1-$K67) -> 39 | O67: =(L67+M67+N67) -> 1539 | P67: =O67*$P$4 -> 0 | Q67: =(O67+P67)*$Q$4 -> 0 | R67: =(O67+P67)*$R$4 -> 30.78 | S67: 0 | T67: =SUM(O67:S67) -> 1569.78 | U67: 0 | V67: =V56 -> 0 | W67: =W56 -> 0 | X67: =SUM(U67:W67) -> 0 | Y67: =$Y$4/(1-$Y$4)*(T67+X67+Z67+AA67) -> 346.275 | Z67: =T67*$Z$4 -> 392.445 | AA67: =X67*$AA$4 -> 0 | AB67: =T67+X67+Y67+Z67+AA67 -> 2308.5 | AC67: =O67*$C67 -> 1539 | AD67: =P67*$C67 -> 0 | AE67: =Q67*$C67 -> 0 | AF67: =R67*$C67 -> 30.78 | AG67: =S67*$C67 -> 0 | AH67: =T67*$C67 -> 1569.78 | AI67: =U67*$C67 -> 0 | AJ67: =V67*$C67 -> 0 | ... AO67: =AA67*$C67 -> 0 | AP67: =AM67+AK67 -> 346.275 | AQ67: =AM67+AL67+AH67 -> 1916.055 | AR67: =AO67+AN67 -> 392.445 | AS67: =AH67+AL67+AM67+AO67+AN67 -> 2308.5
B68: Travaux administratifs | C68: 1 | D68: Forfait | E68: =AB68 -> 900 | F68: =C68*E68 -> 900 | H68: 0 | I68: 0 | J68: =H68*$J$4 -> 0 | K68: 0 | L68: =H68*(1-$K68) -> 0 | M68: =I68*(1-$K68) -> 0 | N68: =J68*(1-$K68) -> 0 | O68: =(L68+M68+N68) -> 0 | P68: =O68*$P$4 -> 0 | Q68: =(O68+P68)*$Q$4 -> 0 | R68: =(O68+P68)*$R$4 -> 0 | S68: 0 | T68: =SUM(O68:S68) -> 0 | U68: 0 | V68: =V57 -> 0 | W68: =W57 -> 900 | X68: =SUM(U68:W68) -> 900 | Y68: 0 | Z68: =T68*$Z$4 -> 0 | AA68: 0 | AB68: =T68+X68+Y68+Z68+AA68 -> 900 | AC68: =O68*$C68 -> 0 | AD68: =P68*$C68 -> 0 | AE68: =Q68*$C68 -> 0 | AF68: =R68*$C68 -> 0 | AG68: =S68*$C68 -> 0 | AH68: =T68*$C68 -> 0 | AI68: =U68*$C68 -> 0 | AJ68: =V68*$C68 -> 0 | ... AO68: =AA68*$C68 -> 0 | AP68: =AM68+AK68 -> 900 | AQ68: =AM68+AL68+AH68 -> 900 | AR68: =AO68+AN68 -> 0 | AS68: =AH68+AL68+AM68+AO68+AN68 -> 900
B69: Travaux électriques, contrôle et Pronovo | C69: 1 | D69: Forfait | E69: =AB69 -> 1200 | F69: =C69*E69 -> 1200 | H69: 0 | I69: 0 | J69: =H69*$J$4 -> 0 | K69: 0 | L69: =H69*(1-$K69) -> 0 | M69: =I69*(1-$K69) -> 0 | N69: =J69*(1-$K69) -> 0 | O69: =(L69+M69+N69) -> 0 | P69: =O69*$P$4 -> 0 | Q69: =(O69+P69)*$Q$4 -> 0 | R69: =(O69+P69)*$R$4 -> 0 | S69: 0 | T69: =SUM(O69:S69) -> 0 | U69: 0 | V69: =V58 -> 1200 | W69: =W58 -> 0 | X69: =SUM(U69:W69) -> 1200 | Y69: 0 | Z69: =T69*$Z$4 -> 0 | AA69: 0 | AB69: =T69+X69+Y69+Z69+AA69 -> 1200 | AC69: =O69*$C69 -> 0 | AD69: =P69*$C69 -> 0 | AE69: =Q69*$C69 -> 0 | AF69: =R69*$C69 -> 0 | AG69: =S69*$C69 -> 0 | AH69: =T69*$C69 -> 0 | AI69: =U69*$C69 -> 0 | AJ69: =V69*$C69 -> 1200 | ... AO69: =AA69*$C69 -> 0 | AP69: =AM69+AK69 -> 0 | AQ69: =AM69+AL69+AH69 -> 1200 | AR69: =AO69+AN69 -> 0 | AS69: =AH69+AL69+AM69+AO69+AN69 -> 1200
A71: =A60+1 -> 16 | B71: Panneaux | C71: Puissance: | D71: =ROUNDUP((A71*465)/1000,2) -> 7.44 | F71: =SUM(F72:F81) -> 19718.794 | AC71: =+SUM(AC72:AC81) -> 7573.5795 | AD71: =+SUM(AD72:AD81) -> 0 | AE71: =+SUM(AE72:AE81) -> 0 | AF71: =+SUM(AF72:AF81) -> 151.47159 | AG71: =+SUM(AG72:AG81) -> 301.72897 | AH71: =+SUM(AH72:AH81) -> 8026.7801 | AI71: =+SUM(AI72:AI81) -> 3954 | AJ71: =+SUM(AJ72:AJ81) -> 1200 | ... AS71: =+SUM(AS72:AS81) -> 19718.794 | AT71: =IF(F71=AS71,"Matching","Not Matching") -> Matching | AU71: =SUM(AC71:AG71) -> 8026.7801 | AV71: =AU71/AS71 -> 0.40706242 | AW71: =AI71 -> 3954 | AX71: =AW71/AS71 -> 0.20051936 | AY71: =AJ71 -> 1200 | AZ71: =AY71/AS71 -> 0.060855648 | BA71: =AK71+AM71 -> 3542.8191 | BB71: =BA71/AS71 -> 0.17966713 | BC71: =AN71+AO71 -> 2995.195 | BD71: =BC71/AS71 -> 0.15189544 | BE71: =IF((AU71+AW71+AY71+BA71+BC71)=AS71,"Matching","Not Matching") -> Matching | BF71: =AQ71 -> 16723.599 | BG71: =BF71/AS71 -> 0.84810456 | BH71: =AR71 -> 2995.195 | BI71: =BH71/AS71 -> 0.15189544 | BJ71: =IF((BH71+BF71)=AS71,"Matching","Not Matching") -> Matching | BK71: =AS71*1.081 -> 21316.017 | BL71: =ROUND(BK71,-1) -> 21320 | BM71: =D71*380 -> 2827.2 | BN71: =BK71-BM71 -> 18488.817 | BO71: =BK71/D71 -> 2865.056
I72: Parafoudres
B73: ="Panneau solaire "&G73 -> Panneau solaire LONGi Hi-MO X10 Artist LR7-54HVB-485M | C73: =A71 -> 16 | D73: U | E73: =AB73 -> 266.65685 | F73: =C73*E73 -> 4266.5095 | G73: =$G$7 -> LONGi Hi-MO X10 Artist LR7-54HVB-485M | H73: =$H$7 -> 105.55 | I73: =$I$7 -> 0 | J73: =H73*$J$4 -> 3.1665 | K73: 0 | L73: =H73*(1-$K73) -> 105.55 | M73: =I73*(1-$K73) -> 0 | N73: =J73*(1-$K73) -> 3.1665 | O73: =(L73+M73+N73) -> 108.7165 | P73: =O73*$P$4 -> 0 | Q73: =(O73+P73)*$Q$4 -> 0 | R73: =(O73+P73)*$R$4 -> 2.17433 | S73: =(O73+P73)*$S$4 -> 5.435825 | T73: =SUM(O73:S73) -> 116.32665 | U73: =1*$U$4 -> 65 | V73: =V62 -> 0 | W73: =W62 -> 0 | X73: =SUM(U73:W73) -> 65 | Y73: =$Y$4/(1-$Y$4)*(T73+X73+Z73+AA73) -> 39.998527 | Z73: =T73*$Z$4 -> 29.081664 | AA73: =X73*$AA$4 -> 16.25 | AB73: =T73+X73+Y73+Z73+AA73 -> 266.65685 | AC73: =O73*$C73 -> 1739.464 | AD73: =P73*$C73 -> 0 | AE73: =Q73*$C73 -> 0 | AF73: =R73*$C73 -> 34.78928 | AG73: =S73*$C73 -> 86.9732 | AH73: =T73*$C73 -> 1861.2265 | AI73: =U73*$C73 -> 1040 | AJ73: =V73*$C73 -> 0 | ... AO73: =AA73*$C73 -> 260 | AP73: =AM73+AK73 -> 639.97643 | AQ73: =AM73+AL73+AH73 -> 3541.2029 | AR73: =AO73+AN73 -> 725.30662 | AS73: =AH73+AL73+AM73+AO73+AN73 -> 4266.5095
B74: ="Onduleur Fronius "&G74 -> Onduleur Fronius Symo GEN24 6.0 SC | C74: 1 | D74: U | E74: =AB74 -> 3133.4317 | F74: =C74*E74 -> 3133.4317 | G74: =$G$8 -> Symo GEN24 6.0 SC | H74: =$H$8 -> 1333.85 | I74: =$I$8 -> 449.25 | J74: =H74*$J$4 -> 40.0155 | K74: 0 | L74: =H74*(1-$K74) -> 1333.85 | M74: =I74*(1-$K74) -> 449.25 | N74: =J74*(1-$K74) -> 40.0155 | O74: =(L74+M74+N74) -> 1823.1155 | P74: =O74*$P$4 -> 0 | Q74: =(O74+P74)*$Q$4 -> 0 | R74: =(O74+P74)*$R$4 -> 36.46231 | S74: =(O74+P74)*$S$4 -> 91.155775 | T74: =SUM(O74:S74) -> 1950.7336 | U74: =2*$U$5 -> 180 | V74: =V63 -> 0 | W74: =W63 -> 0 | X74: =SUM(U74:W74) -> 180 | Y74: =$Y$4/(1-$Y$4)*(T74+X74+Z74+AA74) -> 470.01476 | Z74: =T74*$Z$4 -> 487.6834 | AA74: =X74*$AA$4 -> 45 | AB74: =T74+X74+Y74+Z74+AA74 -> 3133.4317 | AC74: =O74*$C74 -> 1823.1155 | AD74: =P74*$C74 -> 0 | AE74: =Q74*$C74 -> 0 | AF74: =R74*$C74 -> 36.46231 | AG74: =S74*$C74 -> 91.155775 | AH74: =T74*$C74 -> 1950.7336 | AI74: =U74*$C74 -> 180 | AJ74: =V74*$C74 -> 0 | ... AO74: =AA74*$C74 -> 45 | AP74: =AM74+AK74 -> 470.01476 | AQ74: =AM74+AL74+AH74 -> 2600.7483 | AR74: =AO74+AN74 -> 532.6834 | AS74: =AH74+AL74+AM74+AO74+AN74 -> 3133.4317
B75: Accessoires | C75: 1 | D75: Forfait | E75: =AB75 -> 697.98529 | F75: =C75*E75 -> 697.98529 | H75: =$H$9 -> 300 | I75: =I9 -> 0 | J75: =H75*$J$4 -> 9 | K75: 0 | L75: =H75*(1-$K75) -> 300 | M75: =I75*(1-$K75) -> 0 | N75: =J75*(1-$K75) -> 9 | O75: =(L75+M75+N75) -> 309 | P75: =O75*$P$4 -> 0 | Q75: =(O75+P75)*$Q$4 -> 0 | R75: =(O75+P75)*$R$4 -> 6.18 | S75: =(O75+P75)*$S$4 -> 15.45 | T75: =SUM(O75:S75) -> 330.63 | U75: =(C73/10)*$U$5 -> 144 | V75: =V64 -> 0 | W75: =W64 -> 0 | X75: =SUM(U75:W75) -> 144 | Y75: =$Y$4/(1-$Y$4)*(T75+X75+Z75+AA75) -> 104.69779 | Z75: =T75*$Z$4 -> 82.6575 | AA75: =X75*$AA$4 -> 36 | AB75: =T75+X75+Y75+Z75+AA75 -> 697.98529 | AC75: =O75*$C75 -> 309 | AD75: =P75*$C75 -> 0 | AE75: =Q75*$C75 -> 0 | AF75: =R75*$C75 -> 6.18 | AG75: =S75*$C75 -> 15.45 | AH75: =T75*$C75 -> 330.63 | AI75: =U75*$C75 -> 144 | AJ75: =V75*$C75 -> 0 | ... AO75: =AA75*$C75 -> 36 | AP75: =AM75+AK75 -> 104.69779 | AQ75: =AM75+AL75+AH75 -> 579.32779 | AR75: =AO75+AN75 -> 118.6575 | AS75: =AH75+AL75+AM75+AO75+AN75 -> 697.98529
B76: Système de montage sur tuile | C76: =A71 -> 16 | D76: U | E76: =AB76 -> 257.66176 | F76: =C76*E76 -> 4122.5882 | H76: =$H$10 -> 100 | I76: =I10 -> 0 | J76: =H76*$J$4 -> 3 | K76: 0 | L76: =H76*(1-$K76) -> 100 | M76: =I76*(1-$K76) -> 0 | N76: =J76*(1-$K76) -> 3 | O76: =(L76+M76+N76) -> 103 | P76: =O76*$P$4 -> 0 | Q76: =(O76+P76)*$Q$4 -> 0 | R76: =(O76+P76)*$R$4 -> 2.06 | S76: =(O76+P76)*$S$4 -> 5.15 | T76: =SUM(O76:S76) -> 110.21 | U76: =1*$U$4 -> 65 | V76: =V65 -> 0 | W76: =W65 -> 0 | X76: =SUM(U76:W76) -> 65 | Y76: =$Y$4/(1-$Y$4)*(T76+X76+Z76+AA76) -> 38.649265 | Z76: =T76*$Z$4 -> 27.5525 | AA76: =X76*$AA$4 -> 16.25 | AB76: =T76+X76+Y76+Z76+AA76 -> 257.66176 | AC76: =O76*$C76 -> 1648 | AD76: =P76*$C76 -> 0 | AE76: =Q76*$C76 -> 0 | AF76: =R76*$C76 -> 32.96 | AG76: =S76*$C76 -> 82.4 | AH76: =T76*$C76 -> 1763.36 | AI76: =U76*$C76 -> 1040 | AJ76: =V76*$C76 -> 0 | ... AO76: =AA76*$C76 -> 260 | AP76: =AM76+AK76 -> 618.38824 | AQ76: =AM76+AL76+AH76 -> 3421.7482 | AR76: =AO76+AN76 -> 700.84 | AS76: =AH76+AL76+AM76+AO76+AN76 -> 4122.5882
B77: Raccordement AC | C77: 1 | D77: Forfait | E77: =AB77 -> 3089.7794 | F77: =C77*E77 -> 3089.7794 | H77: =$H$11 -> 500 | I77: =I11 -> 0 | J77: =H77*$J$4 -> 15 | K77: 0 | L77: =H77*(1-$K77) -> 500 | M77: =I77*(1-$K77) -> 0 | N77: =J77*(1-$K77) -> 15 | O77: =(L77+M77+N77) -> 515 | P77: =O77*$P$4 -> 0 | Q77: =(O77+P77)*$Q$4 -> 0 | R77: =(O77+P77)*$R$4 -> 10.3 | S77: =(O77+P77)*$S$4 -> 25.75 | T77: =SUM(O77:S77) -> 551.05 | U77: =5*$U$5+600+500 -> 1550 | V77: =V66 -> 0 | W77: =W66 -> 0 | X77: =SUM(U77:W77) -> 1550 | Y77: =$Y$4/(1-$Y$4)*(T77+X77+Z77+AA77) -> 463.46691 | Z77: =T77*$Z$4 -> 137.7625 | AA77: =X77*$AA$4 -> 387.5 | AB77: =T77+X77+Y77+Z77+AA77 -> 3089.7794 | AC77: =O77*$C77 -> 515 | AD77: =P77*$C77 -> 0 | AE77: =Q77*$C77 -> 0 | AF77: =R77*$C77 -> 10.3 | AG77: =S77*$C77 -> 25.75 | AH77: =T77*$C77 -> 551.05 | AI77: =U77*$C77 -> 1550 | AJ77: =V77*$C77 -> 0 | ... AO77: =AA77*$C77 -> 387.5 | AP77: =AM77+AK77 -> 463.46691 | AQ77: =AM77+AL77+AH77 -> 2564.5169 | AR77: =AO77+AN77 -> 525.2625 | AS77: =AH77+AL77+AM77+AO77+AN77 -> 3089.7794
B78: Echafaudage jusqu'à 6m de hauteur | C78: 1 | D78: Forfait | E78: =AB78 -> 2308.5 | F78: =C78*E78 -> 2308.5 | H78: =$H$12 -> 1300 | I78: =I12 -> 200 | J78: =H78*$J$4 -> 39 | K78: 0 | L78: =H78*(1-$K78) -> 1300 | M78: =I78*(1-$K78) -> 200 | N78: =J78*(1-$K78) -> 39 | O78: =(L78+M78+N78) -> 1539 | P78: =O78*$P$4 -> 0 | Q78: =(O78+P78)*$Q$4 -> 0 | R78: =(O78+P78)*$R$4 -> 30.78 | S78: 0 | T78: =SUM(O78:S78) -> 1569.78 | U78: 0 | V78: =V67 -> 0 | W78: =W67 -> 0 | X78: =SUM(U78:W78) -> 0 | Y78: =$Y$4/(1-$Y$4)*(T78+X78+Z78+AA78) -> 346.275 | Z78: =T78*$Z$4 -> 392.445 | AA78: =X78*$AA$4 -> 0 | AB78: =T78+X78+Y78+Z78+AA78 -> 2308.5 | AC78: =O78*$C78 -> 1539 | AD78: =P78*$C78 -> 0 | AE78: =Q78*$C78 -> 0 | AF78: =R78*$C78 -> 30.78 | AG78: =S78*$C78 -> 0 | AH78: =T78*$C78 -> 1569.78 | AI78: =U78*$C78 -> 0 | AJ78: =V78*$C78 -> 0 | ... AO78: =AA78*$C78 -> 0 | AP78: =AM78+AK78 -> 346.275 | AQ78: =AM78+AL78+AH78 -> 1916.055 | AR78: =AO78+AN78 -> 392.445 | AS78: =AH78+AL78+AM78+AO78+AN78 -> 2308.5
B79: Travaux administratifs | C79: 1 | D79: Forfait | E79: =AB79 -> 900 | F79: =C79*E79 -> 900 | H79: 0 | I79: 0 | J79: =H79*$J$4 -> 0 | K79: 0 | L79: =H79*(1-$K79) -> 0 | M79: =I79*(1-$K79) -> 0 | N79: =J79*(1-$K79) -> 0 | O79: =(L79+M79+N79) -> 0 | P79: =O79*$P$4 -> 0 | Q79: =(O79+P79)*$Q$4 -> 0 | R79: =(O79+P79)*$R$4 -> 0 | S79: 0 | T79: =SUM(O79:S79) -> 0 | U79: 0 | V79: =V68 -> 0 | W79: =W68 -> 900 | X79: =SUM(U79:W79) -> 900 | Y79: 0 | Z79: =T79*$Z$4 -> 0 | AA79: 0 | AB79: =T79+X79+Y79+Z79+AA79 -> 900 | AC79: =O79*$C79 -> 0 | AD79: =P79*$C79 -> 0 | AE79: =Q79*$C79 -> 0 | AF79: =R79*$C79 -> 0 | AG79: =S79*$C79 -> 0 | AH79: =T79*$C79 -> 0 | AI79: =U79*$C79 -> 0 | AJ79: =V79*$C79 -> 0 | ... AO79: =AA79*$C79 -> 0 | AP79: =AM79+AK79 -> 900 | AQ79: =AM79+AL79+AH79 -> 900 | AR79: =AO79+AN79 -> 0 | AS79: =AH79+AL79+AM79+AO79+AN79 -> 900
B80: Travaux électriques, contrôle et Pronovo | C80: 1 | D80: Forfait | E80: =AB80 -> 1200 | F80: =C80*E80 -> 1200 | H80: 0 | I80: 0 | J80: =H80*$J$4 -> 0 | K80: 0 | L80: =H80*(1-$K80) -> 0 | M80: =I80*(1-$K80) -> 0 | N80: =J80*(1-$K80) -> 0 | O80: =(L80+M80+N80) -> 0 | P80: =O80*$P$4 -> 0 | Q80: =(O80+P80)*$Q$4 -> 0 | R80: =(O80+P80)*$R$4 -> 0 | S80: 0 | T80: =SUM(O80:S80) -> 0 | U80: 0 | V80: =V69 -> 1200 | W80: =W69 -> 0 | X80: =SUM(U80:W80) -> 1200 | Y80: 0 | Z80: =T80*$Z$4 -> 0 | AA80: 0 | AB80: =T80+X80+Y80+Z80+AA80 -> 1200 | AC80: =O80*$C80 -> 0 | AD80: =P80*$C80 -> 0 | AE80: =Q80*$C80 -> 0 | AF80: =R80*$C80 -> 0 | AG80: =S80*$C80 -> 0 | AH80: =T80*$C80 -> 0 | AI80: =U80*$C80 -> 0 | AJ80: =V80*$C80 -> 1200 | ... AO80: =AA80*$C80 -> 0 | AP80: =AM80+AK80 -> 0 | AQ80: =AM80+AL80+AH80 -> 1200 | AR80: =AO80+AN80 -> 0 | AS80: =AH80+AL80+AM80+AO80+AN80 -> 1200
A82: =A71+1 -> 17 | B82: Panneaux | C82: Puissance: | D82: =ROUNDUP((A82*465)/1000,2) -> 7.91 | F82: =SUM(F83:F92) -> 20708.29 | AC82: =+SUM(AC83:AC92) -> 8072.5115 | AD82: =+SUM(AD83:AD92) -> 0 | AE82: =+SUM(AE83:AE92) -> 0 | AF82: =+SUM(AF83:AF92) -> 161.45023 | AG82: =+SUM(AG83:AG92) -> 326.67557 | AH82: =+SUM(AH83:AH92) -> 8560.6373 | AI82: =+SUM(AI83:AI92) -> 4093 | AJ82: =+SUM(AJ83:AJ92) -> 1200 | ... AS82: =+SUM(AS83:AS92) -> 20708.29 | AT82: =IF(F82=AS82,"Matching","Not Matching") -> Matching | AU82: =SUM(AC82:AG82) -> 8560.6373 | AV82: =AU82/AS82 -> 0.4133918 | AW82: =AI82 -> 4093 | AX82: =AW82/AS82 -> 0.19765031 | AY82: =AJ82 -> 1200 | AZ82: =AY82/AS82 -> 0.057947807 | BA82: =AK82+AM82 -> 3691.2435 | BB82: =BA82/AS82 -> 0.17824956 | BC82: =AN82+AO82 -> 3163.4093 | BD82: =BC82/AS82 -> 0.15276053 | BE82: =IF((AU82+AW82+AY82+BA82+BC82)=AS82,"Matching","Not Matching") -> Matching | BF82: =AQ82 -> 17544.881 | BG82: =BF82/AS82 -> 0.84723947 | BH82: =AR82 -> 3163.4093 | BI82: =BH82/AS82 -> 0.15276053 | BJ82: =IF((BH82+BF82)=AS82,"Matching","Not Matching") -> Matching | BK82: =AS82*1.081 -> 22385.662 | BL82: =ROUND(BK82,-1) -> 22390 | BM82: =D82*380 -> 3005.8 | BN82: =BK82-BM82 -> 19379.862 | BO82: =BK82/D82 -> 2830.0457
I83: Parafoudres
B84: ="Panneau solaire "&G84 -> Panneau solaire LONGi Hi-MO X10 Artist LR7-54HVB-485M | C84: =A82 -> 17 | D84: U | E84: =AB84 -> 266.65685 | F84: =C84*E84 -> 4533.1664 | G84: =$G$7 -> LONGi Hi-MO X10 Artist LR7-54HVB-485M | H84: =H73 -> 105.55 | I84: =$I$7 -> 0 | J84: =H84*$J$4 -> 3.1665 | K84: 0 | L84: =H84*(1-$K84) -> 105.55 | M84: =I84*(1-$K84) -> 0 | N84: =J84*(1-$K84) -> 3.1665 | O84: =(L84+M84+N84) -> 108.7165 | P84: =O84*$P$4 -> 0 | Q84: =(O84+P84)*$Q$4 -> 0 | R84: =(O84+P84)*$R$4 -> 2.17433 | S84: =(O84+P84)*$S$4 -> 5.435825 | T84: =SUM(O84:S84) -> 116.32665 | U84: =1*$U$4 -> 65 | V84: =V73 -> 0 | W84: =W73 -> 0 | X84: =SUM(U84:W84) -> 65 | Y84: =$Y$4/(1-$Y$4)*(T84+X84+Z84+AA84) -> 39.998527 | Z84: =T84*$Z$4 -> 29.081664 | AA84: =X84*$AA$4 -> 16.25 | AB84: =T84+X84+Y84+Z84+AA84 -> 266.65685 | AC84: =O84*$C84 -> 1848.1805 | AD84: =P84*$C84 -> 0 | AE84: =Q84*$C84 -> 0 | AF84: =R84*$C84 -> 36.96361 | AG84: =S84*$C84 -> 92.409025 | AH84: =T84*$C84 -> 1977.5531 | AI84: =U84*$C84 -> 1105 | AJ84: =V84*$C84 -> 0 | ... AO84: =AA84*$C84 -> 276.25 | AP84: =AM84+AK84 -> 679.97496 | AQ84: =AM84+AL84+AH84 -> 3762.5281 | AR84: =AO84+AN84 -> 770.63828 | AS84: =AH84+AL84+AM84+AO84+AN84 -> 4533.1664
B85: ="Onduleur Fronius "&G85 -> Onduleur Fronius Symo GEN24 8.0 SC | C85: 1 | D85: U | E85: =AB85 -> 3585.3738 | F85: =C85*E85 -> 3585.3738 | G85: ='Financial Data'!B43 -> Symo GEN24 8.0 SC | H85: ='Financial Data'!C43 -> 1612.7 | I85: =$I$8 -> 449.25 | J85: =H85*$J$4 -> 48.381 | K85: 0 | L85: =H85*(1-$K85) -> 1612.7 | M85: =I85*(1-$K85) -> 449.25 | N85: =J85*(1-$K85) -> 48.381 | O85: =(L85+M85+N85) -> 2110.331 | P85: =O85*$P$4 -> 0 | Q85: =(O85+P85)*$Q$4 -> 0 | R85: =(O85+P85)*$R$4 -> 42.20662 | S85: =(O85+P85)*$S$4 -> 105.51655 | T85: =SUM(O85:S85) -> 2258.0542 | U85: =2*$U$5 -> 180 | V85: =V74 -> 0 | W85: =W74 -> 0 | X85: =SUM(U85:W85) -> 180 | Y85: =$Y$4/(1-$Y$4)*(T85+X85+Z85+AA85) -> 537.80607 | Z85: =T85*$Z$4 -> 564.51354 | AA85: =X85*$AA$4 -> 45 | AB85: =T85+X85+Y85+Z85+AA85 -> 3585.3738 | AC85: =O85*$C85 -> 2110.331 | AD85: =P85*$C85 -> 0 | AE85: =Q85*$C85 -> 0 | AF85: =R85*$C85 -> 42.20662 | AG85: =S85*$C85 -> 105.51655 | AH85: =T85*$C85 -> 2258.0542 | AI85: =U85*$C85 -> 180 | AJ85: =V85*$C85 -> 0 | ... AO85: =AA85*$C85 -> 45 | AP85: =AM85+AK85 -> 537.80607 | AQ85: =AM85+AL85+AH85 -> 2975.8602 | AR85: =AO85+AN85 -> 609.51354 | AS85: =AH85+AL85+AM85+AO85+AN85 -> 3585.3738
B86: Accessoires | C86: 1 | D86: Forfait | E86: =AB86 -> 711.22059 | F86: =C86*E86 -> 711.22059 | H86: =H9 -> 300 | I86: =I75 -> 0 | J86: =H86*$J$4 -> 9 | K86: 0 | L86: =H86*(1-$K86) -> 300 | M86: =I86*(1-$K86) -> 0 | N86: =J86*(1-$K86) -> 9 | O86: =(L86+M86+N86) -> 309 | P86: =O86*$P$4 -> 0 | Q86: =(O86+P86)*$Q$4 -> 0 | R86: =(O86+P86)*$R$4 -> 6.18 | S86: =(O86+P86)*$S$4 -> 15.45 | T86: =SUM(O86:S86) -> 330.63 | U86: =(C84/10)*$U$5 -> 153 | V86: =V75 -> 0 | W86: =W75 -> 0 | X86: =SUM(U86:W86) -> 153 | Y86: =$Y$4/(1-$Y$4)*(T86+X86+Z86+AA86) -> 106.68309 | Z86: =T86*$Z$4 -> 82.6575 | AA86: =X86*$AA$4 -> 38.25 | AB86: =T86+X86+Y86+Z86+AA86 -> 711.22059 | AC86: =O86*$C86 -> 309 | AD86: =P86*$C86 -> 0 | AE86: =Q86*$C86 -> 0 | AF86: =R86*$C86 -> 6.18 | AG86: =S86*$C86 -> 15.45 | AH86: =T86*$C86 -> 330.63 | AI86: =U86*$C86 -> 153 | AJ86: =V86*$C86 -> 0 | ... AO86: =AA86*$C86 -> 38.25 | AP86: =AM86+AK86 -> 106.68309 | AQ86: =AM86+AL86+AH86 -> 590.31309 | AR86: =AO86+AN86 -> 120.9075 | AS86: =AH86+AL86+AM86+AO86+AN86 -> 711.22059
B87: Système de montage sur tuile | C87: =A82 -> 17 | D87: U | E87: =AB87 -> 257.66176 | F87: =C87*E87 -> 4380.25 | H87: =H10 -> 100 | I87: =I76 -> 0 | J87: =H87*$J$4 -> 3 | K87: 0 | L87: =H87*(1-$K87) -> 100 | M87: =I87*(1-$K87) -> 0 | N87: =J87*(1-$K87) -> 3 | O87: =(L87+M87+N87) -> 103 | P87: =O87*$P$4 -> 0 | Q87: =(O87+P87)*$Q$4 -> 0 | R87: =(O87+P87)*$R$4 -> 2.06 | S87: =(O87+P87)*$S$4 -> 5.15 | T87: =SUM(O87:S87) -> 110.21 | U87: =1*$U$4 -> 65 | V87: =V76 -> 0 | W87: =W76 -> 0 | X87: =SUM(U87:W87) -> 65 | Y87: =$Y$4/(1-$Y$4)*(T87+X87+Z87+AA87) -> 38.649265 | Z87: =T87*$Z$4 -> 27.5525 | AA87: =X87*$AA$4 -> 16.25 | AB87: =T87+X87+Y87+Z87+AA87 -> 257.66176 | AC87: =O87*$C87 -> 1751 | AD87: =P87*$C87 -> 0 | AE87: =Q87*$C87 -> 0 | AF87: =R87*$C87 -> 35.02 | AG87: =S87*$C87 -> 87.55 | AH87: =T87*$C87 -> 1873.57 | AI87: =U87*$C87 -> 1105 | AJ87: =V87*$C87 -> 0 | ... AO87: =AA87*$C87 -> 276.25 | AP87: =AM87+AK87 -> 657.0375 | AQ87: =AM87+AL87+AH87 -> 3635.6075 | AR87: =AO87+AN87 -> 744.6425 | AS87: =AH87+AL87+AM87+AO87+AN87 -> 4380.25
B88: Raccordement AC | C88: 1 | D88: Forfait | E88: =AB88 -> 3089.7794 | F88: =C88*E88 -> 3089.7794 | H88: =H11 -> 500 | I88: =I77 -> 0 | J88: =H88*$J$4 -> 15 | K88: 0 | L88: =H88*(1-$K88) -> 500 | M88: =I88*(1-$K88) -> 0 | N88: =J88*(1-$K88) -> 15 | O88: =(L88+M88+N88) -> 515 | P88: =O88*$P$4 -> 0 | Q88: =(O88+P88)*$Q$4 -> 0 | R88: =(O88+P88)*$R$4 -> 10.3 | S88: =(O88+P88)*$S$4 -> 25.75 | T88: =SUM(O88:S88) -> 551.05 | U88: =5*$U$5+600+500 -> 1550 | V88: =V77 -> 0 | W88: =W77 -> 0 | X88: =SUM(U88:W88) -> 1550 | Y88: =$Y$4/(1-$Y$4)*(T88+X88+Z88+AA88) -> 463.46691 | Z88: =T88*$Z$4 -> 137.7625 | AA88: =X88*$AA$4 -> 387.5 | AB88: =T88+X88+Y88+Z88+AA88 -> 3089.7794 | AC88: =O88*$C88 -> 515 | AD88: =P88*$C88 -> 0 | AE88: =Q88*$C88 -> 0 | AF88: =R88*$C88 -> 10.3 | AG88: =S88*$C88 -> 25.75 | AH88: =T88*$C88 -> 551.05 | AI88: =U88*$C88 -> 1550 | AJ88: =V88*$C88 -> 0 | ... AO88: =AA88*$C88 -> 387.5 | AP88: =AM88+AK88 -> 463.46691 | AQ88: =AM88+AL88+AH88 -> 2564.5169 | AR88: =AO88+AN88 -> 525.2625 | AS88: =AH88+AL88+AM88+AO88+AN88 -> 3089.7794
B89: Echafaudage jusqu'à 6m de hauteur | C89: 1 | D89: Forfait | E89: =AB89 -> 2308.5 | F89: =C89*E89 -> 2308.5 | H89: =$H$12 -> 1300 | I89: =I23 -> 200 | J89: =H89*$J$4 -> 39 | K89: 0 | L89: =H89*(1-$K89) -> 1300 | M89: =I89*(1-$K89) -> 200 | N89: =J89*(1-$K89) -> 39 | O89: =(L89+M89+N89) -> 1539 | P89: =O89*$P$4 -> 0 | Q89: =(O89+P89)*$Q$4 -> 0 | R89: =(O89+P89)*$R$4 -> 30.78 | S89: 0 | T89: =SUM(O89:S89) -> 1569.78 | U89: 0 | V89: =V78 -> 0 | W89: =W78 -> 0 | X89: =SUM(U89:W89) -> 0 | Y89: =$Y$4/(1-$Y$4)*(T89+X89+Z89+AA89) -> 346.275 | Z89: =T89*$Z$4 -> 392.445 | AA89: =X89*$AA$4 -> 0 | AB89: =T89+X89+Y89+Z89+AA89 -> 2308.5 | AC89: =O89*$C89 -> 1539 | AD89: =P89*$C89 -> 0 | AE89: =Q89*$C89 -> 0 | AF89: =R89*$C89 -> 30.78 | AG89: =S89*$C89 -> 0 | AH89: =T89*$C89 -> 1569.78 | AI89: =U89*$C89 -> 0 | AJ89: =V89*$C89 -> 0 | ... AO89: =AA89*$C89 -> 0 | AP89: =AM89+AK89 -> 346.275 | AQ89: =AM89+AL89+AH89 -> 1916.055 | AR89: =AO89+AN89 -> 392.445 | AS89: =AH89+AL89+AM89+AO89+AN89 -> 2308.5
B90: Travaux administratifs | C90: 1 | D90: Forfait | E90: =AB90 -> 900 | F90: =C90*E90 -> 900 | H90: 0 | I90: 0 | J90: =H90*$J$4 -> 0 | K90: 0 | L90: =H90*(1-$K90) -> 0 | M90: =I90*(1-$K90) -> 0 | N90: =J90*(1-$K90) -> 0 | O90: =(L90+M90+N90) -> 0 | P90: =O90*$P$4 -> 0 | Q90: =(O90+P90)*$Q$4 -> 0 | R90: =(O90+P90)*$R$4 -> 0 | S90: 0 | T90: =SUM(O90:S90) -> 0 | U90: 0 | V90: =V79 -> 0 | W90: =W79 -> 900 | X90: =SUM(U90:W90) -> 900 | Y90: 0 | Z90: =T90*$Z$4 -> 0 | AA90: 0 | AB90: =T90+X90+Y90+Z90+AA90 -> 900 | AC90: =O90*$C90 -> 0 | AD90: =P90*$C90 -> 0 | AE90: =Q90*$C90 -> 0 | AF90: =R90*$C90 -> 0 | AG90: =S90*$C90 -> 0 | AH90: =T90*$C90 -> 0 | AI90: =U90*$C90 -> 0 | AJ90: =V90*$C90 -> 0 | ... AO90: =AA90*$C90 -> 0 | AP90: =AM90+AK90 -> 900 | AQ90: =AM90+AL90+AH90 -> 900 | AR90: =AO90+AN90 -> 0 | AS90: =AH90+AL90+AM90+AO90+AN90 -> 900
B91: Travaux électriques, contrôle et Pronovo | C91: 1 | D91: Forfait | E91: =AB91 -> 1200 | F91: =C91*E91 -> 1200 | H91: 0 | I91: 0 | J91: =H91*$J$4 -> 0 | K91: 0 | L91: =H91*(1-$K91) -> 0 | M91: =I91*(1-$K91) -> 0 | N91: =J91*(1-$K91) -> 0 | O91: =(L91+M91+N91) -> 0 | P91: =O91*$P$4 -> 0 | Q91: =(O91+P91)*$Q$4 -> 0 | R91: =(O91+P91)*$R$4 -> 0 | S91: 0 | T91: =SUM(O91:S91) -> 0 | U91: 0 | V91: =V80 -> 1200 | W91: =W80 -> 0 | X91: =SUM(U91:W91) -> 1200 | Y91: 0 | Z91: =T91*$Z$4 -> 0 | AA91: 0 | AB91: =T91+X91+Y91+Z91+AA91 -> 1200 | AC91: =O91*$C91 -> 0 | AD91: =P91*$C91 -> 0 | AE91: =Q91*$C91 -> 0 | AF91: =R91*$C91 -> 0 | AG91: =S91*$C91 -> 0 | AH91: =T91*$C91 -> 0 | AI91: =U91*$C91 -> 0 | AJ91: =V91*$C91 -> 1200 | ... AO91: =AA91*$C91 -> 0 | AP91: =AM91+AK91 -> 0 | AQ91: =AM91+AL91+AH91 -> 1200 | AR91: =AO91+AN91 -> 0 | AS91: =AH91+AL91+AM91+AO91+AN91 -> 1200
A93: =A82+1 -> 18 | B93: Panneaux | C93: Puissance: | D93: =ROUNDUP((A93*465)/1000,2) -> 8.37 | F93: =SUM(F94:F103) -> 21245.844 | AC93: =+SUM(AC94:AC103) -> 8284.228 | AD93: =+SUM(AD94:AD103) -> 0 | AE93: =+SUM(AE94:AE103) -> 0 | AF93: =+SUM(AF94:AF103) -> 165.68456 | AG93: =+SUM(AG94:AG103) -> 337.2614 | AH93: =+SUM(AH94:AH103) -> 8787.174 | AI93: =+SUM(AI94:AI103) -> 4232 | AJ93: =+SUM(AJ94:AJ103) -> 1200 | ... AS93: =+SUM(AS94:AS103) -> 21245.844 | AT93: =IF(F93=AS93,"Matching","Not Matching") -> Matching | AU93: =SUM(AC93:AG93) -> 8787.174 | AV93: =AU93/AS93 -> 0.41359496 | AW93: =AI93 -> 4232 | AX93: =AW93/AS93 -> 0.1991919 | AY93: =AJ93 -> 1200 | AZ93: =AY93/AS93 -> 0.056481635 | BA93: =AK93+AM93 -> 3771.8766 | BB93: =BA93/AS93 -> 0.1775348 | BC93: =AN93+AO93 -> 3254.7935 | BD93: =BC93/AS93 -> 0.15319671 | BE93: =IF((AU93+AW93+AY93+BA93+BC93)=AS93,"Matching","Not Matching") -> Matching | BF93: =AQ93 -> 17991.051 | BG93: =BF93/AS93 -> 0.84680329 | BH93: =AR93 -> 3254.7935 | BI93: =BH93/AS93 -> 0.15319671 | BJ93: =IF((BH93+BF93)=AS93,"Matching","Not Matching") -> Matching | BK93: =AS93*1.081 -> 22966.757 | BL93: =ROUND(BK93,-1) -> 22970 | BM93: =D93*380 -> 3180.6 | BN93: =BK93-BM93 -> 19786.157 | BO93: =BK93/D93 -> 2743.9376
I94: Parafoudres
B95: ="Panneau solaire "&G95 -> Panneau solaire LONGi Hi-MO X10 Artist LR7-54HVB-485M | C95: =A93 -> 18 | D95: U | E95: =AB95 -> 266.65685 | F95: =C95*E95 -> 4799.8232 | G95: =$G$7 -> LONGi Hi-MO X10 Artist LR7-54HVB-485M | H95: =H73 -> 105.55 | I95: =$I$7 -> 0 | J95: =H95*$J$4 -> 3.1665 | K95: 0 | L95: =H95*(1-$K95) -> 105.55 | M95: =I95*(1-$K95) -> 0 | N95: =J95*(1-$K95) -> 3.1665 | O95: =(L95+M95+N95) -> 108.7165 | P95: =O95*$P$4 -> 0 | Q95: =(O95+P95)*$Q$4 -> 0 | R95: =(O95+P95)*$R$4 -> 2.17433 | S95: =(O95+P95)*$S$4 -> 5.435825 | T95: =SUM(O95:S95) -> 116.32665 | U95: =1*$U$4 -> 65 | V95: =V84 -> 0 | W95: =W84 -> 0 | X95: =SUM(U95:W95) -> 65 | Y95: =$Y$4/(1-$Y$4)*(T95+X95+Z95+AA95) -> 39.998527 | Z95: =T95*$Z$4 -> 29.081664 | AA95: =X95*$AA$4 -> 16.25 | AB95: =T95+X95+Y95+Z95+AA95 -> 266.65685 | AC95: =O95*$C95 -> 1956.897 | AD95: =P95*$C95 -> 0 | AE95: =Q95*$C95 -> 0 | AF95: =R95*$C95 -> 39.13794 | AG95: =S95*$C95 -> 97.84485 | AH95: =T95*$C95 -> 2093.8798 | AI95: =U95*$C95 -> 1170 | AJ95: =V95*$C95 -> 0 | ... AO95: =AA95*$C95 -> 292.5 | AP95: =AM95+AK95 -> 719.97348 | AQ95: =AM95+AL95+AH95 -> 3983.8533 | AR95: =AO95+AN95 -> 815.96995 | AS95: =AH95+AL95+AM95+AO95+AN95 -> 4799.8232
B96: ="Onduleur Fronius "&G96 -> Onduleur Fronius Symo GEN24 8.0 SC | C96: 1 | D96: U | E96: =AB96 -> 3585.3738 | F96: =C96*E96 -> 3585.3738 | G96: =$G$85 -> Symo GEN24 8.0 SC | H96: =H85 -> 1612.7 | I96: =I85 -> 449.25 | J96: =H96*$J$4 -> 48.381 | K96: 0 | L96: =H96*(1-$K96) -> 1612.7 | M96: =I96*(1-$K96) -> 449.25 | N96: =J96*(1-$K96) -> 48.381 | O96: =(L96+M96+N96) -> 2110.331 | P96: =O96*$P$4 -> 0 | Q96: =(O96+P96)*$Q$4 -> 0 | R96: =(O96+P96)*$R$4 -> 42.20662 | S96: =(O96+P96)*$S$4 -> 105.51655 | T96: =SUM(O96:S96) -> 2258.0542 | U96: =2*$U$5 -> 180 | V96: =V85 -> 0 | W96: =W85 -> 0 | X96: =SUM(U96:W96) -> 180 | Y96: =$Y$4/(1-$Y$4)*(T96+X96+Z96+AA96) -> 537.80607 | Z96: =T96*$Z$4 -> 564.51354 | AA96: =X96*$AA$4 -> 45 | AB96: =T96+X96+Y96+Z96+AA96 -> 3585.3738 | AC96: =O96*$C96 -> 2110.331 | AD96: =P96*$C96 -> 0 | AE96: =Q96*$C96 -> 0 | AF96: =R96*$C96 -> 42.20662 | AG96: =S96*$C96 -> 105.51655 | AH96: =T96*$C96 -> 2258.0542 | AI96: =U96*$C96 -> 180 | AJ96: =V96*$C96 -> 0 | ... AO96: =AA96*$C96 -> 45 | AP96: =AM96+AK96 -> 537.80607 | AQ96: =AM96+AL96+AH96 -> 2975.8602 | AR96: =AO96+AN96 -> 609.51354 | AS96: =AH96+AL96+AM96+AO96+AN96 -> 3585.3738
B97: Accessoires | C97: 1 | D97: Forfait | E97: =AB97 -> 724.45588 | F97: =C97*E97 -> 724.45588 | H97: =H86 -> 300 | I97: =I86 -> 0 | J97: =H97*$J$4 -> 9 | K97: 0 | L97: =H97*(1-$K97) -> 300 | M97: =I97*(1-$K97) -> 0 | N97: =J97*(1-$K97) -> 9 | O97: =(L97+M97+N97) -> 309 | P97: =O97*$P$4 -> 0 | Q97: =(O97+P97)*$Q$4 -> 0 | R97: =(O97+P97)*$R$4 -> 6.18 | S97: =(O97+P97)*$S$4 -> 15.45 | T97: =SUM(O97:S97) -> 330.63 | U97: =(C95/10)*$U$5 -> 162 | V97: =V86 -> 0 | W97: =W86 -> 0 | X97: =SUM(U97:W97) -> 162 | Y97: =$Y$4/(1-$Y$4)*(T97+X97+Z97+AA97) -> 108.66838 | Z97: =T97*$Z$4 -> 82.6575 | AA97: =X97*$AA$4 -> 40.5 | AB97: =T97+X97+Y97+Z97+AA97 -> 724.45588 | AC97: =O97*$C97 -> 309 | AD97: =P97*$C97 -> 0 | AE97: =Q97*$C97 -> 0 | AF97: =R97*$C97 -> 6.18 | AG97: =S97*$C97 -> 15.45 | AH97: =T97*$C97 -> 330.63 | AI97: =U97*$C97 -> 162 | AJ97: =V97*$C97 -> 0 | ... AO97: =AA97*$C97 -> 40.5 | AP97: =AM97+AK97 -> 108.66838 | AQ97: =AM97+AL97+AH97 -> 601.29838 | AR97: =AO97+AN97 -> 123.1575 | AS97: =AH97+AL97+AM97+AO97+AN97 -> 724.45588
B98: Système de montage sur tuile | C98: =A93 -> 18 | D98: U | E98: =AB98 -> 257.66176 | F98: =C98*E98 -> 4637.9118 | H98: =H87 -> 100 | I98: =I87 -> 0 | J98: =H98*$J$4 -> 3 | K98: 0 | L98: =H98*(1-$K98) -> 100 | M98: =I98*(1-$K98) -> 0 | N98: =J98*(1-$K98) -> 3 | O98: =(L98+M98+N98) -> 103 | P98: =O98*$P$4 -> 0 | Q98: =(O98+P98)*$Q$4 -> 0 | R98: =(O98+P98)*$R$4 -> 2.06 | S98: =(O98+P98)*$S$4 -> 5.15 | T98: =SUM(O98:S98) -> 110.21 | U98: =1*$U$4 -> 65 | V98: =V87 -> 0 | W98: =W87 -> 0 | X98: =SUM(U98:W98) -> 65 | Y98: =$Y$4/(1-$Y$4)*(T98+X98+Z98+AA98) -> 38.649265 | Z98: =T98*$Z$4 -> 27.5525 | AA98: =X98*$AA$4 -> 16.25 | AB98: =T98+X98+Y98+Z98+AA98 -> 257.66176 | AC98: =O98*$C98 -> 1854 | AD98: =P98*$C98 -> 0 | AE98: =Q98*$C98 -> 0 | AF98: =R98*$C98 -> 37.08 | AG98: =S98*$C98 -> 92.7 | AH98: =T98*$C98 -> 1983.78 | AI98: =U98*$C98 -> 1170 | AJ98: =V98*$C98 -> 0 | ... AO98: =AA98*$C98 -> 292.5 | AP98: =AM98+AK98 -> 695.68676 | AQ98: =AM98+AL98+AH98 -> 3849.4668 | AR98: =AO98+AN98 -> 788.445 | AS98: =AH98+AL98+AM98+AO98+AN98 -> 4637.9118
B99: Raccordement AC | C99: 1 | D99: Forfait | E99: =AB99 -> 3089.7794 | F99: =C99*E99 -> 3089.7794 | H99: =H88 -> 500 | I99: =I88 -> 0 | J99: =H99*$J$4 -> 15 | K99: 0 | L99: =H99*(1-$K99) -> 500 | M99: =I99*(1-$K99) -> 0 | N99: =J99*(1-$K99) -> 15 | O99: =(L99+M99+N99) -> 515 | P99: =O99*$P$4 -> 0 | Q99: =(O99+P99)*$Q$4 -> 0 | R99: =(O99+P99)*$R$4 -> 10.3 | S99: =(O99+P99)*$S$4 -> 25.75 | T99: =SUM(O99:S99) -> 551.05 | U99: =5*$U$5+600+500 -> 1550 | V99: =V88 -> 0 | W99: =W88 -> 0 | X99: =SUM(U99:W99) -> 1550 | Y99: =$Y$4/(1-$Y$4)*(T99+X99+Z99+AA99) -> 463.46691 | Z99: =T99*$Z$4 -> 137.7625 | AA99: =X99*$AA$4 -> 387.5 | AB99: =T99+X99+Y99+Z99+AA99 -> 3089.7794 | AC99: =O99*$C99 -> 515 | AD99: =P99*$C99 -> 0 | AE99: =Q99*$C99 -> 0 | AF99: =R99*$C99 -> 10.3 | AG99: =S99*$C99 -> 25.75 | AH99: =T99*$C99 -> 551.05 | AI99: =U99*$C99 -> 1550 | AJ99: =V99*$C99 -> 0 | ... AO99: =AA99*$C99 -> 387.5 | AP99: =AM99+AK99 -> 463.46691 | AQ99: =AM99+AL99+AH99 -> 2564.5169 | AR99: =AO99+AN99 -> 525.2625 | AS99: =AH99+AL99+AM99+AO99+AN99 -> 3089.7794
